Workbook

Sheet assumptions
A1: VELTORA INC. · SALES COMPENSATION MODEL · FY 2025
A2: Confidential — RevOps Team | Austin, TX | Series B
A4: COMPANY OVERVIEW
A5: Company Name | B5: Veltora Inc.
A6: Product | B6: Revenue Operations SaaS Platform
A7: HQ | B7: Austin, TX
A8: Stage | B8: Series B — Growth
A9: Funding Round Closed | B9: January 2025
A10: Fiscal Year | B10: 2025
A12: 2025 ARR TARGETS
A13: ARR — Entering 2025 ($) | B13: 31000000
A14: ARR — Year-End Target ($) | B14: 46000000
A15: Implied YoY Growth (%) | B15: =(B14-B13)/B13 -> 0.48387097
A16: New ARR Target ($) | B16: 15000000
A18: 2025 HEADCOUNT PLAN
A19: Segment | B19: Manager | C19: SDRs (Orig.) | D19: AEs (Orig.) | E19: CSMs (Orig.) | F19: SDR Repl. | G19: AE Repl. | H19: CSM Repl. | I19: Peak HC | J19: Notes
A20: Enterprise | B20: Sarah Chen | C20: 1 | D20: 2 | E20: 1 | F20: 0 | G20: 0 | H20: 1 | I20: 5 | J20: Ent CSM replaced Q4
A21: Mid-Market | B21: Tyler Rodriguez | C21: 2 | D21: 2 | E21: 2 | F21: 1 | G21: 0 | H21: 0 | I21: 7 | J21: MM SDR replaced Q3
A22: SMB | B22: Carlos Mendez | C22: 2 | D22: 2 | E22: 1 | F22: 0 | G22: 1 | H22: 0 | I22: 6 | J22: SMB AE replaced Q3
A23: TOTAL | B23: 3 Managers | C23: 5 | D23: 6 | E23: 4 | F23: 1 | G23: 1 | H23: 1 | I23: 21
A25: 2025 PERFORMANCE CONTEXT & KEY ASSUMPTIONS
A26: Performance Trend | B26: Strong H1 (Q1 blowout at ~118% org attainment), weak H2 as market softens post-raise
A27: Q1 Blowout | B27: January push drives outsized deals; several reps trigger accelerators in Q1
A28: Acquisition Motion | B28: Inbound-led Enterprise (avg ACV $80K-$150K); Outbound-driven SMB (avg ACV $8K-$20K)
A29: Rep Churn | B29: 1 SMB AE (June) · 1 MM SDR (August) · 1 Ent CSM (September) — natural mid-year attrition
A30: Replacements | B30: All 3 replaced on staggered schedule; ramp = 40% / 70% / 100% over first 3 months
A31: August Seasonality | B31: August shows -15% to -20% drop across all segments vs. June
A32: Accelerator Policy | B32: True-up calculated at quarter-end; monthly commissions paid at standard rate
A33: Base Salary Tiering | B33: Enterprise reps earn higher base; all roles tiered by segment (Ent > MM > SMB)
A34: CSM Metric | B34: Net Expansion ARR (NRR) — expansion revenue minus churn on existing book
A35: SDR Metric | B35: Qualified Held Meetings = meetings booked × show rate. Min show rate: Ent 75%, MM 70%, SMB 65%
A36: Manager Override | B36: 2% override on direct reports' total monthly commission; team attainment bonus at 100%
A37: Comp Model Purpose | B37: Q3 2025 review for CFO — assess payout efficiency ahead of 2026 planning cycle

Sheet plan_catalog
A1: VELTORA INC. · COMPENSATION PLAN CATALOG · FY 2025
A2: Source of truth for all comp rates, quotas, and accelerator thresholds
A4: Plan Key | B4: Role | C4: Segment | D4: Annual Base ($) | E4: Annual OTE ($) | F4: Annual Quota | G4: Commission Rate | H4: Rate Type | I4: Accel Tier 1 Threshold | J4: Accel Tier 1 Mult | K4: Accel Tier 2 Threshold | L4: Accel Tier 2 Mult | M4: Performance Metric | N4: Notes
A5: =B5&"_"&C5 -> SDR_Enterprise | B5: SDR | C5: Enterprise | D5: 62000 | E5: 85000 | F5: 96 | G5: 319 | H5: $/held mtg | I5: 1.1 | J5: 1.3 | K5: — | L5: — | M5: Held Meetings | N5: New hire quota: 40%/70%/100% ramp
A6: =B6&"_"&C6 -> SDR_Mid-Market | B6: SDR | C6: Mid-Market | D6: 55000 | E6: 75000 | F6: 120 | G6: 167 | H6: $/held mtg | I6: 1.1 | J6: 1.25 | K6: — | L6: — | M6: Held Meetings | N6: New hire quota: 40%/70%/100% ramp
A7: =B7&"_"&C7 -> SDR_SMB | B7: SDR | C7: SMB | D7: 48000 | E7: 65000 | F7: 192 | G7: 89 | H7: $/held mtg | I7: 1.1 | J7: 1.2 | K7: — | L7: — | M7: Held Meetings | N7: New hire quota: 40%/70%/100% ramp
A8: =B8&"_"&C8 -> AE_Enterprise | B8: AE | C8: Enterprise | D8: 95000 | E8: 185000 | F8: 900000 | G8: 0.1 | H8: % of ARR | I8: 1 | J8: 1.25 | K8: 1.2 | L8: 1.5 | M8: ARR Closed | N8: Accel applied to full quarter at quarter-end true-up
A9: =B9&"_"&C9 -> AE_Mid-Market | B9: AE | C9: Mid-Market | D9: 80000 | E9: 140000 | F9: 600000 | G9: 0.1 | H9: % of ARR | I9: 1 | J9: 1.25 | K9: 1.2 | L9: 1.5 | M9: ARR Closed | N9: Accel applied to full quarter at quarter-end true-up
A10: =B10&"_"&C10 -> AE_SMB | B10: AE | C10: SMB | D10: 65000 | E10: 95000 | F10: 300000 | G10: 0.1 | H10: % of ARR | I10: 1 | J10: 1.2 | K10: 1.2 | L10: 1.4 | M10: ARR Closed | N10: Accel applied to full quarter at quarter-end true-up
A11: =B11&"_"&C11 -> CSM_Enterprise | B11: CSM | C11: Enterprise | D11: 80000 | E11: 107000 | F11: 480000 | G11: 0.06 | H11: % of Exp | I11: 1.05 | J11: 1.2 | K11: — | L11: — | M11: Net Exp ARR | N11: Quota = net expansion target vs book of business
A12: =B12&"_"&C12 -> CSM_Mid-Market | B12: CSM | C12: Mid-Market | D12: 70000 | E12: 105000 | F12: 180000 | G12: 0.06 | H12: % of Exp | I12: 1.05 | J12: 1.2 | K12: — | L12: — | M12: Net Exp ARR | N12: Quota = net expansion target vs book of business
A13: =B13&"_"&C13 -> CSM_SMB | B13: CSM | C13: SMB | D13: 60000 | E13: 88000 | F13: 60000 | G13: 0.06 | H13: % of Exp | I13: 1.05 | J13: 1.15 | K13: — | L13: — | M13: Net Exp ARR | N13: Quota = net expansion target vs book of business
A14: =B14&"_"&C14 -> Manager_All | B14: Manager | C14: All | D14: 110000 | E14: 145000 | F14: — | G14: 0.02 | H14: % of team | I14: 1 | J14: — | K14: — | L14: — | M14: Team Override | N14: Override on direct reports' commissions; bonus at 100% team att
A16: QUARTERLY BONUS TIERS (by Plan Key)
A17: Plan Key | B17: < 80% Att. | C17: 80–99% Att. | D17: 100–119% Att. | E17: ≥ 120% Att. | F17: Per Quarter
A18: AE_Enterprise | B18: 0 | C18: 2000 | D18: 5000 | E18: 10000 | F18: Max bonus shown
A19: AE_Mid-Market | B19: 0 | C19: 1500 | D19: 4000 | E19: 8000 | F19: Max bonus shown
A20: AE_SMB | B20: 0 | C20: 1000 | D20: 3000 | E20: 5000 | F20: Max bonus shown
A21: SDR_Enterprise | B21: 0 | C21: 750 | D21: 1500 | E21: 3000 | F21: Max bonus shown
A22: SDR_Mid-Market | B22: 0 | C22: 600 | D22: 1200 | E22: 2500 | F22: Max bonus shown
A23: SDR_SMB | B23: 0 | C23: 500 | D23: 1000 | E23: 2000 | F23: Max bonus shown
A24: CSM_Enterprise | B24: 0 | C24: 1000 | D24: 2500 | E24: 5000 | F24: Max bonus shown
A25: CSM_Mid-Market | B25: 0 | C25: 750 | D25: 2000 | E25: 4000 | F25: Max bonus shown
A26: CSM_SMB | B26: 0 | C26: 500 | D26: 1500 | E26: 3000 | F26: Max bonus shown
A27: Manager_All | B27: 0 | C27: 1500 | D27: 3500 | E27: 7500 | F27: Max bonus shown

Sheet rep_roster
A1: VELTORA INC. · SALES REP ROSTER · FY 2025
A2: All active, churned, and replacement reps | 18 ICs + 3 Managers = 21 headcount
A4: Rep ID | B4: Full Name | C4: Role | D4: Segment | E4: Manager | F4: City | G4: ST | H4: Start Mo. | I4: End Mo. | J4: Status | K4: Hire Type | L4: Plan Key | M4: Annual Base ($) | N4: Annual OTE ($)
A5: R001 | B5: Sarah Chen | C5: Manager | D5: Enterprise | E5: — | F5: Austin | G5: TX | H5: 1 | I5: 12 | J5: Active | K5: Original | L5: =IF(C5="Manager","Manager_All",C5&"_"&D5) -> Manager_All | M5: =IFERROR(VLOOKUP(L5,plan_catalog!$A:$D,4,0),"") -> 110000 | N5: =IFERROR(VLOOKUP(L5,plan_catalog!$A:$E,5,0),"") -> 145000
A6: R002 | B6: Marcus Williams | C6: SDR | D6: Enterprise | E6: Sarah Chen | F6: New York | G6: NY | H6: 1 | I6: 12 | J6: Active | K6: Original | L6: =IF(C6="Manager","Manager_All",C6&"_"&D6) -> SDR_Enterprise | M6: =IFERROR(VLOOKUP(L6,plan_catalog!$A:$D,4,0),"") -> 62000 | N6: =IFERROR(VLOOKUP(L6,plan_catalog!$A:$E,5,0),"") -> 85000
A7: R003 | B7: James Harrington | C7: AE | D7: Enterprise | E7: Sarah Chen | F7: New York | G7: NY | H7: 1 | I7: 12 | J7: Active | K7: Original | L7: =IF(C7="Manager","Manager_All",C7&"_"&D7) -> AE_Enterprise | M7: =IFERROR(VLOOKUP(L7,plan_catalog!$A:$D,4,0),"") -> 95000 | N7: =IFERROR(VLOOKUP(L7,plan_catalog!$A:$E,5,0),"") -> 185000
A8: R004 | B8: Olivia Brooks | C8: AE | D8: Enterprise | E8: Sarah Chen | F8: San Francisco | G8: CA | H8: 1 | I8: 12 | J8: Active | K8: Original | L8: =IF(C8="Manager","Manager_All",C8&"_"&D8) -> AE_Enterprise | M8: =IFERROR(VLOOKUP(L8,plan_catalog!$A:$D,4,0),"") -> 95000 | N8: =IFERROR(VLOOKUP(L8,plan_catalog!$A:$E,5,0),"") -> 185000
A9: R005 | B9: David Kim | C9: CSM | D9: Enterprise | E9: Sarah Chen | F9: New York | G9: NY | H9: 1 | I9: 9 | J9: Churned | K9: Original | L9: =IF(C9="Manager","Manager_All",C9&"_"&D9) -> CSM_Enterprise | M9: =IFERROR(VLOOKUP(L9,plan_catalog!$A:$D,4,0),"") -> 80000 | N9: =IFERROR(VLOOKUP(L9,plan_catalog!$A:$E,5,0),"") -> 107000
A10: R006 | B10: Lisa Park | C10: CSM | D10: Enterprise | E10: Sarah Chen | F10: San Francisco | G10: CA | H10: 10 | I10: 12 | J10: Ramping | K10: Replacement | L10: =IF(C10="Manager","Manager_All",C10&"_"&D10) -> CSM_Enterprise | M10: =IFERROR(VLOOKUP(L10,plan_catalog!$A:$D,4,0),"") -> 80000 | N10: =IFERROR(VLOOKUP(L10,plan_catalog!$A:$E,5,0),"") -> 107000
A11: R007 | B11: Tyler Rodriguez | C11: Manager | D11: Mid-Market | E11: — | F11: Austin | G11: TX | H11: 1 | I11: 12 | J11: Active | K11: Original | L11: =IF(C11="Manager","Manager_All",C11&"_"&D11) -> Manager_All | M11: =IFERROR(VLOOKUP(L11,plan_catalog!$A:$D,4,0),"") -> 110000 | N11: =IFERROR(VLOOKUP(L11,plan_catalog!$A:$E,5,0),"") -> 145000
A12: R008 | B12: Kevin O'Brien | C12: SDR | D12: Mid-Market | E12: Tyler Rodriguez | F12: Austin | G12: TX | H12: 1 | I12: 8 | J12: Churned | K12: Original | L12: =IF(C12="Manager","Manager_All",C12&"_"&D12) -> SDR_Mid-Market | M12: =IFERROR(VLOOKUP(L12,plan_catalog!$A:$D,4,0),"") -> 55000 | N12: =IFERROR(VLOOKUP(L12,plan_catalog!$A:$E,5,0),"") -> 75000
A13: R009 | B13: Aisha Johnson | C13: SDR | D13: Mid-Market | E13: Tyler Rodriguez | F13: Chicago | G13: IL | H13: 1 | I13: 12 | J13: Active | K13: Original | L13: =IF(C13="Manager","Manager_All",C13&"_"&D13) -> SDR_Mid-Market | M13: =IFERROR(VLOOKUP(L13,plan_catalog!$A:$D,4,0),"") -> 55000 | N13: =IFERROR(VLOOKUP(L13,plan_catalog!$A:$E,5,0),"") -> 75000
A14: R010 | B14: Jessica Martinez | C14: SDR | D14: Mid-Market | E14: Tyler Rodriguez | F14: Houston | G14: TX | H14: 7 | I14: 12 | J14: Ramping | K14: Replacement | L14: =IF(C14="Manager","Manager_All",C14&"_"&D14) -> SDR_Mid-Market | M14: =IFERROR(VLOOKUP(L14,plan_catalog!$A:$D,4,0),"") -> 55000 | N14: =IFERROR(VLOOKUP(L14,plan_catalog!$A:$E,5,0),"") -> 75000
A15: R011 | B15: Ryan Thompson | C15: AE | D15: Mid-Market | E15: Tyler Rodriguez | F15: Austin | G15: TX | H15: 1 | I15: 12 | J15: Active | K15: Original | L15: =IF(C15="Manager","Manager_All",C15&"_"&D15) -> AE_Mid-Market | M15: =IFERROR(VLOOKUP(L15,plan_catalog!$A:$D,4,0),"") -> 80000 | N15: =IFERROR(VLOOKUP(L15,plan_catalog!$A:$E,5,0),"") -> 140000
A16: R012 | B16: Samantha Lee | C16: AE | D16: Mid-Market | E16: Tyler Rodriguez | F16: Chicago | G16: IL | H16: 1 | I16: 12 | J16: Active | K16: Original | L16: =IF(C16="Manager","Manager_All",C16&"_"&D16) -> AE_Mid-Market | M16: =IFERROR(VLOOKUP(L16,plan_catalog!$A:$D,4,0),"") -> 80000 | N16: =IFERROR(VLOOKUP(L16,plan_catalog!$A:$E,5,0),"") -> 140000
... A25: R021 | B25: Jennifer Walsh | C25: CSM | D25: SMB | E25: Carlos Mendez | F25: Austin | G25: TX | H25: 1 | I25: 12 | J25: Active | K25: Original | L25: =IF(C25="Manager","Manager_All",C25&"_"&D25) -> CSM_SMB | M25: =IFERROR(VLOOKUP(L25,plan_catalog!$A:$D,4,0),"") -> 60000 | N25: =IFERROR(VLOOKUP(L25,plan_catalog!$A:$E,5,0),"") -> 88000
A26: TOTALS | B26: 21 People (3 Managers + 18 ICs) | M26: =SUMPRODUCT((rep_roster!C5:C25<>"Manager")*IFERROR(rep_roster!M5:M25,0)) -> 0 | N26: =SUMPRODUCT((rep_roster!C5:C25<>"Manager")*IFERROR(rep_roster!N5:N25,0)) -> 0

Sheet monthly_actuals
A1: VELTORA INC. · MONTHLY ACTUALS · FY 2025
A2: AEs = ARR Closed ($) | CSMs = Net Expansion ARR ($) | SDRs = Held Meetings (#)
A4: Lookup Key | B4: Rep ID | C4: Rep Name | D4: Month # | E4: Month | F4: Segment | G4: Role | H4: Monthly Quota | I4: Actual Performance | J4: Attainment % | K4: vs Quota ($)
A5: =B5&TEXT(D5,"00") -> R00201 | B5: R002 | C5: =VLOOKUP(B5,rep_roster!$A:$B,2,0) -> Marcus Williams | D5: 1 | E5: =INDEX({"Jan","Feb","Mar","Apr","May","Jun","Jul","Aug","Sep","Oct","Nov","Dec"},D5) -> Jan | F5: =VLOOKUP(B5,rep_roster!$A:$D,4,0) -> Enterprise | G5: =VLOOKUP(B5,rep_roster!$A:$C,3,0) -> SDR | H5: 8 | I5: 9 | J5: =IF(H5>0,I5/H5,0) -> 1.125 | K5: =I5-H5 -> 1
A6: =B6&TEXT(D6,"00") -> R00202 | B6: R002 | C6: =VLOOKUP(B6,rep_roster!$A:$B,2,0) -> Marcus Williams | D6: 2 | E6: =INDEX({"Jan","Feb","Mar","Apr","May","Jun","Jul","Aug","Sep","Oct","Nov","Dec"},D6) -> Feb | F6: =VLOOKUP(B6,rep_roster!$A:$D,4,0) -> Enterprise | G6: =VLOOKUP(B6,rep_roster!$A:$C,3,0) -> SDR | H6: 8 | I6: 8 | J6: =IF(H6>0,I6/H6,0) -> 1 | K6: =I6-H6 -> 0
A7: =B7&TEXT(D7,"00") -> R00203 | B7: R002 | C7: =VLOOKUP(B7,rep_roster!$A:$B,2,0) -> Marcus Williams | D7: 3 | E7: =INDEX({"Jan","Feb","Mar","Apr","May","Jun","Jul","Aug","Sep","Oct","Nov","Dec"},D7) -> Mar | F7: =VLOOKUP(B7,rep_roster!$A:$D,4,0) -> Enterprise | G7: =VLOOKUP(B7,rep_roster!$A:$C,3,0) -> SDR | H7: 8 | I7: 9 | J7: =IF(H7>0,I7/H7,0) -> 1.125 | K7: =I7-H7 -> 1
A8: =B8&TEXT(D8,"00") -> R00204 | B8: R002 | C8: =VLOOKUP(B8,rep_roster!$A:$B,2,0) -> Marcus Williams | D8: 4 | E8: =INDEX({"Jan","Feb","Mar","Apr","May","Jun","Jul","Aug","Sep","Oct","Nov","Dec"},D8) -> Apr | F8: =VLOOKUP(B8,rep_roster!$A:$D,4,0) -> Enterprise | G8: =VLOOKUP(B8,rep_roster!$A:$C,3,0) -> SDR | H8: 8 | I8: 7 | J8: =IF(H8>0,I8/H8,0) -> 0.875 | K8: =I8-H8 -> -1
A9: =B9&TEXT(D9,"00") -> R00205 | B9: R002 | C9: =VLOOKUP(B9,rep_roster!$A:$B,2,0) -> Marcus Williams | D9: 5 | E9: =INDEX({"Jan","Feb","Mar","Apr","May","Jun","Jul","Aug","Sep","Oct","Nov","Dec"},D9) -> May | F9: =VLOOKUP(B9,rep_roster!$A:$D,4,0) -> Enterprise | G9: =VLOOKUP(B9,rep_roster!$A:$C,3,0) -> SDR | H9: 8 | I9: 8 | J9: =IF(H9>0,I9/H9,0) -> 1 | K9: =I9-H9 -> 0
A10: =B10&TEXT(D10,"00") -> R00206 | B10: R002 | C10: =VLOOKUP(B10,rep_roster!$A:$B,2,0) -> Marcus Williams | D10: 6 | E10: =INDEX({"Jan","Feb","Mar","Apr","May","Jun","Jul","Aug","Sep","Oct","Nov","Dec"},D10) -> Jun | F10: =VLOOKUP(B10,rep_roster!$A:$D,4,0) -> Enterprise | G10: =VLOOKUP(B10,rep_roster!$A:$C,3,0) -> SDR | H10: 8 | I10: 7 | J10: =IF(H10>0,I10/H10,0) -> 0.875 | K10: =I10-H10 -> -1
A11: =B11&TEXT(D11,"00") -> R00207 | B11: R002 | C11: =VLOOKUP(B11,rep_roster!$A:$B,2,0) -> Marcus Williams | D11: 7 | E11: =INDEX({"Jan","Feb","Mar","Apr","May","Jun","Jul","Aug","Sep","Oct","Nov","Dec"},D11) -> Jul | F11: =VLOOKUP(B11,rep_roster!$A:$D,4,0) -> Enterprise | G11: =VLOOKUP(B11,rep_roster!$A:$C,3,0) -> SDR | H11: 8 | I11: 5 | J11: =IF(H11>0,I11/H11,0) -> 0.625 | K11: =I11-H11 -> -3
A12: =B12&TEXT(D12,"00") -> R00208 | B12: R002 | C12: =VLOOKUP(B12,rep_roster!$A:$B,2,0) -> Marcus Williams | D12: 8 | E12: =INDEX({"Jan","Feb","Mar","Apr","May","Jun","Jul","Aug","Sep","Oct","Nov","Dec"},D12) -> Aug | F12: =VLOOKUP(B12,rep_roster!$A:$D,4,0) -> Enterprise | G12: =VLOOKUP(B12,rep_roster!$A:$C,3,0) -> SDR | H12: 8 | I12: 4 | J12: =IF(H12>0,I12/H12,0) -> 0.5 | K12: =I12-H12 -> -4
A13: =B13&TEXT(D13,"00") -> R00209 | B13: R002 | C13: =VLOOKUP(B13,rep_roster!$A:$B,2,0) -> Marcus Williams | D13: 9 | E13: =INDEX({"Jan","Feb","Mar","Apr","May","Jun","Jul","Aug","Sep","Oct","Nov","Dec"},D13) -> Sep | F13: =VLOOKUP(B13,rep_roster!$A:$D,4,0) -> Enterprise | G13: =VLOOKUP(B13,rep_roster!$A:$C,3,0) -> SDR | H13: 8 | I13: 6 | J13: =IF(H13>0,I13/H13,0) -> 0.75 | K13: =I13-H13 -> -2
A14: =B14&TEXT(D14,"00") -> R00210 | B14: R002 | C14: =VLOOKUP(B14,rep_roster!$A:$B,2,0) -> Marcus Williams | D14: 10 | E14: =INDEX({"Jan","Feb","Mar","Apr","May","Jun","Jul","Aug","Sep","Oct","Nov","Dec"},D14) -> Oct | F14: =VLOOKUP(B14,rep_roster!$A:$D,4,0) -> Enterprise | G14: =VLOOKUP(B14,rep_roster!$A:$C,3,0) -> SDR | H14: 8 | I14: 5 | J14: =IF(H14>0,I14/H14,0) -> 0.625 | K14: =I14-H14 -> -3
A15: =B15&TEXT(D15,"00") -> R00211 | B15: R002 | C15: =VLOOKUP(B15,rep_roster!$A:$B,2,0) -> Marcus Williams | D15: 11 | E15: =INDEX({"Jan","Feb","Mar","Apr","May","Jun","Jul","Aug","Sep","Oct","Nov","Dec"},D15) -> Nov | F15: =VLOOKUP(B15,rep_roster!$A:$D,4,0) -> Enterprise | G15: =VLOOKUP(B15,rep_roster!$A:$C,3,0) -> SDR | H15: 8 | I15: 6 | J15: =IF(H15>0,I15/H15,0) -> 0.75 | K15: =I15-H15 -> -2
A16: =B16&TEXT(D16,"00") -> R00212 | B16: R002 | C16: =VLOOKUP(B16,rep_roster!$A:$B,2,0) -> Marcus Williams | D16: 12 | E16: =INDEX({"Jan","Feb","Mar","Apr","May","Jun","Jul","Aug","Sep","Oct","Nov","Dec"},D16) -> Dec | F16: =VLOOKUP(B16,rep_roster!$A:$D,4,0) -> Enterprise | G16: =VLOOKUP(B16,rep_roster!$A:$C,3,0) -> SDR | H16: 8 | I16: 7 | J16: =IF(H16>0,I16/H16,0) -> 0.875 | K16: =I16-H16 -> -1
... A186: =B186&TEXT(D186,"00") -> R02112 | B186: R021 | C186: =VLOOKUP(B186,rep_roster!$A:$B,2,0) -> Jennifer Walsh | D186: 12 | E186: =INDEX({"Jan","Feb","Mar","Apr","May","Jun","Jul","Aug","Sep","Oct","Nov","Dec"},D186) -> Dec | F186: =VLOOKUP(B186,rep_roster!$A:$D,4,0) -> SMB | G186: =VLOOKUP(B186,rep_roster!$A:$C,3,0) -> CSM | H186: 5000 | I186: 5000 | J186: =IF(H186>0,I186/H186,0) -> 1 | K186: =I186-H186 -> 0

Sheet sdr_meeting_tracker
A1: VELTORA INC. · SDR MEETING TRACKER · FY 2025
A2: Booked vs. Held meetings, Show Rate quality flags, and per-rep payout | Min show rate: Ent 75% · MM 70% · SMB 65%
A4: Lookup Key | B4: Rep ID | C4: Rep Name | D4: Segment | E4: Month # | F4: Month | G4: Mtgs Booked | H4: Mtgs Held | I4: Show Rate % | J4: Booked Quota | K4: Held Quota | L4: Held Attainment % | M4: Show Rate Status
A5: =B5&TEXT(E5,"00") -> R00201 | B5: R002 | C5: =VLOOKUP(B5,rep_roster!$A:$B,2,0) -> Marcus Williams | D5: =VLOOKUP(B5,rep_roster!$A:$D,4,0) -> Enterprise | E5: 1 | F5: =INDEX({"Jan","Feb","Mar","Apr","May","Jun","Jul","Aug","Sep","Oct","Nov","Dec"},E5) -> Jan | G5: 11 | H5: 9 | I5: =IF(G5>0,H5/G5,0) -> 0.81818182 | J5: 8 | K5: 6 | L5: =IF(K5>0,H5/K5,0) -> 1.5 | M5: =IF(H5=0,"Inactive",IF(I5>=0.75+0.05,"Strong",IF(I5>=0.75,"Met Min","Below Min"))) -> Strong
A6: =B6&TEXT(E6,"00") -> R00202 | B6: R002 | C6: =VLOOKUP(B6,rep_roster!$A:$B,2,0) -> Marcus Williams | D6: =VLOOKUP(B6,rep_roster!$A:$D,4,0) -> Enterprise | E6: 2 | F6: =INDEX({"Jan","Feb","Mar","Apr","May","Jun","Jul","Aug","Sep","Oct","Nov","Dec"},E6) -> Feb | G6: 10 | H6: 8 | I6: =IF(G6>0,H6/G6,0) -> 0.8 | J6: 8 | K6: 6 | L6: =IF(K6>0,H6/K6,0) -> 1.3333333 | M6: =IF(H6=0,"Inactive",IF(I6>=0.75+0.05,"Strong",IF(I6>=0.75,"Met Min","Below Min"))) -> Strong
A7: =B7&TEXT(E7,"00") -> R00203 | B7: R002 | C7: =VLOOKUP(B7,rep_roster!$A:$B,2,0) -> Marcus Williams | D7: =VLOOKUP(B7,rep_roster!$A:$D,4,0) -> Enterprise | E7: 3 | F7: =INDEX({"Jan","Feb","Mar","Apr","May","Jun","Jul","Aug","Sep","Oct","Nov","Dec"},E7) -> Mar | G7: 12 | H7: 9 | I7: =IF(G7>0,H7/G7,0) -> 0.75 | J7: 8 | K7: 6 | L7: =IF(K7>0,H7/K7,0) -> 1.5 | M7: =IF(H7=0,"Inactive",IF(I7>=0.75+0.05,"Strong",IF(I7>=0.75,"Met Min","Below Min"))) -> Met Min
A8: =B8&TEXT(E8,"00") -> R00204 | B8: R002 | C8: =VLOOKUP(B8,rep_roster!$A:$B,2,0) -> Marcus Williams | D8: =VLOOKUP(B8,rep_roster!$A:$D,4,0) -> Enterprise | E8: 4 | F8: =INDEX({"Jan","Feb","Mar","Apr","May","Jun","Jul","Aug","Sep","Oct","Nov","Dec"},E8) -> Apr | G8: 9 | H8: 7 | I8: =IF(G8>0,H8/G8,0) -> 0.77777778 | J8: 8 | K8: 6 | L8: =IF(K8>0,H8/K8,0) -> 1.1666667 | M8: =IF(H8=0,"Inactive",IF(I8>=0.75+0.05,"Strong",IF(I8>=0.75,"Met Min","Below Min"))) -> Met Min
A9: =B9&TEXT(E9,"00") -> R00205 | B9: R002 | C9: =VLOOKUP(B9,rep_roster!$A:$B,2,0) -> Marcus Williams | D9: =VLOOKUP(B9,rep_roster!$A:$D,4,0) -> Enterprise | E9: 5 | F9: =INDEX({"Jan","Feb","Mar","Apr","May","Jun","Jul","Aug","Sep","Oct","Nov","Dec"},E9) -> May | G9: 10 | H9: 8 | I9: =IF(G9>0,H9/G9,0) -> 0.8 | J9: 8 | K9: 6 | L9: =IF(K9>0,H9/K9,0) -> 1.3333333 | M9: =IF(H9=0,"Inactive",IF(I9>=0.75+0.05,"Strong",IF(I9>=0.75,"Met Min","Below Min"))) -> Strong
A10: =B10&TEXT(E10,"00") -> R00206 | B10: R002 | C10: =VLOOKUP(B10,rep_roster!$A:$B,2,0) -> Marcus Williams | D10: =VLOOKUP(B10,rep_roster!$A:$D,4,0) -> Enterprise | E10: 6 | F10: =INDEX({"Jan","Feb","Mar","Apr","May","Jun","Jul","Aug","Sep","Oct","Nov","Dec"},E10) -> Jun | G10: 9 | H10: 7 | I10: =IF(G10>0,H10/G10,0) -> 0.77777778 | J10: 8 | K10: 6 | L10: =IF(K10>0,H10/K10,0) -> 1.1666667 | M10: =IF(H10=0,"Inactive",IF(I10>=0.75+0.05,"Strong",IF(I10>=0.75,"Met Min","Below Min"))) -> Met Min
A11: =B11&TEXT(E11,"00") -> R00207 | B11: R002 | C11: =VLOOKUP(B11,rep_roster!$A:$B,2,0) -> Marcus Williams | D11: =VLOOKUP(B11,rep_roster!$A:$D,4,0) -> Enterprise | E11: 7 | F11: =INDEX({"Jan","Feb","Mar","Apr","May","Jun","Jul","Aug","Sep","Oct","Nov","Dec"},E11) -> Jul | G11: 7 | H11: 5 | I11: =IF(G11>0,H11/G11,0) -> 0.71428571 | J11: 8 | K11: 6 | L11: =IF(K11>0,H11/K11,0) -> 0.83333333 | M11: =IF(H11=0,"Inactive",IF(I11>=0.75+0.05,"Strong",IF(I11>=0.75,"Met Min","Below Min"))) -> Below Min
A12: =B12&TEXT(E12,"00") -> R00208 | B12: R002 | C12: =VLOOKUP(B12,rep_roster!$A:$B,2,0) -> Marcus Williams | D12: =VLOOKUP(B12,rep_roster!$A:$D,4,0) -> Enterprise | E12: 8 | F12: =INDEX({"Jan","Feb","Mar","Apr","May","Jun","Jul","Aug","Sep","Oct","Nov","Dec"},E12) -> Aug | G12: 6 | H12: 4 | I12: =IF(G12>0,H12/G12,0) -> 0.66666667 | J12: 8 | K12: 6 | L12: =IF(K12>0,H12/K12,0) -> 0.66666667 | M12: =IF(H12=0,"Inactive",IF(I12>=0.75+0.05,"Strong",IF(I12>=0.75,"Met Min","Below Min"))) -> Below Min
A13: =B13&TEXT(E13,"00") -> R00209 | B13: R002 | C13: =VLOOKUP(B13,rep_roster!$A:$B,2,0) -> Marcus Williams | D13: =VLOOKUP(B13,rep_roster!$A:$D,4,0) -> Enterprise | E13: 9 | F13: =INDEX({"Jan","Feb","Mar","Apr","May","Jun","Jul","Aug","Sep","Oct","Nov","Dec"},E13) -> Sep | G13: 8 | H13: 6 | I13: =IF(G13>0,H13/G13,0) -> 0.75 | J13: 8 | K13: 6 | L13: =IF(K13>0,H13/K13,0) -> 1 | M13: =IF(H13=0,"Inactive",IF(I13>=0.75+0.05,"Strong",IF(I13>=0.75,"Met Min","Below Min"))) -> Met Min
A14: =B14&TEXT(E14,"00") -> R00210 | B14: R002 | C14: =VLOOKUP(B14,rep_roster!$A:$B,2,0) -> Marcus Williams | D14: =VLOOKUP(B14,rep_roster!$A:$D,4,0) -> Enterprise | E14: 10 | F14: =INDEX({"Jan","Feb","Mar","Apr","May","Jun","Jul","Aug","Sep","Oct","Nov","Dec"},E14) -> Oct | G14: 7 | H14: 5 | I14: =IF(G14>0,H14/G14,0) -> 0.71428571 | J14: 8 | K14: 6 | L14: =IF(K14>0,H14/K14,0) -> 0.83333333 | M14: =IF(H14=0,"Inactive",IF(I14>=0.75+0.05,"Strong",IF(I14>=0.75,"Met Min","Below Min"))) -> Below Min
A15: =B15&TEXT(E15,"00") -> R00211 | B15: R002 | C15: =VLOOKUP(B15,rep_roster!$A:$B,2,0) -> Marcus Williams | D15: =VLOOKUP(B15,rep_roster!$A:$D,4,0) -> Enterprise | E15: 11 | F15: =INDEX({"Jan","Feb","Mar","Apr","May","Jun","Jul","Aug","Sep","Oct","Nov","Dec"},E15) -> Nov | G15: 8 | H15: 6 | I15: =IF(G15>0,H15/G15,0) -> 0.75 | J15: 8 | K15: 6 | L15: =IF(K15>0,H15/K15,0) -> 1 | M15: =IF(H15=0,"Inactive",IF(I15>=0.75+0.05,"Strong",IF(I15>=0.75,"Met Min","Below Min"))) -> Met Min
A16: =B16&TEXT(E16,"00") -> R00212 | B16: R002 | C16: =VLOOKUP(B16,rep_roster!$A:$B,2,0) -> Marcus Williams | D16: =VLOOKUP(B16,rep_roster!$A:$D,4,0) -> Enterprise | E16: 12 | F16: =INDEX({"Jan","Feb","Mar","Apr","May","Jun","Jul","Aug","Sep","Oct","Nov","Dec"},E16) -> Dec | G16: 9 | H16: 7 | I16: =IF(G16>0,H16/G16,0) -> 0.77777778 | J16: 8 | K16: 6 | L16: =IF(K16>0,H16/K16,0) -> 1.1666667 | M16: =IF(H16=0,"Inactive",IF(I16>=0.75+0.05,"Strong",IF(I16>=0.75,"Met Min","Below Min"))) -> Met Min
A17: =B17&TEXT(E17,"00") -> R00801 | B17: R008 | C17: =VLOOKUP(B17,rep_roster!$A:$B,2,0) -> Kevin O'Brien | D17: =VLOOKUP(B17,rep_roster!$A:$D,4,0) -> Mid-Market | E17: 1 | F17: =INDEX({"Jan","Feb","Mar","Apr","May","Jun","Jul","Aug","Sep","Oct","Nov","Dec"},E17) -> Jan | G17: 17 | H17: 12 | I17: =IF(G17>0,H17/G17,0) -> 0.70588235 | J17: 15 | K17: 10 | L17: =IF(K17>0,H17/K17,0) -> 1.2 | M17: =IF(H17=0,"Inactive",IF(I17>=0.7+0.05,"Strong",IF(I17>=0.7,"Met Min","Below Min"))) -> Met Min
A18: =B18&TEXT(E18,"00") -> R00802 | B18: R008 | C18: =VLOOKUP(B18,rep_roster!$A:$B,2,0) -> Kevin O'Brien | D18: =VLOOKUP(B18,rep_roster!$A:$D,4,0) -> Mid-Market | E18: 2 | F18: =INDEX({"Jan","Feb","Mar","Apr","May","Jun","Jul","Aug","Sep","Oct","Nov","Dec"},E18) -> Feb | G18: 16 | H18: 11 | I18: =IF(G18>0,H18/G18,0) -> 0.6875 | J18: 15 | K18: 10 | L18: =IF(K18>0,H18/K18,0) -> 1.1 | M18: =IF(H18=0,"Inactive",IF(I18>=0.7+0.05,"Strong",IF(I18>=0.7,"Met Min","Below Min"))) -> Below Min
A19: =B19&TEXT(E19,"00") -> R00803 | B19: R008 | C19: =VLOOKUP(B19,rep_roster!$A:$B,2,0) -> Kevin O'Brien | D19: =VLOOKUP(B19,rep_roster!$A:$D,4,0) -> Mid-Market | E19: 3 | F19: =INDEX({"Jan","Feb","Mar","Apr","May","Jun","Jul","Aug","Sep","Oct","Nov","Dec"},E19) -> Mar | G19: 18 | H19: 13 | I19: =IF(G19>0,H19/G19,0) -> 0.72222222 | J19: 15 | K19: 10 | L19: =IF(K19>0,H19/K19,0) -> 1.3 | M19: =IF(H19=0,"Inactive",IF(I19>=0.7+0.05,"Strong",IF(I19>=0.7,"Met Min","Below Min"))) -> Met Min
A20: =B20&TEXT(E20,"00") -> R00804 | B20: R008 | C20: =VLOOKUP(B20,rep_roster!$A:$B,2,0) -> Kevin O'Brien | D20: =VLOOKUP(B20,rep_roster!$A:$D,4,0) -> Mid-Market | E20: 4 | F20: =INDEX({"Jan","Feb","Mar","Apr","May","Jun","Jul","Aug","Sep","Oct","Nov","Dec"},E20) -> Apr | G20: 15 | H20: 11 | I20: =IF(G20>0,H20/G20,0) -> 0.73333333 | J20: 15 | K20: 10 | L20: =IF(K20>0,H20/K20,0) -> 1.1 | M20: =IF(H20=0,"Inactive",IF(I20>=0.7+0.05,"Strong",IF(I20>=0.7,"Met Min","Below Min"))) -> Met Min
A21: =B21&TEXT(E21,"00") -> R00805 | B21: R008 | C21: =VLOOKUP(B21,rep_roster!$A:$B,2,0) -> Kevin O'Brien | D21: =VLOOKUP(B21,rep_roster!$A:$D,4,0) -> Mid-Market | E21: 5 | F21: =INDEX({"Jan","Feb","Mar","Apr","May","Jun","Jul","Aug","Sep","Oct","Nov","Dec"},E21) -> May | G21: 16 | H21: 11 | I21: =IF(G21>0,H21/G21,0) -> 0.6875 | J21: 15 | K21: 10 | L21: =IF(K21>0,H21/K21,0) -> 1.1 | M21: =IF(H21=0,"Inactive",IF(I21>=0.7+0.05,"Strong",IF(I21>=0.7,"Met Min","Below Min"))) -> Below Min
A22: =B22&TEXT(E22,"00") -> R00806 | B22: R008 | C22: =VLOOKUP(B22,rep_roster!$A:$B,2,0) -> Kevin O'Brien | D22: =VLOOKUP(B22,rep_roster!$A:$D,4,0) -> Mid-Market | E22: 6 | F22: =INDEX({"Jan","Feb","Mar","Apr","May","Jun","Jul","Aug","Sep","Oct","Nov","Dec"},E22) -> Jun | G22: 14 | H22: 10 | I22: =IF(G22>0,H22/G22,0) -> 0.71428571 | J22: 15 | K22: 10 | L22: =IF(K22>0,H22/K22,0) -> 1 | M22: =IF(H22=0,"Inactive",IF(I22>=0.7+0.05,"Strong",IF(I22>=0.7,"Met Min","Below Min"))) -> Met Min
A23: =B23&TEXT(E23,"00") -> R00807 | B23: R008 | C23: =VLOOKUP(B23,rep_roster!$A:$B,2,0) -> Kevin O'Brien | D23: =VLOOKUP(B23,rep_roster!$A:$D,4,0) -> Mid-Market | E23: 7 | F23: =INDEX({"Jan","Feb","Mar","Apr","May","Jun","Jul","Aug","Sep","Oct","Nov","Dec"},E23) -> Jul | G23: 12 | H23: 8 | I23: =IF(G23>0,H23/G23,0) -> 0.66666667 | J23: 15 | K23: 10 | L23: =IF(K23>0,H23/K23,0) -> 0.8 | M23: =IF(H23=0,"Inactive",IF(I23>=0.7+0.05,"Strong",IF(I23>=0.7,"Met Min","Below Min"))) -> Below Min
A24: =B24&TEXT(E24,"00") -> R00808 | B24: R008 | C24: =VLOOKUP(B24,rep_roster!$A:$B,2,0) -> Kevin O'Brien | D24: =VLOOKUP(B24,rep_roster!$A:$D,4,0) -> Mid-Market | E24: 8 | F24: =INDEX({"Jan","Feb","Mar","Apr","May","Jun","Jul","Aug","Sep","Oct","Nov","Dec"},E24) -> Aug | G24: 8 | H24: 5 | I24: =IF(G24>0,H24/G24,0) -> 0.625 | J24: 15 | K24: 10 | L24: =IF(K24>0,H24/K24,0) -> 0.5 | M24: =IF(H24=0,"Inactive",IF(I24>=0.7+0.05,"Strong",IF(I24>=0.7,"Met Min","Below Min"))) -> Below Min
A25: =B25&TEXT(E25,"00") -> R00901 | B25: R009 | C25: =VLOOKUP(B25,rep_roster!$A:$B,2,0) -> Aisha Johnson | D25: =VLOOKUP(B25,rep_roster!$A:$D,4,0) -> Mid-Market | E25: 1 | F25: =INDEX({"Jan","Feb","Mar","Apr","May","Jun","Jul","Aug","Sep","Oct","Nov","Dec"},E25) -> Jan | G25: 17 | H25: 12 | I25: =IF(G25>0,H25/G25,0) -> 0.70588235 | J25: 15 | K25: 10 | L25: =IF(K25>0,H25/K25,0) -> 1.2 | M25: =IF(H25=0,"Inactive",IF(I25>=0.7+0.05,"Strong",IF(I25>=0.7,"Met Min","Below Min"))) -> Met Min
A26: =B26&TEXT(E26,"00") -> R00902 | B26: R009 | C26: =VLOOKUP(B26,rep_roster!$A:$B,2,0) -> Aisha Johnson | D26: =VLOOKUP(B26,rep_roster!$A:$D,4,0) -> Mid-Market | E26: 2 | F26: =INDEX({"Jan","Feb","Mar","Apr","May","Jun","Jul","Aug","Sep","Oct","Nov","Dec"},E26) -> Feb | G26: 17 | H26: 12 | I26: =IF(G26>0,H26/G26,0) -> 0.70588235 | J26: 15 | K26: 10 | L26: =IF(K26>0,H26/K26,0) -> 1.2 | M26: =IF(H26=0,"Inactive",IF(I26>=0.7+0.05,"Strong",IF(I26>=0.7,"Met Min","Below Min"))) -> Met Min
A27: =B27&TEXT(E27,"00") -> R00903 | B27: R009 | C27: =VLOOKUP(B27,rep_roster!$A:$B,2,0) -> Aisha Johnson | D27: =VLOOKUP(B27,rep_roster!$A:$D,4,0) -> Mid-Market | E27: 3 | F27: =INDEX({"Jan","Feb","Mar","Apr","May","Jun","Jul","Aug","Sep","Oct","Nov","Dec"},E27) -> Mar | G27: 19 | H27: 14 | I27: =IF(G27>0,H27/G27,0) -> 0.73684211 | J27: 15 | K27: 10 | L27: =IF(K27>0,H27/K27,0) -> 1.4 | M27: =IF(H27=0,"Inactive",IF(I27>=0.7+0.05,"Strong",IF(I27>=0.7,"Met Min","Below Min"))) -> Met Min
A28: =B28&TEXT(E28,"00") -> R00904 | B28: R009 | C28: =VLOOKUP(B28,rep_roster!$A:$B,2,0) -> Aisha Johnson | D28: =VLOOKUP(B28,rep_roster!$A:$D,4,0) -> Mid-Market | E28: 4 | F28: =INDEX({"Jan","Feb","Mar","Apr","May","Jun","Jul","Aug","Sep","Oct","Nov","Dec"},E28) -> Apr | G28: 16 | H28: 11 | I28: =IF(G28>0,H28/G28,0) -> 0.6875 | J28: 15 | K28: 10 | L28: =IF(K28>0,H28/K28,0) -> 1.1 | M28: =IF(H28=0,"Inactive",IF(I28>=0.7+0.05,"Strong",IF(I28>=0.7,"Met Min","Below Min"))) -> Below Min
... A42: =B42&TEXT(E42,"00") -> R01012 | B42: R010 | C42: =VLOOKUP(B42,rep_roster!$A:$B,2,0) -> Jessica Martinez | D42: =VLOOKUP(B42,rep_roster!$A:$D,4,0) -> Mid-Market | E42: 12 | F42: =INDEX({"Jan","Feb","Mar","Apr","May","Jun","Jul","Aug","Sep","Oct","Nov","Dec"},E42) -> Dec | G42: 16 | H42: 11 | I42: =IF(G42>0,H42/G42,0) -> 0.6875 | J42: 9 | K42: 6 | L42: =IF(K42>0,H42/K42,0) -> 1.8333333 | M42: =IF(H42=0,"Inactive",IF(I42>=0.7+0.05,"Strong",IF(I42>=0.7,"Met Min","Below Min"))) -> Below Min
A43: =B43&TEXT(E43,"00") -> R01601 | B43: R016 | C43: =VLOOKUP(B43,rep_roster!$A:$B,2,0) -> Nina Patel | D43: =VLOOKUP(B43,rep_roster!$A:$D,4,0) -> SMB | E43: 1 | F43: =INDEX({"Jan","Feb","Mar","Apr","May","Jun","Jul","Aug","Sep","Oct","Nov","Dec"},E43) -> Jan | G43: 29 | H43: 20 | I43: =IF(G43>0,H43/G43,0) -> 0.68965517 | J43: 25 | K43: 16 | L43: =IF(K43>0,H43/K43,0) -> 1.25 | M43: =IF(H43=0,"Inactive",IF(I43>=0.65+0.05,"Strong",IF(I43>=0.65,"Met Min","Below Min"))) -> Met Min
A44: =B44&TEXT(E44,"00") -> R01602 | B44: R016 | C44: =VLOOKUP(B44,rep_roster!$A:$B,2,0) -> Nina Patel | D44: =VLOOKUP(B44,rep_roster!$A:$D,4,0) -> SMB | E44: 2 | F44: =INDEX({"Jan","Feb","Mar","Apr","May","Jun","Jul","Aug","Sep","Oct","Nov","Dec"},E44) -> Feb | G44: 27 | H44: 18 | I44: =IF(G44>0,H44/G44,0) -> 0.66666667 | J44: 25 | K44: 16 | L44: =IF(K44>0,H44/K44,0) -> 1.125 | M44: =IF(H44=0,"Inactive",IF(I44>=0.65+0.05,"Strong",IF(I44>=0.65,"Met Min","Below Min"))) -> Met Min
A45: =B45&TEXT(E45,"00") -> R01603 | B45: R016 | C45: =VLOOKUP(B45,rep_roster!$A:$B,2,0) -> Nina Patel | D45: =VLOOKUP(B45,rep_roster!$A:$D,4,0) -> SMB | E45: 3 | F45: =INDEX({"Jan","Feb","Mar","Apr","May","Jun","Jul","Aug","Sep","Oct","Nov","Dec"},E45) -> Mar | G45: 31 | H45: 21 | I45: =IF(G45>0,H45/G45,0) -> 0.67741935 | J45: 25 | K45: 16 | L45: =IF(K45>0,H45/K45,0) -> 1.3125 | M45: =IF(H45=0,"Inactive",IF(I45>=0.65+0.05,"Strong",IF(I45>=0.65,"Met Min","Below Min"))) -> Met Min
A46: =B46&TEXT(E46,"00") -> R01604 | B46: R016 | C46: =VLOOKUP(B46,rep_roster!$A:$B,2,0) -> Nina Patel | D46: =VLOOKUP(B46,rep_roster!$A:$D,4,0) -> SMB | E46: 4 | F46: =INDEX({"Jan","Feb","Mar","Apr","May","Jun","Jul","Aug","Sep","Oct","Nov","Dec"},E46) -> Apr | G46: 26 | H46: 17 | I46: =IF(G46>0,H46/G46,0) -> 0.65384615 | J46: 25 | K46: 16 | L46: =IF(K46>0,H46/K46,0) -> 1.0625 | M46: =IF(H46=0,"Inactive",IF(I46>=0.65+0.05,"Strong",IF(I46>=0.65,"Met Min","Below Min"))) -> Met Min
A47: =B47&TEXT(E47,"00") -> R01605 | B47: R016 | C47: =VLOOKUP(B47,rep_roster!$A:$B,2,0) -> Nina Patel | D47: =VLOOKUP(B47,rep_roster!$A:$D,4,0) -> SMB | E47: 5 | F47: =INDEX({"Jan","Feb","Mar","Apr","May","Jun","Jul","Aug","Sep","Oct","Nov","Dec"},E47) -> May | G47: 27 | H47: 18 | I47: =IF(G47>0,H47/G47,0) -> 0.66666667 | J47: 25 | K47: 16 | L47: =IF(K47>0,H47/K47,0) -> 1.125 | M47: =IF(H47=0,"Inactive",IF(I47>=0.65+0.05,"Strong",IF(I47>=0.65,"Met Min","Below Min"))) -> Met Min
A48: =B48&TEXT(E48,"00") -> R01606 | B48: R016 | C48: =VLOOKUP(B48,rep_roster!$A:$B,2,0) -> Nina Patel | D48: =VLOOKUP(B48,rep_roster!$A:$D,4,0) -> SMB | E48: 6 | F48: =INDEX({"Jan","Feb","Mar","Apr","May","Jun","Jul","Aug","Sep","Oct","Nov","Dec"},E48) -> Jun | G48: 25 | H48: 16 | I48: =IF(G48>0,H48/G48,0) -> 0.64 | J48: 25 | K48: 16 | L48: =IF(K48>0,H48/K48,0) -> 1 | M48: =IF(H48=0,"Inactive",IF(I48>=0.65+0.05,"Strong",IF(I48>=0.65,"Met Min","Below Min"))) -> Below Min
A49: =B49&TEXT(E49,"00") -> R01607 | B49: R016 | C49: =VLOOKUP(B49,rep_roster!$A:$B,2,0) -> Nina Patel | D49: =VLOOKUP(B49,rep_roster!$A:$D,4,0) -> SMB | E49: 7 | F49: =INDEX({"Jan","Feb","Mar","Apr","May","Jun","Jul","Aug","Sep","Oct","Nov","Dec"},E49) -> Jul | G49: 21 | H49: 13 | I49: =IF(G49>0,H49/G49,0) -> 0.61904762 | J49: 25 | K49: 16 | L49: =IF(K49>0,H49/K49,0) -> 0.8125 | M49: =IF(H49=0,"Inactive",IF(I49>=0.65+0.05,"Strong",IF(I49>=0.65,"Met Min","Below Min"))) -> Below Min
A50: =B50&TEXT(E50,"00") -> R01608 | B50: R016 | C50: =VLOOKUP(B50,rep_roster!$A:$B,2,0) -> Nina Patel | D50: =VLOOKUP(B50,rep_roster!$A:$D,4,0) -> SMB | E50: 8 | F50: =INDEX({"Jan","Feb","Mar","Apr","May","Jun","Jul","Aug","Sep","Oct","Nov","Dec"},E50) -> Aug | G50: 19 | H50: 12 | I50: =IF(G50>0,H50/G50,0) -> 0.63157895 | J50: 25 | K50: 16 | L50: =IF(K50>0,H50/K50,0) -> 0.75 | M50: =IF(H50=0,"Inactive",IF(I50>=0.65+0.05,"Strong",IF(I50>=0.65,"Met Min","Below Min"))) -> Below Min
A51: =B51&TEXT(E51,"00") -> R01609 | B51: R016 | C51: =VLOOKUP(B51,rep_roster!$A:$B,2,0) -> Nina Patel | D51: =VLOOKUP(B51,rep_roster!$A:$D,4,0) -> SMB | E51: 9 | F51: =INDEX({"Jan","Feb","Mar","Apr","May","Jun","Jul","Aug","Sep","Oct","Nov","Dec"},E51) -> Sep | G51: 23 | H51: 15 | I51: =IF(G51>0,H51/G51,0) -> 0.65217391 | J51: 25 | K51: 16 | L51: =IF(K51>0,H51/K51,0) -> 0.9375 | M51: =IF(H51=0,"Inactive",IF(I51>=0.65+0.05,"Strong",IF(I51>=0.65,"Met Min","Below Min"))) -> Met Min
A52: =B52&TEXT(E52,"00") -> R01610 | B52: R016 | C52: =VLOOKUP(B52,rep_roster!$A:$B,2,0) -> Nina Patel | D52: =VLOOKUP(B52,rep_roster!$A:$D,4,0) -> SMB | E52: 10 | F52: =INDEX({"Jan","Feb","Mar","Apr","May","Jun","Jul","Aug","Sep","Oct","Nov","Dec"},E52) -> Oct | G52: 20 | H52: 13 | I52: =IF(G52>0,H52/G52,0) -> 0.65 | J52: 25 | K52: 16 | L52: =IF(K52>0,H52/K52,0) -> 0.8125 | M52: =IF(H52=0,"Inactive",IF(I52>=0.65+0.05,"Strong",IF(I52>=0.65,"Met Min","Below Min"))) -> Met Min
A53: =B53&TEXT(E53,"00") -> R01611 | B53: R016 | C53: =VLOOKUP(B53,rep_roster!$A:$B,2,0) -> Nina Patel | D53: =VLOOKUP(B53,rep_roster!$A:$D,4,0) -> SMB | E53: 11 | F53: =INDEX({"Jan","Feb","Mar","Apr","May","Jun","Jul","Aug","Sep","Oct","Nov","Dec"},E53) -> Nov | G53: 22 | H53: 14 | I53: =IF(G53>0,H53/G53,0) -> 0.63636364 | J53: 25 | K53: 16 | L53: =IF(K53>0,H53/K53,0) -> 0.875 | M53: =IF(H53=0,"Inactive",IF(I53>=0.65+0.05,"Strong",IF(I53>=0.65,"Met Min","Below Min"))) -> Below Min
A54: =B54&TEXT(E54,"00") -> R01612 | B54: R016 | C54: =VLOOKUP(B54,rep_roster!$A:$B,2,0) -> Nina Patel | D54: =VLOOKUP(B54,rep_roster!$A:$D,4,0) -> SMB | E54: 12 | F54: =INDEX({"Jan","Feb","Mar","Apr","May","Jun","Jul","Aug","Sep","Oct","Nov","Dec"},E54) -> Dec | G54: 25 | H54: 17 | I54: =IF(G54>0,H54/G54,0) -> 0.68 | J54: 25 | K54: 16 | L54: =IF(K54>0,H54/K54,0) -> 1.0625 | M54: =IF(H54=0,"Inactive",IF(I54>=0.65+0.05,"Strong",IF(I54>=0.65,"Met Min","Below Min"))) -> Met Min
... A66: =B66&TEXT(E66,"00") -> R01712 | B66: R017 | C66: =VLOOKUP(B66,rep_roster!$A:$B,2,0) -> Derek Washington | D66: =VLOOKUP(B66,rep_roster!$A:$D,4,0) -> SMB | E66: 12 | F66: =INDEX({"Jan","Feb","Mar","Apr","May","Jun","Jul","Aug","Sep","Oct","Nov","Dec"},E66) -> Dec | G66: 24 | H66: 16 | I66: =IF(G66>0,H66/G66,0) -> 0.66666667 | J66: 25 | K66: 16 | L66: =IF(K66>0,H66/K66,0) -> 1 | M66: =IF(H66=0,"Inactive",IF(I66>=0.65+0.05,"Strong",IF(I66>=0.65,"Met Min","Below Min"))) -> Met Min

Sheet commission_calc
A1: VELTORA INC. · COMMISSION CALCULATION ENGINE · FY 2025
A2: VLOOKUP-driven comp engine | IFS accelerator logic | Monthly base + variable | Managers excluded (see team_rollup)
A4: Row | B4: Rep ID | C4: Mo # | D4: Rep Name | E4: Role | F4: Segment | G4: Mo | H4: Yr | I4: Monthly Base ($) | J4: Monthly Quota | K4: Actual | L4: Attainment % | M4: Plan Key | N4: Comm. Rate | O4: Std. Commission ($) | P4: Accel 1 Threshold | Q4: Accel 1 Mult | R4: Accel 2 Threshold | S4: Accel 2 Mult | T4: Accel Multiplier (IFS) | U4: Total Monthly Variable ($) | V4: Total Monthly Cash ($)
A5: 1 | B5: R002 | C5: 1 | D5: =VLOOKUP(B5,rep_roster!$A:$B,2,0) -> Marcus Williams | E5: =VLOOKUP(B5,rep_roster!$A:$C,3,0) -> SDR | F5: =VLOOKUP(B5,rep_roster!$A:$D,4,0) -> Enterprise | G5: =INDEX({"Jan","Feb","Mar","Apr","May","Jun","Jul","Aug","Sep","Oct","Nov","Dec"},C5) -> Jan | H5: 2025 | I5: =IFERROR(VLOOKUP(E5&"_"&F5,plan_catalog!$A:$D,4,0)/12,0) -> 5166.6667 | J5: 8 | K5: 9 | L5: =IF(J5>0,K5/J5,0) -> 1.125 | M5: =IFERROR(VLOOKUP(B5,rep_roster!$A:$L,12,0),E5&"_"&F5) -> SDR_Enterprise | N5: =IFERROR(VLOOKUP(M5,plan_catalog!$A:$G,7,0),0) -> 319 | O5: =K5*N5 -> 2871 | P5: =IFERROR(VLOOKUP(M5,plan_catalog!$A:$I,9,0),0) -> 1.1 | Q5: =IFERROR(VLOOKUP(M5,plan_catalog!$A:$J,10,0),1) -> 1.3 | R5: =IFERROR(VLOOKUP(M5,plan_catalog!$A:$K,11,0),0) -> — | S5: =IFERROR(VLOOKUP(M5,plan_catalog!$A:$L,12,0),1) -> — | T5: =IF(AND(R5>0,L5>=R5),S5,IF(AND(P5>0,L5>=P5),Q5,1)) -> 1.3 | U5: =O5*T5 -> 3732.3 | V5: =I5+U5 -> 8898.9667
A6: 2 | B6: R002 | C6: 2 | D6: =VLOOKUP(B6,rep_roster!$A:$B,2,0) -> Marcus Williams | E6: =VLOOKUP(B6,rep_roster!$A:$C,3,0) -> SDR | F6: =VLOOKUP(B6,rep_roster!$A:$D,4,0) -> Enterprise | G6: =INDEX({"Jan","Feb","Mar","Apr","May","Jun","Jul","Aug","Sep","Oct","Nov","Dec"},C6) -> Feb | H6: 2025 | I6: =IFERROR(VLOOKUP(E6&"_"&F6,plan_catalog!$A:$D,4,0)/12,0) -> 5166.6667 | J6: 8 | K6: 8 | L6: =IF(J6>0,K6/J6,0) -> 1 | M6: =IFERROR(VLOOKUP(B6,rep_roster!$A:$L,12,0),E6&"_"&F6) -> SDR_Enterprise | N6: =IFERROR(VLOOKUP(M6,plan_catalog!$A:$G,7,0),0) -> 319 | O6: =K6*N6 -> 2552 | P6: =IFERROR(VLOOKUP(M6,plan_catalog!$A:$I,9,0),0) -> 1.1 | Q6: =IFERROR(VLOOKUP(M6,plan_catalog!$A:$J,10,0),1) -> 1.3 | R6: =IFERROR(VLOOKUP(M6,plan_catalog!$A:$K,11,0),0) -> — | S6: =IFERROR(VLOOKUP(M6,plan_catalog!$A:$L,12,0),1) -> — | T6: =IF(AND(R6>0,L6>=R6),S6,IF(AND(P6>0,L6>=P6),Q6,1)) -> 1 | U6: =O6*T6 -> 2552 | V6: =I6+U6 -> 7718.6667
A7: 3 | B7: R002 | C7: 3 | D7: =VLOOKUP(B7,rep_roster!$A:$B,2,0) -> Marcus Williams | E7: =VLOOKUP(B7,rep_roster!$A:$C,3,0) -> SDR | F7: =VLOOKUP(B7,rep_roster!$A:$D,4,0) -> Enterprise | G7: =INDEX({"Jan","Feb","Mar","Apr","May","Jun","Jul","Aug","Sep","Oct","Nov","Dec"},C7) -> Mar | H7: 2025 | I7: =IFERROR(VLOOKUP(E7&"_"&F7,plan_catalog!$A:$D,4,0)/12,0) -> 5166.6667 | J7: 8 | K7: 9 | L7: =IF(J7>0,K7/J7,0) -> 1.125 | M7: =IFERROR(VLOOKUP(B7,rep_roster!$A:$L,12,0),E7&"_"&F7) -> SDR_Enterprise | N7: =IFERROR(VLOOKUP(M7,plan_catalog!$A:$G,7,0),0) -> 319 | O7: =K7*N7 -> 2871 | P7: =IFERROR(VLOOKUP(M7,plan_catalog!$A:$I,9,0),0) -> 1.1 | Q7: =IFERROR(VLOOKUP(M7,plan_catalog!$A:$J,10,0),1) -> 1.3 | R7: =IFERROR(VLOOKUP(M7,plan_catalog!$A:$K,11,0),0) -> — | S7: =IFERROR(VLOOKUP(M7,plan_catalog!$A:$L,12,0),1) -> — | T7: =IF(AND(R7>0,L7>=R7),S7,IF(AND(plan_catalog!P7>0,L7>=P7),Q7,1)) -> 1 | U7: =O7*T7 -> 2871 | V7: =I7+U7 -> 8037.6667
A8: 4 | B8: R002 | C8: 4 | D8: =VLOOKUP(B8,rep_roster!$A:$B,2,0) -> Marcus Williams | E8: =VLOOKUP(B8,rep_roster!$A:$C,3,0) -> SDR | F8: =VLOOKUP(B8,rep_roster!$A:$D,4,0) -> Enterprise | G8: =INDEX({"Jan","Feb","Mar","Apr","May","Jun","Jul","Aug","Sep","Oct","Nov","Dec"},C8) -> Apr | H8: 2025 | I8: =IFERROR(VLOOKUP(E8&"_"&F8,plan_catalog!$A:$D,4,0)/12,0) -> 5166.6667 | J8: 8 | K8: 7 | L8: =IF(J8>0,K8/J8,0) -> 0.875 | M8: =IFERROR(VLOOKUP(B8,rep_roster!$A:$L,12,0),E8&"_"&F8) -> SDR_Enterprise | N8: =IFERROR(VLOOKUP(M8,plan_catalog!$A:$G,7,0),0) -> 319 | O8: =K8*N8 -> 2233 | P8: =IFERROR(VLOOKUP(M8,plan_catalog!$A:$I,9,0),0) -> 1.1 | Q8: =IFERROR(VLOOKUP(M8,plan_catalog!$A:$J,10,0),1) -> 1.3 | R8: =IFERROR(VLOOKUP(M8,plan_catalog!$A:$K,11,0),0) -> — | S8: =IFERROR(VLOOKUP(M8,plan_catalog!$A:$L,12,0),1) -> — | T8: =IF(AND(R8>0,L8>=R8),S8,IF(AND(P8>0,L8>=P8),Q8,1)) -> 1 | U8: =O8*T8 -> 2233 | V8: =I8+U8 -> 7399.6667
A9: 5 | B9: R002 | C9: 5 | D9: =VLOOKUP(B9,rep_roster!$A:$B,2,0) -> Marcus Williams | E9: =VLOOKUP(B9,rep_roster!$A:$C,3,0) -> SDR | F9: =VLOOKUP(B9,rep_roster!$A:$D,4,0) -> Enterprise | G9: =INDEX({"Jan","Feb","Mar","Apr","May","Jun","Jul","Aug","Sep","Oct","Nov","Dec"},C9) -> May | H9: 2025 | I9: =IFERROR(VLOOKUP(E9&"_"&F9,plan_catalog!$A:$D,4,0)/12,0) -> 5166.6667 | J9: 8 | K9: 8 | L9: =IF(J9>0,K9/J9,0) -> 1 | M9: =IFERROR(VLOOKUP(B9,rep_roster!$A:$L,12,0),E9&"_"&F9) -> SDR_Enterprise | N9: =IFERROR(VLOOKUP(M9,plan_catalog!$A:$G,7,0),0) -> 319 | O9: =K9*N9 -> 2552 | P9: =IFERROR(VLOOKUP(M9,plan_catalog!$A:$I,9,0),0) -> 1.1 | Q9: =IFERROR(VLOOKUP(M9,plan_catalog!$A:$J,10,0),1) -> 1.3 | R9: =IFERROR(VLOOKUP(M9,plan_catalog!$A:$K,11,0),0) -> — | S9: =IFERROR(VLOOKUP(M9,plan_catalog!$A:$L,12,0),1) -> — | T9: =IF(AND(R9>0,L9>=R9),S9,IF(AND(P9>0,L9>=P9),Q9,1)) -> 1 | U9: =O9*T9 -> 2552 | V9: =I9+U9 -> 7718.6667
A10: 6 | B10: R002 | C10: 6 | D10: =VLOOKUP(B10,rep_roster!$A:$B,2,0) -> Marcus Williams | E10: =VLOOKUP(B10,rep_roster!$A:$C,3,0) -> SDR | F10: =VLOOKUP(B10,rep_roster!$A:$D,4,0) -> Enterprise | G10: =INDEX({"Jan","Feb","Mar","Apr","May","Jun","Jul","Aug","Sep","Oct","Nov","Dec"},C10) -> Jun | H10: 2025 | I10: =IFERROR(VLOOKUP(E10&"_"&F10,plan_catalog!$A:$D,4,0)/12,0) -> 5166.6667 | J10: 8 | K10: 7 | L10: =IF(J10>0,K10/J10,0) -> 0.875 | M10: =IFERROR(VLOOKUP(B10,rep_roster!$A:$L,12,0),E10&"_"&F10) -> SDR_Enterprise | N10: =IFERROR(VLOOKUP(M10,plan_catalog!$A:$G,7,0),0) -> 319 | O10: =K10*N10 -> 2233 | P10: =IFERROR(VLOOKUP(M10,plan_catalog!$A:$I,9,0),0) -> 1.1 | Q10: =IFERROR(VLOOKUP(M10,plan_catalog!$A:$J,10,0),1) -> 1.3 | R10: =IFERROR(VLOOKUP(M10,plan_catalog!$A:$K,11,0),0) -> — | S10: =IFERROR(VLOOKUP(M10,plan_catalog!$A:$L,12,0),1) -> — | T10: =IF(AND(R10>0,L10>=R10),S10,IF(AND(P10>0,L10>=P10),Q10,1)) -> 1 | U10: =O10*T10 -> 2233 | V10: =I10+U10 -> 7399.6667
A11: 7 | B11: R002 | C11: 7 | D11: =VLOOKUP(B11,rep_roster!$A:$B,2,0) -> Marcus Williams | E11: =VLOOKUP(B11,rep_roster!$A:$C,3,0) -> SDR | F11: =VLOOKUP(B11,rep_roster!$A:$D,4,0) -> Enterprise | G11: =INDEX({"Jan","Feb","Mar","Apr","May","Jun","Jul","Aug","Sep","Oct","Nov","Dec"},C11) -> Jul | H11: 2025 | I11: =IFERROR(VLOOKUP(E11&"_"&F11,plan_catalog!$A:$D,4,0)/12,0) -> 5166.6667 | J11: 8 | K11: 5 | L11: =IF(J11>0,K11/J11,0) -> 0.625 | M11: =IFERROR(VLOOKUP(B11,rep_roster!$A:$L,12,0),E11&"_"&F11) -> SDR_Enterprise | N11: =IFERROR(VLOOKUP(M11,plan_catalog!$A:$G,7,0),0) -> 319 | O11: =K11*N11 -> 1595 | P11: =IFERROR(VLOOKUP(M11,plan_catalog!$A:$I,9,0),0) -> 1.1 | Q11: =IFERROR(VLOOKUP(M11,plan_catalog!$A:$J,10,0),1) -> 1.3 | R11: =IFERROR(VLOOKUP(M11,plan_catalog!$A:$K,11,0),0) -> — | S11: =IFERROR(VLOOKUP(M11,plan_catalog!$A:$L,12,0),1) -> — | T11: =IF(AND(R11>0,L11>=R11),S11,IF(AND(P11>0,L11>=P11),Q11,1)) -> 1 | U11: =O11*T11 -> 1595 | V11: =I11+U11 -> 6761.6667
A12: 8 | B12: R002 | C12: 8 | D12: =VLOOKUP(B12,rep_roster!$A:$B,2,0) -> Marcus Williams | E12: =VLOOKUP(B12,rep_roster!$A:$C,3,0) -> SDR | F12: =VLOOKUP(B12,rep_roster!$A:$D,4,0) -> Enterprise | G12: =INDEX({"Jan","Feb","Mar","Apr","May","Jun","Jul","Aug","Sep","Oct","Nov","Dec"},C12) -> Aug | H12: 2025 | I12: =IFERROR(VLOOKUP(E12&"_"&F12,plan_catalog!$A:$D,4,0)/12,0) -> 5166.6667 | J12: 8 | K12: 4 | L12: =IF(J12>0,K12/J12,0) -> 0.5 | M12: =IFERROR(VLOOKUP(B12,rep_roster!$A:$L,12,0),E12&"_"&F12) -> SDR_Enterprise | N12: =IFERROR(VLOOKUP(M12,plan_catalog!$A:$G,7,0),0) -> 319 | O12: =K12*N12 -> 1276 | P12: =IFERROR(VLOOKUP(M12,plan_catalog!$A:$I,9,0),0) -> 1.1 | Q12: =IFERROR(VLOOKUP(M12,plan_catalog!$A:$J,10,0),1) -> 1.3 | R12: =IFERROR(VLOOKUP(M12,plan_catalog!$A:$K,11,0),0) -> — | S12: =IFERROR(VLOOKUP(M12,plan_catalog!$A:$L,12,0),1) -> — | T12: =IF(AND(R12>0,L12>=R12),S12,IF(AND(P12>0,L12>=P12),Q12,1)) -> 1 | U12: =O12*T12 -> 1276 | V12: =I12+U12 -> 6442.6667
A13: 9 | B13: R002 | C13: 9 | D13: =VLOOKUP(B13,rep_roster!$A:$B,2,0) -> Marcus Williams | E13: =VLOOKUP(B13,rep_roster!$A:$C,3,0) -> SDR | F13: =VLOOKUP(B13,rep_roster!$A:$D,4,0) -> Enterprise | G13: =INDEX({"Jan","Feb","Mar","Apr","May","Jun","Jul","Aug","Sep","Oct","Nov","Dec"},C13) -> Sep | H13: 2025 | I13: =IFERROR(VLOOKUP(E13&"_"&F13,plan_catalog!$A:$D,4,0)/12,0) -> 5166.6667 | J13: 8 | K13: 6 | L13: =IF(J13>0,K13/J13,0) -> 0.75 | M13: =IFERROR(VLOOKUP(B13,rep_roster!$A:$L,12,0),E13&"_"&F13) -> SDR_Enterprise | N13: =IFERROR(VLOOKUP(M13,plan_catalog!$A:$G,7,0),0) -> 319 | O13: =K13*N13 -> 1914 | P13: =IFERROR(VLOOKUP(M13,plan_catalog!$A:$I,9,0),0) -> 1.1 | Q13: =IFERROR(VLOOKUP(M13,plan_catalog!$A:$J,10,0),1) -> 1.3 | R13: =IFERROR(VLOOKUP(M13,plan_catalog!$A:$K,11,0),0) -> — | S13: =IFERROR(VLOOKUP(M13,plan_catalog!$A:$L,12,0),1) -> — | T13: =IF(AND(R13>0,L13>=R13),S13,IF(AND(P13>0,L13>=P13),Q13,1)) -> 1 | U13: =O13*T13 -> 1914 | V13: =I13+U13 -> 7080.6667
A14: 10 | B14: R002 | C14: 10 | D14: =VLOOKUP(B14,rep_roster!$A:$B,2,0) -> Marcus Williams | E14: =VLOOKUP(B14,rep_roster!$A:$C,3,0) -> SDR | F14: =VLOOKUP(B14,rep_roster!$A:$D,4,0) -> Enterprise | G14: =INDEX({"Jan","Feb","Mar","Apr","May","Jun","Jul","Aug","Sep","Oct","Nov","Dec"},C14) -> Oct | H14: 2025 | I14: =IFERROR(VLOOKUP(E14&"_"&F14,plan_catalog!$A:$D,4,0)/12,0) -> 5166.6667 | J14: 8 | K14: 5 | L14: =IF(J14>0,K14/J14,0) -> 0.625 | M14: =IFERROR(VLOOKUP(B14,rep_roster!$A:$L,12,0),E14&"_"&F14) -> SDR_Enterprise | N14: =IFERROR(VLOOKUP(M14,plan_catalog!$A:$G,7,0),0) -> 319 | O14: =K14*N14 -> 1595 | P14: =IFERROR(VLOOKUP(M14,plan_catalog!$A:$I,9,0),0) -> 1.1 | Q14: =IFERROR(VLOOKUP(M14,plan_catalog!$A:$J,10,0),1) -> 1.3 | R14: =IFERROR(VLOOKUP(M14,plan_catalog!$A:$K,11,0),0) -> — | S14: =IFERROR(VLOOKUP(M14,plan_catalog!$A:$L,12,0),1) -> — | T14: =IF(AND(R14>0,L14>=R14),S14,IF(AND(P14>0,L14>=P14),Q14,1)) -> 1 | U14: =O14*T14 -> 1595 | V14: =I14+U14 -> 6761.6667
A15: 11 | B15: R002 | C15: 11 | D15: =VLOOKUP(B15,rep_roster!$A:$B,2,0) -> Marcus Williams | E15: =VLOOKUP(B15,rep_roster!$A:$C,3,0) -> SDR | F15: =VLOOKUP(B15,rep_roster!$A:$D,4,0) -> Enterprise | G15: =INDEX({"Jan","Feb","Mar","Apr","May","Jun","Jul","Aug","Sep","Oct","Nov","Dec"},C15) -> Nov | H15: 2025 | I15: =IFERROR(VLOOKUP(E15&"_"&F15,plan_catalog!$A:$D,4,0)/12,0) -> 5166.6667 | J15: 8 | K15: 6 | L15: =IF(J15>0,K15/J15,0) -> 0.75 | M15: =IFERROR(VLOOKUP(B15,rep_roster!$A:$L,12,0),E15&"_"&F15) -> SDR_Enterprise | N15: =IFERROR(VLOOKUP(M15,plan_catalog!$A:$G,7,0),0) -> 319 | O15: =K15*N15 -> 1914 | P15: =IFERROR(VLOOKUP(M15,plan_catalog!$A:$I,9,0),0) -> 1.1 | Q15: =IFERROR(VLOOKUP(M15,plan_catalog!$A:$J,10,0),1) -> 1.3 | R15: =IFERROR(VLOOKUP(M15,plan_catalog!$A:$K,11,0),0) -> — | S15: =IFERROR(VLOOKUP(M15,plan_catalog!$A:$L,12,0),1) -> — | T15: =IF(AND(R15>0,L15>=R15),S15,IF(AND(P15>0,L15>=P15),Q15,1)) -> 1 | U15: =O15*T15 -> 1914 | V15: =I15+U15 -> 7080.6667
A16: 12 | B16: R002 | C16: 12 | D16: =VLOOKUP(B16,rep_roster!$A:$B,2,0) -> Marcus Williams | E16: =VLOOKUP(B16,rep_roster!$A:$C,3,0) -> SDR | F16: =VLOOKUP(B16,rep_roster!$A:$D,4,0) -> Enterprise | G16: =INDEX({"Jan","Feb","Mar","Apr","May","Jun","Jul","Aug","Sep","Oct","Nov","Dec"},C16) -> Dec | H16: 2025 | I16: =IFERROR(VLOOKUP(E16&"_"&F16,plan_catalog!$A:$D,4,0)/12,0) -> 5166.6667 | J16: 8 | K16: 7 | L16: =IF(J16>0,K16/J16,0) -> 0.875 | M16: =IFERROR(VLOOKUP(B16,rep_roster!$A:$L,12,0),E16&"_"&F16) -> SDR_Enterprise | N16: =IFERROR(VLOOKUP(M16,plan_catalog!$A:$G,7,0),0) -> 319 | O16: =K16*N16 -> 2233 | P16: =IFERROR(VLOOKUP(M16,plan_catalog!$A:$I,9,0),0) -> 1.1 | Q16: =IFERROR(VLOOKUP(M16,plan_catalog!$A:$J,10,0),1) -> 1.3 | R16: =IFERROR(VLOOKUP(M16,plan_catalog!$A:$K,11,0),0) -> — | S16: =IFERROR(VLOOKUP(M16,plan_catalog!$A:$L,12,0),1) -> — | T16: =IF(AND(R16>0,L16>=R16),S16,IF(AND(P16>0,L16>=P16),Q16,1)) -> 1 | U16: =O16*T16 -> 2233 | V16: =I16+U16 -> 7399.6667
A17: 13 | B17: R003 | C17: 1 | D17: =VLOOKUP(B17,rep_roster!$A:$B,2,0) -> James Harrington | E17: =VLOOKUP(B17,rep_roster!$A:$C,3,0) -> AE | F17: =VLOOKUP(B17,rep_roster!$A:$D,4,0) -> Enterprise | G17: =INDEX({"Jan","Feb","Mar","Apr","May","Jun","Jul","Aug","Sep","Oct","Nov","Dec"},C17) -> Jan | H17: 2025 | I17: =IFERROR(VLOOKUP(E17&"_"&F17,plan_catalog!$A:$D,4,0)/12,0) -> 7916.6667 | J17: 75000 | K17: 95000 | L17: =IF(J17>0,K17/J17,0) -> 1.2666667 | M17: =IFERROR(VLOOKUP(B17,rep_roster!$A:$L,12,0),E17&"_"&F17) -> AE_Enterprise | N17: =IFERROR(VLOOKUP(M17,plan_catalog!$A:$G,7,0),0) -> 0.1 | O17: =K17*N17 -> 9500 | P17: =IFERROR(VLOOKUP(M17,plan_catalog!$A:$I,9,0),0) -> 1 | Q17: =IFERROR(VLOOKUP(M17,plan_catalog!$A:$J,10,0),1) -> 1.25 | R17: =IFERROR(VLOOKUP(M17,plan_catalog!$A:$K,11,0),0) -> 1.2 | S17: =IFERROR(VLOOKUP(M17,plan_catalog!$A:$L,12,0),1) -> 1.5 | T17: =IF(AND(R17>0,L17>=R17),S17,IF(AND(P17>0,L17>=P17),Q17,1)) -> 1.5 | U17: =O17*T17 -> 14250 | V17: =I17+U17 -> 22166.667
A18: 14 | B18: R003 | C18: 2 | D18: =VLOOKUP(B18,rep_roster!$A:$B,2,0) -> James Harrington | E18: =VLOOKUP(B18,rep_roster!$A:$C,3,0) -> AE | F18: =VLOOKUP(B18,rep_roster!$A:$D,4,0) -> Enterprise | G18: =INDEX({"Jan","Feb","Mar","Apr","May","Jun","Jul","Aug","Sep","Oct","Nov","Dec"},C18) -> Feb | H18: 2025 | I18: =IFERROR(VLOOKUP(E18&"_"&F18,plan_catalog!$A:$D,4,0)/12,0) -> 7916.6667 | J18: 75000 | K18: 88000 | L18: =IF(J18>0,K18/J18,0) -> 1.1733333 | M18: =IFERROR(VLOOKUP(B18,rep_roster!$A:$L,12,0),E18&"_"&F18) -> AE_Enterprise | N18: =IFERROR(VLOOKUP(M18,plan_catalog!$A:$G,7,0),0) -> 0.1 | O18: =K18*N18 -> 8800 | P18: =IFERROR(VLOOKUP(M18,plan_catalog!$A:$I,9,0),0) -> 1 | Q18: =IFERROR(VLOOKUP(M18,plan_catalog!$A:$J,10,0),1) -> 1.25 | R18: =IFERROR(VLOOKUP(M18,plan_catalog!$A:$K,11,0),0) -> 1.2 | S18: =IFERROR(VLOOKUP(M18,plan_catalog!$A:$L,12,0),1) -> 1.5 | T18: =IF(AND(R18>0,L18>=R18),S18,IF(AND(P18>0,L18>=P18),Q18,1)) -> 1.25 | U18: =O18*T18 -> 11000 | V18: =I18+U18 -> 18916.667
A19: 15 | B19: R003 | C19: 3 | D19: =VLOOKUP(B19,rep_roster!$A:$B,2,0) -> James Harrington | E19: =VLOOKUP(B19,rep_roster!$A:$C,3,0) -> AE | F19: =VLOOKUP(B19,rep_roster!$A:$D,4,0) -> Enterprise | G19: =INDEX({"Jan","Feb","Mar","Apr","May","Jun","Jul","Aug","Sep","Oct","Nov","Dec"},C19) -> Mar | H19: 2025 | I19: =IFERROR(VLOOKUP(E19&"_"&F19,plan_catalog!$A:$D,4,0)/12,0) -> 7916.6667 | J19: 75000 | K19: 105000 | L19: =IF(J19>0,K19/J19,0) -> 1.4 | M19: =IFERROR(VLOOKUP(B19,rep_roster!$A:$L,12,0),E19&"_"&F19) -> AE_Enterprise | N19: =IFERROR(VLOOKUP(M19,plan_catalog!$A:$G,7,0),0) -> 0.1 | O19: =K19*N19 -> 10500 | P19: =IFERROR(VLOOKUP(M19,plan_catalog!$A:$I,9,0),0) -> 1 | Q19: =IFERROR(VLOOKUP(M19,plan_catalog!$A:$J,10,0),1) -> 1.25 | R19: =IFERROR(VLOOKUP(M19,plan_catalog!$A:$K,11,0),0) -> 1.2 | S19: =IFERROR(VLOOKUP(M19,plan_catalog!$A:$L,12,0),1) -> 1.5 | T19: =IF(AND(R19>0,L19>=R19),S19,IF(AND(P19>0,L19>=P19),Q19,1)) -> 1.5 | U19: =O19*T19 -> 15750 | V19: =I19+U19 -> 23666.667
... A186: 182 | B186: R021 | C186: 12 | D186: =VLOOKUP(B186,rep_roster!$A:$B,2,0) -> Jennifer Walsh | E186: =VLOOKUP(B186,rep_roster!$A:$C,3,0) -> CSM | F186: =VLOOKUP(B186,rep_roster!$A:$D,4,0) -> SMB | G186: =INDEX({"Jan","Feb","Mar","Apr","May","Jun","Jul","Aug","Sep","Oct","Nov","Dec"},C186) -> Dec | H186: 2025 | I186: =IFERROR(VLOOKUP(E186&"_"&F186,plan_catalog!$A:$D,4,0)/12,0) -> 5000 | J186: 5000 | K186: 5000 | L186: =IF(J186>0,K186/J186,0) -> 1 | M186: =IFERROR(VLOOKUP(B186,rep_roster!$A:$L,12,0),E186&"_"&F186) -> CSM_SMB | N186: =IFERROR(VLOOKUP(M186,plan_catalog!$A:$G,7,0),0) -> 0.06 | O186: =K186*N186 -> 300 | P186: =IFERROR(VLOOKUP(M186,plan_catalog!$A:$I,9,0),0) -> 1.05 | Q186: =IFERROR(VLOOKUP(M186,plan_catalog!$A:$J,10,0),1) -> 1.15 | R186: =IFERROR(VLOOKUP(M186,plan_catalog!$A:$K,11,0),0) -> — | S186: =IFERROR(VLOOKUP(M186,plan_catalog!$A:$L,12,0),1) -> — | T186: =IF(AND(R186>0,L186>=R186),S186,IF(AND(P186>0,L186>=P186),Q186,1)) -> 1 | U186: =O186*T186 -> 300 | V186: =I186+U186 -> 5300
A187: TOTALS | O187: =SUM(O5:O186) -> 531474 | U187: =SUM(U5:U186) -> 637943 | V187: =SUM(V5:V186) -> 1675109.7

Sheet quarterly_bonus
A1: VELTORA INC. · QUARTERLY BONUS TRACKER · FY 2025
A2: SUMPRODUCT aggregations from commission_calc | IFS bonus tier logic | Quarterly attainment true-ups
A4: Rep ID | B4: Rep Name | C4: Role | D4: Segment | E4: Q1 Actual | F4: Q1 Quota | G4: Q1 Att% | H4: Q1 Bonus ($) | I4: Q2 Actual | J4: Q2 Quota | K4: Q2 Att% | L4: Q2 Bonus ($) | M4: Q3 Actual | N4: Q3 Quota | O4: Q3 Att% | P4: Q3 Bonus ($) | Q4: Q4 Actual | R4: Q4 Quota | S4: Q4 Att% | T4: Q4 Bonus ($) | U4: Annual Bonus ($)
A5: R002 | B5: =VLOOKUP(A5,rep_roster!$A:$B,2,0) -> Marcus Williams | C5: =VLOOKUP(A5,rep_roster!$A:$C,3,0) -> SDR | D5: =VLOOKUP(A5,rep_roster!$A:$D,4,0) -> Enterprise | E5: =SUMPRODUCT((commission_calc!$B$5:$B$186=A5)*(commission_calc!$C$5:$C$186>=1)*(commission_calc!$C$5:$C$186<=3)*commission_calc!$K$5:$K$186) -> 26 | F5: =SUMPRODUCT((commission_calc!$B$5:$B$186=A5)*(commission_calc!$C$5:$C$186>=1)*(commission_calc!$C$5:$C$186<=3)*commission_calc!$J$5:$J$186) -> 24 | G5: =IF(F5>0,E5/F5,0) -> 1.0833333 | H5: =IF(G5>=1.2,3000,IF(G5>=1,1500,IF(G5>=0.8,750,0))) -> 1500 | I5: =SUMPRODUCT((commission_calc!$B$5:$B$186=A5)*(commission_calc!$C$5:$C$186>=4)*(commission_calc!$C$5:$C$186<=6)*commission_calc!$K$5:$K$186) -> 22 | J5: =SUMPRODUCT((commission_calc!$B$5:$B$186=A5)*(commission_calc!$C$5:$C$186>=4)*(commission_calc!$C$5:$C$186<=6)*commission_calc!$J$5:$J$186) -> 24 | K5: =IF(J5>0,I5/J5,0) -> 0.91666667 | L5: =IF(K5>=1.2,3000,IF(K5>=1,1500,IF(K5>=0.8,750,0))) -> 750 | M5: =SUMPRODUCT((commission_calc!$B$5:$B$186=A5)*(commission_calc!$C$5:$C$186>=7)*(commission_calc!$C$5:$C$186<=9)*commission_calc!$K$5:$K$186) -> 15 | N5: =SUMPRODUCT((commission_calc!$B$5:$B$186=A5)*(commission_calc!$C$5:$C$186>=7)*(commission_calc!$C$5:$C$186<=9)*commission_calc!$J$5:$J$186) -> 24 | O5: =IF(N5>0,M5/N5,0) -> 0.625 | P5: =IF(O5>=1.2,3000,IF(O5>=1,1500,IF(O5>=0.8,750,0))) -> 0 | Q5: =SUMPRODUCT((commission_calc!$B$5:$B$186=A5)*(commission_calc!$C$5:$C$186>=10)*(commission_calc!$C$5:$C$186<=12)*commission_calc!$K$5:$K$186) -> 18 | R5: =SUMPRODUCT((commission_calc!$B$5:$B$186=A5)*(commission_calc!$C$5:$C$186>=10)*(commission_calc!$C$5:$C$186<=12)*commission_calc!$J$5:$J$186) -> 24 | S5: =IF(R5>0,Q5/R5,0) -> 0.75 | T5: =IF(S5>=1.2,3000,IF(S5>=1,1500,IF(S5>=0.8,750,0))) -> 0 | U5: =H5+L5+P5+T5 -> 2250
A6: R003 | B6: =VLOOKUP(A6,rep_roster!$A:$B,2,0) -> James Harrington | C6: =VLOOKUP(A6,rep_roster!$A:$C,3,0) -> AE | D6: =VLOOKUP(A6,rep_roster!$A:$D,4,0) -> Enterprise | E6: =SUMPRODUCT((commission_calc!$B$5:$B$186=A6)*(commission_calc!$C$5:$C$186>=1)*(commission_calc!$C$5:$C$186<=3)*commission_calc!$K$5:$K$186) -> 288000 | F6: =SUMPRODUCT((commission_calc!$B$5:$B$186=A6)*(commission_calc!$C$5:$C$186>=1)*(commission_calc!$C$5:$C$186<=3)*commission_calc!$J$5:$J$186) -> 225000 | G6: =IF(F6>0,E6/F6,0) -> 1.28 | H6: =IF(G6>=1.2,10000,IF(G6>=1,5000,IF(G6>=0.8,2000,0))) -> 10000 | I6: =SUMPRODUCT((commission_calc!$B$5:$B$186=A6)*(commission_calc!$C$5:$C$186>=4)*(commission_calc!$C$5:$C$186<=6)*commission_calc!$K$5:$K$186) -> 247000 | J6: =SUMPRODUCT((commission_calc!$B$5:$B$186=A6)*(commission_calc!$C$5:$C$186>=4)*(commission_calc!$C$5:$C$186<=6)*commission_calc!$J$5:$J$186) -> 225000 | K6: =IF(J6>0,I6/J6,0) -> 1.0977778 | L6: =IF(K6>=1.2,10000,IF(K6>=1,5000,IF(K6>=0.8,2000,0))) -> 5000 | M6: =SUMPRODUCT((commission_calc!$B$5:$B$186=A6)*(commission_calc!$C$5:$C$186>=7)*(commission_calc!$C$5:$C$186<=9)*commission_calc!$K$5:$K$186) -> 193000 | N6: =SUMPRODUCT((commission_calc!$B$5:$B$186=A6)*(commission_calc!$C$5:$C$186>=7)*(commission_calc!$C$5:$C$186<=9)*commission_calc!$J$5:$J$186) -> 225000 | O6: =IF(N6>0,M6/N6,0) -> 0.85777778 | P6: =IF(O6>=1.2,10000,IF(O6>=1,5000,IF(O6>=0.8,2000,0))) -> 2000 | Q6: =SUMPRODUCT((commission_calc!$B$5:$B$186=A6)*(commission_calc!$C$5:$C$186>=10)*(commission_calc!$C$5:$C$186<=12)*commission_calc!$K$5:$K$186) -> 195000 | R6: =SUMPRODUCT((commission_calc!$B$5:$B$186=A6)*(commission_calc!$C$5:$C$186>=10)*(commission_calc!$C$5:$C$186<=12)*commission_calc!$J$5:$J$186) -> 225000 | S6: =IF(R6>0,Q6/R6,0) -> 0.86666667 | T6: =IF(S6>=1.2,10000,IF(S6>=1,5000,IF(S6>=0.8,2000,0))) -> 2000 | U6: =H6+L6+P6+T6 -> 19000
A7: R004 | B7: =VLOOKUP(A7,rep_roster!$A:$B,2,0) -> Olivia Brooks | C7: =VLOOKUP(A7,rep_roster!$A:$C,3,0) -> AE | D7: =VLOOKUP(A7,rep_roster!$A:$D,4,0) -> Enterprise | E7: =SUMPRODUCT((commission_calc!$B$5:$B$186=A7)*(commission_calc!$C$5:$C$186>=1)*(commission_calc!$C$5:$C$186<=3)*commission_calc!$K$5:$K$186) -> 312000 | F7: =SUMPRODUCT((commission_calc!$B$5:$B$186=A7)*(commission_calc!$C$5:$C$186>=1)*(commission_calc!$C$5:$C$186<=3)*commission_calc!$J$5:$J$186) -> 225000 | G7: =IF(F7>0,E7/F7,0) -> 1.3866667 | H7: =IF(G7>=1.2,10000,IF(G7>=1,5000,IF(G7>=0.8,2000,0))) -> 10000 | I7: =SUMPRODUCT((commission_calc!$B$5:$B$186=A7)*(commission_calc!$C$5:$C$186>=4)*(commission_calc!$C$5:$C$186<=6)*commission_calc!$K$5:$K$186) -> 265000 | J7: =SUMPRODUCT((commission_calc!$B$5:$B$186=A7)*(commission_calc!$C$5:$C$186>=4)*(commission_calc!$C$5:$C$186<=6)*commission_calc!$J$5:$J$186) -> 225000 | K7: =IF(J7>0,I7/J7,0) -> 1.1777778 | L7: =IF(K7>=1.2,10000,IF(K7>=1,5000,IF(K7>=0.8,2000,0))) -> 5000 | M7: =SUMPRODUCT((commission_calc!$B$5:$B$186=A7)*(commission_calc!$C$5:$C$186>=7)*(commission_calc!$C$5:$C$186<=9)*commission_calc!$K$5:$K$186) -> 215000 | N7: =SUMPRODUCT((commission_calc!$B$5:$B$186=A7)*(commission_calc!$C$5:$C$186>=7)*(commission_calc!$C$5:$C$186<=9)*commission_calc!$J$5:$J$186) -> 225000 | O7: =IF(N7>0,M7/N7,0) -> 0.95555556 | P7: =IF(O7>=1.2,10000,IF(O7>=1,5000,IF(O7>=0.8,2000,0))) -> 2000 | Q7: =SUMPRODUCT((commission_calc!$B$5:$B$186=A7)*(commission_calc!$C$5:$C$186>=10)*(commission_calc!$C$5:$C$186<=12)*commission_calc!$K$5:$K$186) -> 217000 | R7: =SUMPRODUCT((commission_calc!$B$5:$B$186=A7)*(commission_calc!$C$5:$C$186>=10)*(commission_calc!$C$5:$C$186<=12)*commission_calc!$J$5:$J$186) -> 225000 | S7: =IF(R7>0,Q7/R7,0) -> 0.96444444 | T7: =IF(S7>=1.2,10000,IF(S7>=1,5000,IF(S7>=0.8,2000,0))) -> 2000 | U7: =H7+L7+P7+T7 -> 19000
A8: R005 | B8: =VLOOKUP(A8,rep_roster!$A:$B,2,0) -> David Kim | C8: =VLOOKUP(A8,rep_roster!$A:$C,3,0) -> CSM | D8: =VLOOKUP(A8,rep_roster!$A:$D,4,0) -> Enterprise | E8: =SUMPRODUCT((commission_calc!$B$5:$B$186=A8)*(commission_calc!$C$5:$C$186>=1)*(commission_calc!$C$5:$C$186<=3)*commission_calc!$K$5:$K$186) -> 158000 | F8: =SUMPRODUCT((commission_calc!$B$5:$B$186=A8)*(commission_calc!$C$5:$C$186>=1)*(commission_calc!$C$5:$C$186<=3)*commission_calc!$J$5:$J$186) -> 120000 | G8: =IF(F8>0,E8/F8,0) -> 1.3166667 | H8: =IF(G8>=1.2,5000,IF(G8>=1,2500,IF(G8>=0.8,1000,0))) -> 5000 | I8: =SUMPRODUCT((commission_calc!$B$5:$B$186=A8)*(commission_calc!$C$5:$C$186>=4)*(commission_calc!$C$5:$C$186<=6)*commission_calc!$K$5:$K$186) -> 132000 | J8: =SUMPRODUCT((commission_calc!$B$5:$B$186=A8)*(commission_calc!$C$5:$C$186>=4)*(commission_calc!$C$5:$C$186<=6)*commission_calc!$J$5:$J$186) -> 120000 | K8: =IF(J8>0,I8/J8,0) -> 1.1 | L8: =IF(K8>=1.2,5000,IF(K8>=1,2500,IF(K8>=0.8,1000,0))) -> 2500 | M8: =SUMPRODUCT((commission_calc!$B$5:$B$186=A8)*(commission_calc!$C$5:$C$186>=7)*(commission_calc!$C$5:$C$186<=9)*commission_calc!$K$5:$K$186) -> 103000 | N8: =SUMPRODUCT((commission_calc!$B$5:$B$186=A8)*(commission_calc!$C$5:$C$186>=7)*(commission_calc!$C$5:$C$186<=9)*commission_calc!$J$5:$J$186) -> 120000 | O8: =IF(N8>0,M8/N8,0) -> 0.85833333 | P8: =IF(O8>=1.2,5000,IF(O8>=1,2500,IF(O8>=0.8,1000,0))) -> 1000 | Q8: =SUMPRODUCT((commission_calc!$B$5:$B$186=A8)*(commission_calc!$C$5:$C$186>=10)*(commission_calc!$C$5:$C$186<=12)*commission_calc!$K$5:$K$186) -> 0 | R8: =SUMPRODUCT((commission_calc!$B$5:$B$186=A8)*(commission_calc!$C$5:$C$186>=10)*(commission_calc!$C$5:$C$186<=12)*commission_calc!$J$5:$J$186) -> 0 | S8: =IF(R8>0,Q8/R8,0) -> 0 | T8: =IF(S8>=1.2,5000,IF(S8>=1,2500,IF(S8>=0.8,1000,0))) -> 0 | U8: =H8+L8+P8+T8 -> 8500
A9: R006 | B9: =VLOOKUP(A9,rep_roster!$A:$B,2,0) -> Lisa Park | C9: =VLOOKUP(A9,rep_roster!$A:$C,3,0) -> CSM | D9: =VLOOKUP(A9,rep_roster!$A:$D,4,0) -> Enterprise | E9: =SUMPRODUCT((commission_calc!$B$5:$B$186=A9)*(commission_calc!$C$5:$C$186>=1)*(commission_calc!$C$5:$C$186<=3)*commission_calc!$K$5:$K$186) -> 0 | F9: =SUMPRODUCT((commission_calc!$B$5:$B$186=A9)*(commission_calc!$C$5:$C$186>=1)*(commission_calc!$C$5:$C$186<=3)*commission_calc!$J$5:$J$186) -> 0 | G9: =IF(F9>0,E9/F9,0) -> 0 | H9: =IF(G9>=1.2,5000,IF(G9>=1,2500,IF(G9>=0.8,1000,0))) -> 0 | I9: =SUMPRODUCT((commission_calc!$B$5:$B$186=A9)*(commission_calc!$C$5:$C$186>=4)*(commission_calc!$C$5:$C$186<=6)*commission_calc!$K$5:$K$186) -> 0 | J9: =SUMPRODUCT((commission_calc!$B$5:$B$186=A9)*(commission_calc!$C$5:$C$186>=4)*(commission_calc!$C$5:$C$186<=6)*commission_calc!$J$5:$J$186) -> 0 | K9: =IF(J9>0,I9/J9,0) -> 0 | L9: =IF(K9>=1.2,5000,IF(K9>=1,2500,IF(K9>=0.8,1000,0))) -> 0 | M9: =SUMPRODUCT((commission_calc!$B$5:$B$186=A9)*(commission_calc!$C$5:$C$186>=7)*(commission_calc!$C$5:$C$186<=9)*commission_calc!$K$5:$K$186) -> 0 | N9: =SUMPRODUCT((commission_calc!$B$5:$B$186=A9)*(commission_calc!$C$5:$C$186>=7)*(commission_calc!$C$5:$C$186<=9)*commission_calc!$J$5:$J$186) -> 0 | O9: =IF(N9>0,M9/N9,0) -> 0 | P9: =IF(O9>=1.2,5000,IF(O9>=1,2500,IF(O9>=0.8,1000,0))) -> 0 | Q9: =SUMPRODUCT((commission_calc!$B$5:$B$186=A9)*(commission_calc!$C$5:$C$186>=10)*(commission_calc!$C$5:$C$186<=12)*commission_calc!$K$5:$K$186) -> 37000 | R9: =SUMPRODUCT((commission_calc!$B$5:$B$186=A9)*(commission_calc!$C$5:$C$186>=10)*(commission_calc!$C$5:$C$186<=12)*commission_calc!$J$5:$J$186) -> 84000 | S9: =IF(R9>0,Q9/R9,0) -> 0.44047619 | T9: =IF(S9>=1.2,5000,IF(S9>=1,2500,IF(S9>=0.8,1000,0))) -> 0 | U9: =H9+L9+P9+T9 -> 0
A10: R008 | B10: =VLOOKUP(A10,rep_roster!$A:$B,2,0) -> Kevin O'Brien | C10: =VLOOKUP(A10,rep_roster!$A:$C,3,0) -> SDR | D10: =VLOOKUP(A10,rep_roster!$A:$D,4,0) -> Mid-Market | E10: =SUMPRODUCT((commission_calc!$B$5:$B$186=A10)*(commission_calc!$C$5:$C$186>=1)*(commission_calc!$C$5:$C$186<=3)*commission_calc!$K$5:$K$186) -> 36 | F10: =SUMPRODUCT((commission_calc!$B$5:$B$186=A10)*(commission_calc!$C$5:$C$186>=1)*(commission_calc!$C$5:$C$186<=3)*commission_calc!$J$5:$J$186) -> 30 | G10: =IF(F10>0,E10/F10,0) -> 1.2 | H10: =IF(G10>=1.2,2500,IF(G10>=1,1200,IF(G10>=0.8,600,0))) -> 2500 | I10: =SUMPRODUCT((commission_calc!$B$5:$B$186=A10)*(commission_calc!$C$5:$C$186>=4)*(commission_calc!$C$5:$C$186<=6)*commission_calc!$K$5:$K$186) -> 32 | J10: =SUMPRODUCT((commission_calc!$B$5:$B$186=A10)*(commission_calc!$C$5:$C$186>=4)*(commission_calc!$C$5:$C$186<=6)*commission_calc!$J$5:$J$186) -> 30 | K10: =IF(J10>0,I10/J10,0) -> 1.0666667 | L10: =IF(K10>=1.2,2500,IF(K10>=1,1200,IF(K10>=0.8,600,0))) -> 1200 | M10: =SUMPRODUCT((commission_calc!$B$5:$B$186=A10)*(commission_calc!$C$5:$C$186>=7)*(commission_calc!$C$5:$C$186<=9)*commission_calc!$K$5:$K$186) -> 13 | N10: =SUMPRODUCT((commission_calc!$B$5:$B$186=A10)*(commission_calc!$C$5:$C$186>=7)*(commission_calc!$C$5:$C$186<=9)*commission_calc!$J$5:$J$186) -> 20 | O10: =IF(N10>0,M10/N10,0) -> 0.65 | P10: =IF(O10>=1.2,2500,IF(O10>=1,1200,IF(O10>=0.8,600,0))) -> 0 | Q10: =SUMPRODUCT((commission_calc!$B$5:$B$186=A10)*(commission_calc!$C$5:$C$186>=10)*(commission_calc!$C$5:$C$186<=12)*commission_calc!$K$5:$K$186) -> 0 | R10: =SUMPRODUCT((commission_calc!$B$5:$B$186=A10)*(commission_calc!$C$5:$C$186>=10)*(commission_calc!$C$5:$C$186<=12)*commission_calc!$J$5:$J$186) -> 0 | S10: =IF(R10>0,Q10/R10,0) -> 0 | T10: =IF(S10>=1.2,2500,IF(S10>=1,1200,IF(S10>=0.8,600,0))) -> 0 | U10: =H10+L10+P10+T10 -> 3700
A11: R009 | B11: =VLOOKUP(A11,rep_roster!$A:$B,2,0) -> Aisha Johnson | C11: =VLOOKUP(A11,rep_roster!$A:$C,3,0) -> SDR | D11: =VLOOKUP(A11,rep_roster!$A:$D,4,0) -> Mid-Market | E11: =SUMPRODUCT((commission_calc!$B$5:$B$186=A11)*(commission_calc!$C$5:$C$186>=1)*(commission_calc!$C$5:$C$186<=3)*commission_calc!$K$5:$K$186) -> 38 | F11: =SUMPRODUCT((commission_calc!$B$5:$B$186=A11)*(commission_calc!$C$5:$C$186>=1)*(commission_calc!$C$5:$C$186<=3)*commission_calc!$J$5:$J$186) -> 30 | G11: =IF(F11>0,E11/F11,0) -> 1.2666667 | H11: =IF(G11>=1.2,2500,IF(G11>=1,1200,IF(G11>=0.8,600,0))) -> 2500 | I11: =SUMPRODUCT((commission_calc!$B$5:$B$186=A11)*(commission_calc!$C$5:$C$186>=4)*(commission_calc!$C$5:$C$186<=6)*commission_calc!$K$5:$K$186) -> 34 | J11: =SUMPRODUCT((commission_calc!$B$5:$B$186=A11)*(commission_calc!$C$5:$C$186>=4)*(commission_calc!$C$5:$C$186<=6)*commission_calc!$J$5:$J$186) -> 30 | K11: =IF(J11>0,I11/J11,0) -> 1.1333333 | L11: =IF(K11>=1.2,2500,IF(K11>=1,1200,IF(K11>=0.8,600,0))) -> 1200 | M11: =SUMPRODUCT((commission_calc!$B$5:$B$186=A11)*(commission_calc!$C$5:$C$186>=7)*(commission_calc!$C$5:$C$186<=9)*commission_calc!$K$5:$K$186) -> 27 | N11: =SUMPRODUCT((commission_calc!$B$5:$B$186=A11)*(commission_calc!$C$5:$C$186>=7)*(commission_calc!$C$5:$C$186<=9)*commission_calc!$J$5:$J$186) -> 30 | O11: =IF(N11>0,M11/N11,0) -> 0.9 | P11: =IF(O11>=1.2,2500,IF(O11>=1,1200,IF(O11>=0.8,600,0))) -> 600 | Q11: =SUMPRODUCT((commission_calc!$B$5:$B$186=A11)*(commission_calc!$C$5:$C$186>=10)*(commission_calc!$C$5:$C$186<=12)*commission_calc!$K$5:$K$186) -> 29 | R11: =SUMPRODUCT((commission_calc!$B$5:$B$186=A11)*(commission_calc!$C$5:$C$186>=10)*(commission_calc!$C$5:$C$186<=12)*commission_calc!$J$5:$J$186) -> 30 | S11: =IF(R11>0,Q11/R11,0) -> 0.96666667 | T11: =IF(S11>=1.2,2500,IF(S11>=1,1200,IF(S11>=0.8,600,0))) -> 600 | U11: =H11+L11+P11+T11 -> 4900
A12: R010 | B12: =VLOOKUP(A12,rep_roster!$A:$B,2,0) -> Jessica Martinez | C12: =VLOOKUP(A12,rep_roster!$A:$C,3,0) -> SDR | D12: =VLOOKUP(A12,rep_roster!$A:$D,4,0) -> Mid-Market | E12: =SUMPRODUCT((commission_calc!$B$5:$B$186=A12)*(commission_calc!$C$5:$C$186>=1)*(commission_calc!$C$5:$C$186<=3)*commission_calc!$K$5:$K$186) -> 0 | F12: =SUMPRODUCT((commission_calc!$B$5:$B$186=A12)*(commission_calc!$C$5:$C$186>=1)*(commission_calc!$C$5:$C$186<=3)*commission_calc!$J$5:$J$186) -> 0 | G12: =IF(F12>0,E12/F12,0) -> 0 | H12: =IF(G12>=1.2,2500,IF(G12>=1,1200,IF(G12>=0.8,600,0))) -> 0 | I12: =SUMPRODUCT((commission_calc!$B$5:$B$186=A12)*(commission_calc!$C$5:$C$186>=4)*(commission_calc!$C$5:$C$186<=6)*commission_calc!$K$5:$K$186) -> 0 | J12: =SUMPRODUCT((commission_calc!$B$5:$B$186=A12)*(commission_calc!$C$5:$C$186>=4)*(commission_calc!$C$5:$C$186<=6)*commission_calc!$J$5:$J$186) -> 0 | K12: =IF(J12>0,I12/J12,0) -> 0 | L12: =IF(K12>=1.2,2500,IF(K12>=1,1200,IF(K12>=0.8,600,0))) -> 0 | M12: =SUMPRODUCT((commission_calc!$B$5:$B$186=A12)*(commission_calc!$C$5:$C$186>=7)*(commission_calc!$C$5:$C$186<=9)*commission_calc!$K$5:$K$186) -> 25 | N12: =SUMPRODUCT((commission_calc!$B$5:$B$186=A12)*(commission_calc!$C$5:$C$186>=7)*(commission_calc!$C$5:$C$186<=9)*commission_calc!$J$5:$J$186) -> 21 | O12: =IF(N12>0,M12/N12,0) -> 1.1904762 | P12: =IF(O12>=1.2,2500,IF(O12>=1,1200,IF(O12>=0.8,600,0))) -> 1200 | Q12: =SUMPRODUCT((commission_calc!$B$5:$B$186=A12)*(commission_calc!$C$5:$C$186>=10)*(commission_calc!$C$5:$C$186<=12)*commission_calc!$K$5:$K$186) -> 32 | R12: =SUMPRODUCT((commission_calc!$B$5:$B$186=A12)*(commission_calc!$C$5:$C$186>=10)*(commission_calc!$C$5:$C$186<=12)*commission_calc!$J$5:$J$186) -> 30 | S12: =IF(R12>0,Q12/R12,0) -> 1.0666667 | T12: =IF(S12>=1.2,2500,IF(S12>=1,1200,IF(S12>=0.8,600,0))) -> 1200 | U12: =H12+L12+P12+T12 -> 2400
A13: R011 | B13: =VLOOKUP(A13,rep_roster!$A:$B,2,0) -> Ryan Thompson | C13: =VLOOKUP(A13,rep_roster!$A:$C,3,0) -> AE | D13: =VLOOKUP(A13,rep_roster!$A:$D,4,0) -> Mid-Market | E13: =SUMPRODUCT((commission_calc!$B$5:$B$186=A13)*(commission_calc!$C$5:$C$186>=1)*(commission_calc!$C$5:$C$186<=3)*commission_calc!$K$5:$K$186) -> 188000 | F13: =SUMPRODUCT((commission_calc!$B$5:$B$186=A13)*(commission_calc!$C$5:$C$186>=1)*(commission_calc!$C$5:$C$186<=3)*commission_calc!$J$5:$J$186) -> 150000 | G13: =IF(F13>0,E13/F13,0) -> 1.2533333 | H13: =IF(G13>=1.2,8000,IF(G13>=1,4000,IF(G13>=0.8,1500,0))) -> 8000 | I13: =SUMPRODUCT((commission_calc!$B$5:$B$186=A13)*(commission_calc!$C$5:$C$186>=4)*(commission_calc!$C$5:$C$186<=6)*commission_calc!$K$5:$K$186) -> 163000 | J13: =SUMPRODUCT((commission_calc!$B$5:$B$186=A13)*(commission_calc!$C$5:$C$186>=4)*(commission_calc!$C$5:$C$186<=6)*commission_calc!$J$5:$J$186) -> 150000 | K13: =IF(J13>0,I13/J13,0) -> 1.0866667 | L13: =IF(K13>=1.2,8000,IF(K13>=1,4000,IF(K13>=0.8,1500,0))) -> 4000 | M13: =SUMPRODUCT((commission_calc!$B$5:$B$186=A13)*(commission_calc!$C$5:$C$186>=7)*(commission_calc!$C$5:$C$186<=9)*commission_calc!$K$5:$K$186) -> 132000 | N13: =SUMPRODUCT((commission_calc!$B$5:$B$186=A13)*(commission_calc!$C$5:$C$186>=7)*(commission_calc!$C$5:$C$186<=9)*commission_calc!$J$5:$J$186) -> 150000 | O13: =IF(N13>0,M13/N13,0) -> 0.88 | P13: =IF(O13>=1.2,8000,IF(O13>=1,4000,IF(O13>=0.8,1500,0))) -> 1500 | Q13: =SUMPRODUCT((commission_calc!$B$5:$B$186=A13)*(commission_calc!$C$5:$C$186>=10)*(commission_calc!$C$5:$C$186<=12)*commission_calc!$K$5:$K$186) -> 132000 | R13: =SUMPRODUCT((commission_calc!$B$5:$B$186=A13)*(commission_calc!$C$5:$C$186>=10)*(commission_calc!$C$5:$C$186<=12)*commission_calc!$J$5:$J$186) -> 150000 | S13: =IF(R13>0,Q13/R13,0) -> 0.88 | T13: =IF(S13>=1.2,8000,IF(S13>=1,4000,IF(S13>=0.8,1500,0))) -> 1500 | U13: =H13+L13+P13+T13 -> 15000
A14: R012 | B14: =VLOOKUP(A14,rep_roster!$A:$B,2,0) -> Samantha Lee | C14: =VLOOKUP(A14,rep_roster!$A:$C,3,0) -> AE | D14: =VLOOKUP(A14,rep_roster!$A:$D,4,0) -> Mid-Market | E14: =SUMPRODUCT((commission_calc!$B$5:$B$186=A14)*(commission_calc!$C$5:$C$186>=1)*(commission_calc!$C$5:$C$186<=3)*commission_calc!$K$5:$K$186) -> 204000 | F14: =SUMPRODUCT((commission_calc!$B$5:$B$186=A14)*(commission_calc!$C$5:$C$186>=1)*(commission_calc!$C$5:$C$186<=3)*commission_calc!$J$5:$J$186) -> 150000 | G14: =IF(F14>0,E14/F14,0) -> 1.36 | H14: =IF(G14>=1.2,8000,IF(G14>=1,4000,IF(G14>=0.8,1500,0))) -> 8000 | I14: =SUMPRODUCT((commission_calc!$B$5:$B$186=A14)*(commission_calc!$C$5:$C$186>=4)*(commission_calc!$C$5:$C$186<=6)*commission_calc!$K$5:$K$186) -> 175000 | J14: =SUMPRODUCT((commission_calc!$B$5:$B$186=A14)*(commission_calc!$C$5:$C$186>=4)*(commission_calc!$C$5:$C$186<=6)*commission_calc!$J$5:$J$186) -> 150000 | K14: =IF(J14>0,I14/J14,0) -> 1.1666667 | L14: =IF(K14>=1.2,8000,IF(K14>=1,4000,IF(K14>=0.8,1500,0))) -> 4000 | M14: =SUMPRODUCT((commission_calc!$B$5:$B$186=A14)*(commission_calc!$C$5:$C$186>=7)*(commission_calc!$C$5:$C$186<=9)*commission_calc!$K$5:$K$186) -> 137000 | N14: =SUMPRODUCT((commission_calc!$B$5:$B$186=A14)*(commission_calc!$C$5:$C$186>=7)*(commission_calc!$C$5:$C$186<=9)*commission_calc!$J$5:$J$186) -> 150000 | O14: =IF(N14>0,M14/N14,0) -> 0.91333333 | P14: =IF(O14>=1.2,8000,IF(O14>=1,4000,IF(O14>=0.8,1500,0))) -> 1500 | Q14: =SUMPRODUCT((commission_calc!$B$5:$B$186=A14)*(commission_calc!$C$5:$C$186>=10)*(commission_calc!$C$5:$C$186<=12)*commission_calc!$K$5:$K$186) -> 143000 | R14: =SUMPRODUCT((commission_calc!$B$5:$B$186=A14)*(commission_calc!$C$5:$C$186>=10)*(commission_calc!$C$5:$C$186<=12)*commission_calc!$J$5:$J$186) -> 150000 | S14: =IF(R14>0,Q14/R14,0) -> 0.95333333 | T14: =IF(S14>=1.2,8000,IF(S14>=1,4000,IF(S14>=0.8,1500,0))) -> 1500 | U14: =H14+L14+P14+T14 -> 15000
A15: R013 | B15: =VLOOKUP(A15,rep_roster!$A:$B,2,0) -> Daniel Foster | C15: =VLOOKUP(A15,rep_roster!$A:$C,3,0) -> CSM | D15: =VLOOKUP(A15,rep_roster!$A:$D,4,0) -> Mid-Market | E15: =SUMPRODUCT((commission_calc!$B$5:$B$186=A15)*(commission_calc!$C$5:$C$186>=1)*(commission_calc!$C$5:$C$186<=3)*commission_calc!$K$5:$K$186) -> 60000 | F15: =SUMPRODUCT((commission_calc!$B$5:$B$186=A15)*(commission_calc!$C$5:$C$186>=1)*(commission_calc!$C$5:$C$186<=3)*commission_calc!$J$5:$J$186) -> 45000 | G15: =IF(F15>0,E15/F15,0) -> 1.3333333 | H15: =IF(G15>=1.2,4000,IF(G15>=1,2000,IF(G15>=0.8,750,0))) -> 4000 | I15: =SUMPRODUCT((commission_calc!$B$5:$B$186=A15)*(commission_calc!$C$5:$C$186>=4)*(commission_calc!$C$5:$C$186<=6)*commission_calc!$K$5:$K$186) -> 51000 | J15: =SUMPRODUCT((commission_calc!$B$5:$B$186=A15)*(commission_calc!$C$5:$C$186>=4)*(commission_calc!$C$5:$C$186<=6)*commission_calc!$J$5:$J$186) -> 45000 | K15: =IF(J15>0,I15/J15,0) -> 1.1333333 | L15: =IF(K15>=1.2,4000,IF(K15>=1,2000,IF(K15>=0.8,750,0))) -> 2000 | M15: =SUMPRODUCT((commission_calc!$B$5:$B$186=A15)*(commission_calc!$C$5:$C$186>=7)*(commission_calc!$C$5:$C$186<=9)*commission_calc!$K$5:$K$186) -> 38000 | N15: =SUMPRODUCT((commission_calc!$B$5:$B$186=A15)*(commission_calc!$C$5:$C$186>=7)*(commission_calc!$C$5:$C$186<=9)*commission_calc!$J$5:$J$186) -> 45000 | O15: =IF(N15>0,M15/N15,0) -> 0.84444444 | P15: =IF(O15>=1.2,4000,IF(O15>=1,2000,IF(O15>=0.8,750,0))) -> 750 | Q15: =SUMPRODUCT((commission_calc!$B$5:$B$186=A15)*(commission_calc!$C$5:$C$186>=10)*(commission_calc!$C$5:$C$186<=12)*commission_calc!$K$5:$K$186) -> 37000 | R15: =SUMPRODUCT((commission_calc!$B$5:$B$186=A15)*(commission_calc!$C$5:$C$186>=10)*(commission_calc!$C$5:$C$186<=12)*commission_calc!$J$5:$J$186) -> 45000 | S15: =IF(R15>0,Q15/R15,0) -> 0.82222222 | T15: =IF(S15>=1.2,4000,IF(S15>=1,2000,IF(S15>=0.8,750,0))) -> 750 | U15: =H15+L15+P15+T15 -> 7500
A16: R014 | B16: =VLOOKUP(A16,rep_roster!$A:$B,2,0) -> Rachel Green | C16: =VLOOKUP(A16,rep_roster!$A:$C,3,0) -> CSM | D16: =VLOOKUP(A16,rep_roster!$A:$D,4,0) -> Mid-Market | E16: =SUMPRODUCT((commission_calc!$B$5:$B$186=A16)*(commission_calc!$C$5:$C$186>=1)*(commission_calc!$C$5:$C$186<=3)*commission_calc!$K$5:$K$186) -> 66000 | F16: =SUMPRODUCT((commission_calc!$B$5:$B$186=A16)*(commission_calc!$C$5:$C$186>=1)*(commission_calc!$C$5:$C$186<=3)*commission_calc!$J$5:$J$186) -> 45000 | G16: =IF(F16>0,E16/F16,0) -> 1.4666667 | H16: =IF(G16>=1.2,4000,IF(G16>=1,2000,IF(G16>=0.8,750,0))) -> 4000 | I16: =SUMPRODUCT((commission_calc!$B$5:$B$186=A16)*(commission_calc!$C$5:$C$186>=4)*(commission_calc!$C$5:$C$186<=6)*commission_calc!$K$5:$K$186) -> 54000 | J16: =SUMPRODUCT((commission_calc!$B$5:$B$186=A16)*(commission_calc!$C$5:$C$186>=4)*(commission_calc!$C$5:$C$186<=6)*commission_calc!$J$5:$J$186) -> 45000 | K16: =IF(J16>0,I16/J16,0) -> 1.2 | L16: =IF(K16>=1.2,4000,IF(K16>=1,2000,IF(K16>=0.8,750,0))) -> 4000 | M16: =SUMPRODUCT((commission_calc!$B$5:$B$186=A16)*(commission_calc!$C$5:$C$186>=7)*(commission_calc!$C$5:$C$186<=9)*commission_calc!$K$5:$K$186) -> 42000 | N16: =SUMPRODUCT((commission_calc!$B$5:$B$186=A16)*(commission_calc!$C$5:$C$186>=7)*(commission_calc!$C$5:$C$186<=9)*commission_calc!$J$5:$J$186) -> 45000 | O16: =IF(N16>0,M16/N16,0) -> 0.93333333 | P16: =IF(O16>=1.2,4000,IF(O16>=1,2000,IF(O16>=0.8,750,0))) -> 750 | Q16: =SUMPRODUCT((commission_calc!$B$5:$B$186=A16)*(commission_calc!$C$5:$C$186>=10)*(commission_calc!$C$5:$C$186<=12)*commission_calc!$K$5:$K$186) -> 44000 | R16: =SUMPRODUCT((commission_calc!$B$5:$B$186=A16)*(commission_calc!$C$5:$C$186>=10)*(commission_calc!$C$5:$C$186<=12)*commission_calc!$J$5:$J$186) -> 45000 | S16: =IF(R16>0,Q16/R16,0) -> 0.97777778 | T16: =IF(S16>=1.2,4000,IF(S16>=1,2000,IF(S16>=0.8,750,0))) -> 750 | U16: =H16+L16+P16+T16 -> 9500
A17: R016 | B17: =VLOOKUP(A17,rep_roster!$A:$B,2,0) -> Nina Patel | C17: =VLOOKUP(A17,rep_roster!$A:$C,3,0) -> SDR | D17: =VLOOKUP(A17,rep_roster!$A:$D,4,0) -> SMB | E17: =SUMPRODUCT((commission_calc!$B$5:$B$186=A17)*(commission_calc!$C$5:$C$186>=1)*(commission_calc!$C$5:$C$186<=3)*commission_calc!$K$5:$K$186) -> 59 | F17: =SUMPRODUCT((commission_calc!$B$5:$B$186=A17)*(commission_calc!$C$5:$C$186>=1)*(commission_calc!$C$5:$C$186<=3)*commission_calc!$J$5:$J$186) -> 48 | G17: =IF(F17>0,E17/F17,0) -> 1.2291667 | H17: =IF(G17>=1.2,2000,IF(G17>=1,1000,IF(G17>=0.8,500,0))) -> 2000 | I17: =SUMPRODUCT((commission_calc!$B$5:$B$186=A17)*(commission_calc!$C$5:$C$186>=4)*(commission_calc!$C$5:$C$186<=6)*commission_calc!$K$5:$K$186) -> 51 | J17: =SUMPRODUCT((commission_calc!$B$5:$B$186=A17)*(commission_calc!$C$5:$C$186>=4)*(commission_calc!$C$5:$C$186<=6)*commission_calc!$J$5:$J$186) -> 48 | K17: =IF(J17>0,I17/J17,0) -> 1.0625 | L17: =IF(K17>=1.2,2000,IF(K17>=1,1000,IF(K17>=0.8,500,0))) -> 1000 | M17: =SUMPRODUCT((commission_calc!$B$5:$B$186=A17)*(commission_calc!$C$5:$C$186>=7)*(commission_calc!$C$5:$C$186<=9)*commission_calc!$K$5:$K$186) -> 40 | N17: =SUMPRODUCT((commission_calc!$B$5:$B$186=A17)*(commission_calc!$C$5:$C$186>=7)*(commission_calc!$C$5:$C$186<=9)*commission_calc!$J$5:$J$186) -> 48 | O17: =IF(N17>0,M17/N17,0) -> 0.83333333 | P17: =IF(O17>=1.2,2000,IF(O17>=1,1000,IF(O17>=0.8,500,0))) -> 500 | Q17: =SUMPRODUCT((commission_calc!$B$5:$B$186=A17)*(commission_calc!$C$5:$C$186>=10)*(commission_calc!$C$5:$C$186<=12)*commission_calc!$K$5:$K$186) -> 44 | R17: =SUMPRODUCT((commission_calc!$B$5:$B$186=A17)*(commission_calc!$C$5:$C$186>=10)*(commission_calc!$C$5:$C$186<=12)*commission_calc!$J$5:$J$186) -> 48 | S17: =IF(R17>0,Q17/R17,0) -> 0.91666667 | T17: =IF(S17>=1.2,2000,IF(S17>=1,1000,IF(S17>=0.8,500,0))) -> 500 | U17: =H17+L17+P17+T17 -> 4000
A18: R017 | B18: =VLOOKUP(A18,rep_roster!$A:$B,2,0) -> Derek Washington | C18: =VLOOKUP(A18,rep_roster!$A:$C,3,0) -> SDR | D18: =VLOOKUP(A18,rep_roster!$A:$D,4,0) -> SMB | E18: =SUMPRODUCT((commission_calc!$B$5:$B$186=A18)*(commission_calc!$C$5:$C$186>=1)*(commission_calc!$C$5:$C$186<=3)*commission_calc!$K$5:$K$186) -> 54 | F18: =SUMPRODUCT((commission_calc!$B$5:$B$186=A18)*(commission_calc!$C$5:$C$186>=1)*(commission_calc!$C$5:$C$186<=3)*commission_calc!$J$5:$J$186) -> 48 | G18: =IF(F18>0,E18/F18,0) -> 1.125 | H18: =IF(G18>=1.2,2000,IF(G18>=1,1000,IF(G18>=0.8,500,0))) -> 1000 | I18: =SUMPRODUCT((commission_calc!$B$5:$B$186=A18)*(commission_calc!$C$5:$C$186>=4)*(commission_calc!$C$5:$C$186<=6)*commission_calc!$K$5:$K$186) -> 48 | J18: =SUMPRODUCT((commission_calc!$B$5:$B$186=A18)*(commission_calc!$C$5:$C$186>=4)*(commission_calc!$C$5:$C$186<=6)*commission_calc!$J$5:$J$186) -> 48 | K18: =IF(J18>0,I18/J18,0) -> 1 | L18: =IF(K18>=1.2,2000,IF(K18>=1,1000,IF(K18>=0.8,500,0))) -> 1000 | M18: =SUMPRODUCT((commission_calc!$B$5:$B$186=A18)*(commission_calc!$C$5:$C$186>=7)*(commission_calc!$C$5:$C$186<=9)*commission_calc!$K$5:$K$186) -> 39 | N18: =SUMPRODUCT((commission_calc!$B$5:$B$186=A18)*(commission_calc!$C$5:$C$186>=7)*(commission_calc!$C$5:$C$186<=9)*commission_calc!$J$5:$J$186) -> 48 | O18: =IF(N18>0,M18/N18,0) -> 0.8125 | P18: =IF(O18>=1.2,2000,IF(O18>=1,1000,IF(O18>=0.8,500,0))) -> 500 | Q18: =SUMPRODUCT((commission_calc!$B$5:$B$186=A18)*(commission_calc!$C$5:$C$186>=10)*(commission_calc!$C$5:$C$186<=12)*commission_calc!$K$5:$K$186) -> 42 | R18: =SUMPRODUCT((commission_calc!$B$5:$B$186=A18)*(commission_calc!$C$5:$C$186>=10)*(commission_calc!$C$5:$C$186<=12)*commission_calc!$J$5:$J$186) -> 48 | S18: =IF(R18>0,Q18/R18,0) -> 0.875 | T18: =IF(S18>=1.2,2000,IF(S18>=1,1000,IF(S18>=0.8,500,0))) -> 500 | U18: =H18+L18+P18+T18 -> 3000
A19: R018 | B19: =VLOOKUP(A19,rep_roster!$A:$B,2,0) -> Brandon Cole | C19: =VLOOKUP(A19,rep_roster!$A:$C,3,0) -> AE | D19: =VLOOKUP(A19,rep_roster!$A:$D,4,0) -> SMB | E19: =SUMPRODUCT((commission_calc!$B$5:$B$186=A19)*(commission_calc!$C$5:$C$186>=1)*(commission_calc!$C$5:$C$186<=3)*commission_calc!$K$5:$K$186) -> 53000 | F19: =SUMPRODUCT((commission_calc!$B$5:$B$186=A19)*(commission_calc!$C$5:$C$186>=1)*(commission_calc!$C$5:$C$186<=3)*commission_calc!$J$5:$J$186) -> 75000 | G19: =IF(F19>0,E19/F19,0) -> 0.70666667 | H19: =IF(G19>=1.2,5000,IF(G19>=1,3000,IF(G19>=0.8,1000,0))) -> 0 | I19: =SUMPRODUCT((commission_calc!$B$5:$B$186=A19)*(commission_calc!$C$5:$C$186>=4)*(commission_calc!$C$5:$C$186<=6)*commission_calc!$K$5:$K$186) -> 46000 | J19: =SUMPRODUCT((commission_calc!$B$5:$B$186=A19)*(commission_calc!$C$5:$C$186>=4)*(commission_calc!$C$5:$C$186<=6)*commission_calc!$J$5:$J$186) -> 75000 | K19: =IF(J19>0,I19/J19,0) -> 0.61333333 | L19: =IF(K19>=1.2,5000,IF(K19>=1,3000,IF(K19>=0.8,1000,0))) -> 0 | M19: =SUMPRODUCT((commission_calc!$B$5:$B$186=A19)*(commission_calc!$C$5:$C$186>=7)*(commission_calc!$C$5:$C$186<=9)*commission_calc!$K$5:$K$186) -> 0 | N19: =SUMPRODUCT((commission_calc!$B$5:$B$186=A19)*(commission_calc!$C$5:$C$186>=7)*(commission_calc!$C$5:$C$186<=9)*commission_calc!$J$5:$J$186) -> 0 | O19: =IF(N19>0,M19/N19,0) -> 0 | P19: =IF(O19>=1.2,5000,IF(O19>=1,3000,IF(O19>=0.8,1000,0))) -> 0 | Q19: =SUMPRODUCT((commission_calc!$B$5:$B$186=A19)*(commission_calc!$C$5:$C$186>=10)*(commission_calc!$C$5:$C$186<=12)*commission_calc!$K$5:$K$186) -> 0 | R19: =SUMPRODUCT((commission_calc!$B$5:$B$186=A19)*(commission_calc!$C$5:$C$186>=10)*(commission_calc!$C$5:$C$186<=12)*commission_calc!$J$5:$J$186) -> 0 | S19: =IF(R19>0,Q19/R19,0) -> 0 | T19: =IF(S19>=1.2,5000,IF(S19>=1,3000,IF(S19>=0.8,1000,0))) -> 0 | U19: =H19+L19+P19+T19 -> 0
A20: R019 | B20: =VLOOKUP(A20,rep_roster!$A:$B,2,0) -> Stephanie Kim | C20: =VLOOKUP(A20,rep_roster!$A:$C,3,0) -> AE | D20: =VLOOKUP(A20,rep_roster!$A:$D,4,0) -> SMB | E20: =SUMPRODUCT((commission_calc!$B$5:$B$186=A20)*(commission_calc!$C$5:$C$186>=1)*(commission_calc!$C$5:$C$186<=3)*commission_calc!$K$5:$K$186) -> 0 | F20: =SUMPRODUCT((commission_calc!$B$5:$B$186=A20)*(commission_calc!$C$5:$C$186>=1)*(commission_calc!$C$5:$C$186<=3)*commission_calc!$J$5:$J$186) -> 0 | G20: =IF(F20>0,E20/F20,0) -> 0 | H20: =IF(G20>=1.2,5000,IF(G20>=1,3000,IF(G20>=0.8,1000,0))) -> 0 | I20: =SUMPRODUCT((commission_calc!$B$5:$B$186=A20)*(commission_calc!$C$5:$C$186>=4)*(commission_calc!$C$5:$C$186<=6)*commission_calc!$K$5:$K$186) -> 0 | J20: =SUMPRODUCT((commission_calc!$B$5:$B$186=A20)*(commission_calc!$C$5:$C$186>=4)*(commission_calc!$C$5:$C$186<=6)*commission_calc!$J$5:$J$186) -> 0 | K20: =IF(J20>0,I20/J20,0) -> 0 | L20: =IF(K20>=1.2,5000,IF(K20>=1,3000,IF(K20>=0.8,1000,0))) -> 0 | M20: =SUMPRODUCT((commission_calc!$B$5:$B$186=A20)*(commission_calc!$C$5:$C$186>=7)*(commission_calc!$C$5:$C$186<=9)*commission_calc!$K$5:$K$186) -> 52000 | N20: =SUMPRODUCT((commission_calc!$B$5:$B$186=A20)*(commission_calc!$C$5:$C$186>=7)*(commission_calc!$C$5:$C$186<=9)*commission_calc!$J$5:$J$186) -> 52500 | O20: =IF(N20>0,M20/N20,0) -> 0.99047619 | P20: =IF(O20>=1.2,5000,IF(O20>=1,3000,IF(O20>=0.8,1000,0))) -> 1000 | Q20: =SUMPRODUCT((commission_calc!$B$5:$B$186=A20)*(commission_calc!$C$5:$C$186>=10)*(commission_calc!$C$5:$C$186<=12)*commission_calc!$K$5:$K$186) -> 71000 | R20: =SUMPRODUCT((commission_calc!$B$5:$B$186=A20)*(commission_calc!$C$5:$C$186>=10)*(commission_calc!$C$5:$C$186<=12)*commission_calc!$J$5:$J$186) -> 75000 | S20: =IF(R20>0,Q20/R20,0) -> 0.94666667 | T20: =IF(S20>=1.2,5000,IF(S20>=1,3000,IF(S20>=0.8,1000,0))) -> 1000 | U20: =H20+L20+P20+T20 -> 2000
A21: R020 | B21: =VLOOKUP(A21,rep_roster!$A:$B,2,0) -> Amy Chen | C21: =VLOOKUP(A21,rep_roster!$A:$C,3,0) -> AE | D21: =VLOOKUP(A21,rep_roster!$A:$D,4,0) -> SMB | E21: =SUMPRODUCT((commission_calc!$B$5:$B$186=A21)*(commission_calc!$C$5:$C$186>=1)*(commission_calc!$C$5:$C$186<=3)*commission_calc!$K$5:$K$186) -> 96000 | F21: =SUMPRODUCT((commission_calc!$B$5:$B$186=A21)*(commission_calc!$C$5:$C$186>=1)*(commission_calc!$C$5:$C$186<=3)*commission_calc!$J$5:$J$186) -> 75000 | G21: =IF(F21>0,E21/F21,0) -> 1.28 | H21: =IF(G21>=1.2,5000,IF(G21>=1,3000,IF(G21>=0.8,1000,0))) -> 5000 | I21: =SUMPRODUCT((commission_calc!$B$5:$B$186=A21)*(commission_calc!$C$5:$C$186>=4)*(commission_calc!$C$5:$C$186<=6)*commission_calc!$K$5:$K$186) -> 85000 | J21: =SUMPRODUCT((commission_calc!$B$5:$B$186=A21)*(commission_calc!$C$5:$C$186>=4)*(commission_calc!$C$5:$C$186<=6)*commission_calc!$J$5:$J$186) -> 75000 | K21: =IF(J21>0,I21/J21,0) -> 1.1333333 | L21: =IF(K21>=1.2,5000,IF(K21>=1,3000,IF(K21>=0.8,1000,0))) -> 3000 | M21: =SUMPRODUCT((commission_calc!$B$5:$B$186=A21)*(commission_calc!$C$5:$C$186>=7)*(commission_calc!$C$5:$C$186<=9)*commission_calc!$K$5:$K$186) -> 67000 | N21: =SUMPRODUCT((commission_calc!$B$5:$B$186=A21)*(commission_calc!$C$5:$C$186>=7)*(commission_calc!$C$5:$C$186<=9)*commission_calc!$J$5:$J$186) -> 75000 | O21: =IF(N21>0,M21/N21,0) -> 0.89333333 | P21: =IF(O21>=1.2,5000,IF(O21>=1,3000,IF(O21>=0.8,1000,0))) -> 1000 | Q21: =SUMPRODUCT((commission_calc!$B$5:$B$186=A21)*(commission_calc!$C$5:$C$186>=10)*(commission_calc!$C$5:$C$186<=12)*commission_calc!$K$5:$K$186) -> 69000 | R21: =SUMPRODUCT((commission_calc!$B$5:$B$186=A21)*(commission_calc!$C$5:$C$186>=10)*(commission_calc!$C$5:$C$186<=12)*commission_calc!$J$5:$J$186) -> 75000 | S21: =IF(R21>0,Q21/R21,0) -> 0.92 | T21: =IF(S21>=1.2,5000,IF(S21>=1,3000,IF(S21>=0.8,1000,0))) -> 1000 | U21: =H21+L21+P21+T21 -> 10000
A22: R021 | B22: =VLOOKUP(A22,rep_roster!$A:$B,2,0) -> Jennifer Walsh | C22: =VLOOKUP(A22,rep_roster!$A:$C,3,0) -> CSM | D22: =VLOOKUP(A22,rep_roster!$A:$D,4,0) -> SMB | E22: =SUMPRODUCT((commission_calc!$B$5:$B$186=A22)*(commission_calc!$C$5:$C$186>=1)*(commission_calc!$C$5:$C$186<=3)*commission_calc!$K$5:$K$186) -> 21000 | F22: =SUMPRODUCT((commission_calc!$B$5:$B$186=A22)*(commission_calc!$C$5:$C$186>=1)*(commission_calc!$C$5:$C$186<=3)*commission_calc!$J$5:$J$186) -> 15000 | G22: =IF(F22>0,E22/F22,0) -> 1.4 | H22: =IF(G22>=1.2,3000,IF(G22>=1,1500,IF(G22>=0.8,500,0))) -> 3000 | I22: =SUMPRODUCT((commission_calc!$B$5:$B$186=A22)*(commission_calc!$C$5:$C$186>=4)*(commission_calc!$C$5:$C$186<=6)*commission_calc!$K$5:$K$186) -> 17500 | J22: =SUMPRODUCT((commission_calc!$B$5:$B$186=A22)*(commission_calc!$C$5:$C$186>=4)*(commission_calc!$C$5:$C$186<=6)*commission_calc!$J$5:$J$186) -> 15000 | K22: =IF(J22>0,I22/J22,0) -> 1.1666667 | L22: =IF(K22>=1.2,3000,IF(K22>=1,1500,IF(K22>=0.8,500,0))) -> 1500 | M22: =SUMPRODUCT((commission_calc!$B$5:$B$186=A22)*(commission_calc!$C$5:$C$186>=7)*(commission_calc!$C$5:$C$186<=9)*commission_calc!$K$5:$K$186) -> 13000 | N22: =SUMPRODUCT((commission_calc!$B$5:$B$186=A22)*(commission_calc!$C$5:$C$186>=7)*(commission_calc!$C$5:$C$186<=9)*commission_calc!$J$5:$J$186) -> 15000 | O22: =IF(N22>0,M22/N22,0) -> 0.86666667 | P22: =IF(O22>=1.2,3000,IF(O22>=1,1500,IF(O22>=0.8,500,0))) -> 500 | Q22: =SUMPRODUCT((commission_calc!$B$5:$B$186=A22)*(commission_calc!$C$5:$C$186>=10)*(commission_calc!$C$5:$C$186<=12)*commission_calc!$K$5:$K$186) -> 12500 | R22: =SUMPRODUCT((commission_calc!$B$5:$B$186=A22)*(commission_calc!$C$5:$C$186>=10)*(commission_calc!$C$5:$C$186<=12)*commission_calc!$J$5:$J$186) -> 15000 | S22: =IF(R22>0,Q22/R22,0) -> 0.83333333 | T22: =IF(S22>=1.2,3000,IF(S22>=1,1500,IF(S22>=0.8,500,0))) -> 500 | U22: =H22+L22+P22+T22 -> 5500
A23: TOTALS | E23: =SUM(E5:E22) -> 1446213 | F23: =SUM(F5:F22) -> 1125180 | H23: =SUM(H5:H22) -> 66500 | I23: =SUM(I5:I22) -> 1235687 | J23: =SUM(J5:J22) -> 1125180 | L23: =SUM(L5:L22) -> 36150 | M23: =SUM(M5:M22) -> 992159 | N23: =SUM(N5:N22) -> 1102691 | P23: =SUM(P5:P22) -> 14800 | Q23: =SUM(Q5:Q22) -> 957665 | R23: =SUM(R5:R22) -> 1089180 | S23: - | T23: =SUM(T5:T22) -> 13800 | U23: =SUM(U5:U22) -> 131250

Sheet team_rollup
A1: VELTORA INC. · TEAM & SEGMENT ROLLUP · FY 2025
A2: SUMPRODUCT aggregations by segment and role | Manager overrides | Budget vs. actual comp cost
A4: ANNUAL PERFORMANCE SUMMARY BY SEGMENT (AEs only — ARR Closed)
A5: Segment | B5: Annual Quota ($) | C5: Annual Actual ($) | D5: Org Attainment % | E5: # Reps | F5: Avg Attainment % | G5: Top Rep Attainment | H5: Accel Events | I5: Budget Variance Note
A6: Enterprise | B6: 1800000 | C6: =SUMPRODUCT((commission_calc!$F$5:$F$186="Enterprise")*(commission_calc!$E$5:$E$186="AE")*commission_calc!$K$5:$K$186) -> 1932000 | D6: =IF(B6>0,C6/B6,0) -> 1.0733333 | E6: 2
A7: Mid-Market | B7: 1200000 | C7: =SUMPRODUCT((commission_calc!$F$5:$F$186="Mid-Market")*(commission_calc!$E$5:$E$186="AE")*commission_calc!$K$5:$K$186) -> 1274000 | D7: =IF(B7>0,C7/B7,0) -> 1.0616667 | E7: 2
A8: SMB | B8: 900000 | C8: =SUMPRODUCT((commission_calc!$F$5:$F$186="SMB")*(commission_calc!$E$5:$E$186="AE")*commission_calc!$K$5:$K$186) -> 539000 | D8: =IF(B8>0,C8/B8,0) -> 0.59888889 | E8: 3
A10: ANNUAL COMP COST BY ROLE & SEGMENT (SUMPRODUCT)
A11: Role | B11: Segment | C11: Total Base Cost ($) | D11: Total Variable Paid ($) | E11: Total Bonus ($) | F11: Total Comp Cost ($) | G11: Headcount | H11: Cost per Rep ($)
A12: SDR | B12: Enterprise | C12: =SUMPRODUCT((commission_calc!$E$5:$E$186="SDR")*(commission_calc!$F$5:$F$186="Enterprise")*commission_calc!$I$5:$I$186) -> 62000 | D12: =SUMPRODUCT((commission_calc!$E$5:$E$186="SDR")*(commission_calc!$F$5:$F$186="Enterprise")*commission_calc!$U$5:$U$186) -> 26700.3 | E12: =SUMPRODUCT((quarterly_bonus!$C$5:$C$22="SDR")*(quarterly_bonus!$D$5:$D$22="Enterprise")*(quarterly_bonus!$H$5:$H$22+quarterly_bonus!$L$5:$L$22+quarterly_bonus!$P$5:$P$22)) -> 2250 | F12: =C12+D12+E12 -> 90950.3 | G12: 1 | H12: =IF(G12>0,F12/G12,0) -> 90950.3
A13: SDR | B13: Mid-Market | C13: =SUMPRODUCT((commission_calc!$E$5:$E$186="SDR")*(commission_calc!$F$5:$F$186="Mid-Market")*commission_calc!$I$5:$I$186) -> 119166.67 | D13: =SUMPRODUCT((commission_calc!$E$5:$E$186="SDR")*(commission_calc!$F$5:$F$186="Mid-Market")*commission_calc!$U$5:$U$186) -> 52271 | E13: =SUMPRODUCT((quarterly_bonus!$C$5:$C$22="SDR")*(quarterly_bonus!$D$5:$D$22="Mid-Market")*(quarterly_bonus!$H$5:$H$22+quarterly_bonus!$L$5:$L$22+quarterly_bonus!$P$5:$P$22)) -> 9200 | F13: =C13+D13+E13 -> 180637.67 | G13: 2 | H13: =IF(G13>0,F13/G13,0) -> 90318.833
A14: SDR | B14: SMB | C14: {=SUMPRODUCT((commission_calc!$E$5:$E$186="SDR")*(commission_calc!$F$5:$F$186="SMB")*commission_calc!$I$5:$I$186)} -> 96000 | D14: =SUMPRODUCT((commission_calc!$E$5:$E$186="SDR")*(commission_calc!$F$5:$F$186="SMB")*commission_calc!$U$5:$U$186) -> 35582.2 | E14: =SUMPRODUCT((quarterly_bonus!$C$5:$C$22="SDR")*(quarterly_bonus!$D$5:$D$22="SMB")*(quarterly_bonus!$H$5:$H$22+quarterly_bonus!$L$5:$L$22+quarterly_bonus!$P$5:$P$22)) -> 6000 | F14: =C14+D14+E14 -> 137582.2 | G14: 2 | H14: =IF(G14>0,F14/G14,0) -> 68791.1
A15: AE | B15: Enterprise | C15: =SUMPRODUCT((commission_calc!$E$5:$E$186="AE")*(commission_calc!$F$5:$F$186="Enterprise")*commission_calc!$I$5:$I$186) -> 190000 | D15: =SUMPRODUCT((commission_calc!$E$5:$E$186="AE")*(commission_calc!$F$5:$F$186="Enterprise")*commission_calc!$U$5:$U$186) -> 242125 | E15: =SUMPRODUCT((quarterly_bonus!$C$5:$C$22="AE")*(quarterly_bonus!$D$5:$D$22="Enterprise")*(quarterly_bonus!$H$5:$H$22+quarterly_bonus!$L$5:$L$22+quarterly_bonus!$P$5:$P$22)) -> 34000 | F15: =C15+D15+E15 -> 466125 | G15: 2 | H15: =IF(G15>0,F15/G15,0) -> 233062.5
A16: AE | B16: Mid-Market | C16: =SUMPRODUCT((commission_calc!$E$5:$E$186="AE")*(commission_calc!$F$5:$F$186="Mid-Market")*commission_calc!$I$5:$I$186) -> 160000 | D16: =SUMPRODUCT((commission_calc!$E$5:$E$186="AE")*(commission_calc!$F$5:$F$186="Mid-Market")*commission_calc!$U$5:$U$186) -> 159550 | E16: =SUMPRODUCT((quarterly_bonus!$C$5:$C$22="AE")*(quarterly_bonus!$D$5:$D$22="Mid-Market")*(quarterly_bonus!$H$5:$H$22+quarterly_bonus!$L$5:$L$22+quarterly_bonus!$P$5:$P$22)) -> 27000 | F16: =C16+D16+E16 -> 346550 | G16: 2 | H16: =IF(G16>0,F16/G16,0) -> 173275
A17: AE | B17: SMB | C17: =SUMPRODUCT((commission_calc!$E$5:$E$186="AE")*(commission_calc!$F$5:$F$186="SMB")*commission_calc!$I$5:$I$186) -> 130000 | D17: =SUMPRODUCT((commission_calc!$E$5:$E$186="AE")*(commission_calc!$F$5:$F$186="SMB")*commission_calc!$U$5:$U$186) -> 61740 | E17: =SUMPRODUCT((quarterly_bonus!$C$5:$C$22="AE")*(quarterly_bonus!$D$5:$D$22="SMB")*(quarterly_bonus!$H$5:$H$22+quarterly_bonus!$L$5:$L$22+quarterly_bonus!$P$5:$P$22)) -> 10000 | F17: =C17+D17+E17 -> 201740 | G17: 3 | H17: =IF(G17>0,F17/G17,0) -> 67246.667
A18: CSM | B18: Enterprise | C18: =SUMPRODUCT((commission_calc!$E$5:$E$186="CSM")*(commission_calc!$F$5:$F$186="Enterprise")*commission_calc!$I$5:$I$186) -> 80000 | D18: =SUMPRODUCT((commission_calc!$E$5:$E$186="CSM")*(commission_calc!$F$5:$F$186="Enterprise")*commission_calc!$U$5:$U$186) -> 29280 | E18: =SUMPRODUCT((quarterly_bonus!$C$5:$C$22="CSM")*(quarterly_bonus!$D$5:$D$22="Enterprise")*(quarterly_bonus!$H$5:$H$22+quarterly_bonus!$L$5:$L$22+quarterly_bonus!$P$5:$P$22)) -> 8500 | F18: =C18+D18+E18 -> 117780 | G18: 2 | H18: =IF(G18>0,F18/G18,0) -> 58890
A19: CSM | B19: Mid-Market | C19: =SUMPRODUCT((commission_calc!$E$5:$E$186="CSM")*(commission_calc!$F$5:$F$186="Mid-Market")*commission_calc!$I$5:$I$186) -> 140000 | D19: =SUMPRODUCT((commission_calc!$E$5:$E$186="CSM")*(commission_calc!$F$5:$F$186="Mid-Market")*commission_calc!$U$5:$U$186) -> 26508 | E19: =SUMPRODUCT((quarterly_bonus!$C$5:$C$22="CSM")*(quarterly_bonus!$D$5:$D$22="Mid-Market")*(quarterly_bonus!$H$5:$H$22+quarterly_bonus!$L$5:$L$22+quarterly_bonus!$P$5:$P$22)) -> 15500 | F19: =C19+D19+E19 -> 182008 | G19: 2 | H19: =IF(G19>0,F19/G19,0) -> 91004
A20: CSM | B20: SMB | C20: =SUMPRODUCT((commission_calc!$E$5:$E$186="CSM")*(commission_calc!$F$5:$F$186="SMB")*commission_calc!$I$5:$I$186) -> 60000 | D20: =SUMPRODUCT((commission_calc!$E$5:$E$186="CSM")*(commission_calc!$F$5:$F$186="SMB")*commission_calc!$U$5:$U$186) -> 4186.5 | E20: =SUMPRODUCT((quarterly_bonus!$C$5:$C$22="CSM")*(quarterly_bonus!$D$5:$D$22="SMB")*(quarterly_bonus!$H$5:$H$22+quarterly_bonus!$L$5:$L$22+quarterly_bonus!$P$5:$P$22)) -> 5000 | F20: =C20+D20+E20 -> 69186.5 | G20: 1 | H20: =IF(G20>0,F20/G20,0) -> 69186.5
A21: TOTAL COMP COST | C21: =SUM(C12:C20) -> 1037166.7 | D21: =SUM(D12:D20) -> 637943 | E21: =SUM(E12:E20) -> 117450 | F21: =SUM(F12:F20) -> 1792559.7
A23: MANAGER OVERRIDE CALCULATION (2% of Direct Reports' Monthly Commission)
A24: Manager | B24: Segment | C24: Direct Reports' Total Variable ($) | D24: Override Rate | E24: Override Earned ($) | F24: Notes
A25: Sarah Chen | B25: Enterprise | C25: =SUMPRODUCT((commission_calc!$F$5:$F$186="Enterprise")*commission_calc!$U$5:$U$186) -> 298105.3 | D25: 0.02 | E25: =C25*D25 -> 5962.106 | F25: Override on direct reports' accelerated commission
A26: Tyler Rodriguez | B26: Mid-Market | C26: =SUMPRODUCT((commission_calc!$F$5:$F$186="Mid-Market")*commission_calc!$U$5:$U$186) -> 238329 | D26: 0.02 | E26: =C26*D26 -> 4766.58 | F26: Override on direct reports' accelerated commission
A27: Carlos Mendez | B27: SMB | C27: =SUMPRODUCT((commission_calc!$F$5:$F$186="SMB")*commission_calc!$U$5:$U$186) -> 101508.7 | D27: 0.02 | E27: =C27*D27 -> 2030.174 | F27: Override on direct reports' accelerated commission
A29: MANAGER TOTAL COMPENSATION SUMMARY (FY 2025)
A30: Manager | B30: Segment | C30: Annual Base ($) | D30: Override Earned ($) | E30: Est. Q Bonuses ($) | F30: Total FY Comp ($) | G30: OTE ($) | H30: vs. OTE ($)
A31: Sarah Chen | B31: Enterprise | C31: 110000 | D31: =SUMPRODUCT((commission_calc!$F$5:$F$186="Enterprise")*commission_calc!$U$5:$U$186)*0.02 -> 5962.106 | E31: 15000 | F31: =C31+D31+E31 -> 130962.11 | G31: 145000 | H31: =F31-G31 -> -14037.894
A32: Tyler Rodriguez | B32: Mid-Market | C32: 110000 | D32: =SUMPRODUCT((commission_calc!$F$5:$F$186="Mid-Market")*commission_calc!$U$5:$U$186)*0.02 -> 4766.58 | E32: 15000 | F32: =C32+D32+E32 -> 129766.58 | G32: 145000 | H32: =F32-G32 -> -15233.42
A33: Carlos Mendez | B33: SMB | C33: 110000 | D33: =SUMPRODUCT((commission_calc!$F$5:$F$186="SMB")*commission_calc!$U$5:$U$186)*0.02 -> 2030.174 | E33: 15000 | F33: =C33+D33+E33 -> 127030.17 | G33: 145000 | H33: =F33-G33 -> -17969.826

Sheet dashboard
A2: VELTORA INC.
A3: SALES COMPENSATION EXECUTIVE DASHBOARD · FY 2025
A4: Prepared for: Rachel Torres, VP Sales | G4: RevOps Team · Austin, TX · Series B | N4: CFO Review: Q1 2026 Planning Cycle
C6: TOTAL ARR CLOSED | I6: ORG ATTAINMENT | O6: TOTAL COMP COST
C7: =SUMPRODUCT((commission_calc!$E$5:$E$186="AE")*commission_calc!$K$5:$K$186) -> 3745000 | I7: =IFERROR(SUMPRODUCT((commission_calc!$E$5:$E$186="AE")*commission_calc!$K$5:$K$186)/SUMPRODUCT((commission_calc!$E$5:$E$186="AE")*commission_calc!$J$5:$J$186),0) -> 1.0468204 | O7: =SUMPRODUCT(commission_calc!$I$5:$I$186)+SUMPRODUCT(commission_calc!$U$5:$U$186) -> 1675109.7
C8: FY 2025 · All AEs | I8: AE blended · vs quota | O8: Base + Variable · All roles
C10: COMP AS % OF ARR | I10: ACCELERATOR EVENTS | O10: TOP 20% CONCENTRATION
C11: =IFERROR((SUMPRODUCT(commission_calc!$I$5:$I$186)+SUMPRODUCT(commission_calc!$U$5:$U$186))/SUMPRODUCT((commission_calc!$E$5:$E$186="AE")*commission_calc!$K$5:$K$186),0) -> 0.4472923 | I11: =SUMPRODUCT((commission_calc!$T$5:$T$186>1)*1) -> 90 | O11: =SUMPRODUCT(LARGE(U26:U43,{1,2,3,4}))/SUM(U26:U43) -> 0.62964089
C12: Cost efficiency ratio | I12: Months where accel fired | O12: Top 4 reps share of variable
C14: MONTHLY ARR CLOSED BY SEGMENT | L14: SEGMENT COMP COST BREAKDOWN
C15: Month | E15: Enterprise | G15: Mid-Market | I15: Total AE ARR | L15: Segment | N15: Role | P15: Variable ($) | R15: % of Total | V15: SMB
C16: Jan | E16: =SUMPRODUCT((commission_calc!$E$5:$E$186="AE")*(commission_calc!$F$5:$F$186="Enterprise")*(commission_calc!$C$5:$C$186=1)*commission_calc!$K$5:$K$186) -> 197000 | G16: =SUMPRODUCT((commission_calc!$E$5:$E$186="AE")*(commission_calc!$F$5:$F$186="Mid-Market")*(commission_calc!$C$5:$C$186=1)*commission_calc!$K$5:$K$186) -> 130000 | I16: =SUMPRODUCT((commission_calc!$E$5:$E$186="AE")*(commission_calc!$C$5:$C$186=1)*commission_calc!$K$5:$K$186) -> 377000 | L16: Enterprise | N16: AE | P16: =SUMPRODUCT((commission_calc!$E$5:$E$186="AE")*(commission_calc!$F$5:$F$186="Enterprise")*commission_calc!$U$5:$U$186) -> 242125 | R16: =IFERROR(P16/SUMPRODUCT(commission_calc!$U$5:$U$186),0) -> 0.37954018 | V16: =SUMPRODUCT((commission_calc!$E$5:$E$186="AE")*(commission_calc!$F$5:$F$186="SMB")*(commission_calc!$C$5:$C$186=1)*commission_calc!$K$5:$K$186) -> 50000
C17: Feb | E17: =SUMPRODUCT((commission_calc!$E$5:$E$186="AE")*(commission_calc!$F$5:$F$186="Enterprise")*(commission_calc!$C$5:$C$186=2)*commission_calc!$K$5:$K$186) -> 183000 | G17: =SUMPRODUCT((commission_calc!$E$5:$E$186="AE")*(commission_calc!$F$5:$F$186="Mid-Market")*(commission_calc!$C$5:$C$186=2)*commission_calc!$K$5:$K$186) -> 122000 | I17: =SUMPRODUCT((commission_calc!$E$5:$E$186="AE")*(commission_calc!$C$5:$C$186=2)*commission_calc!$K$5:$K$186) -> 349000 | L17: Enterprise | N17: CSM | P17: =SUMPRODUCT((commission_calc!$E$5:$E$186="CSM")*(commission_calc!$F$5:$F$186="Enterprise")*commission_calc!$U$5:$U$186) -> 29280 | R17: =IFERROR(P17/SUMPRODUCT(commission_calc!$U$5:$U$186),0) -> 0.045897517 | V17: =SUMPRODUCT((commission_calc!$E$5:$E$186="AE")*(commission_calc!$F$5:$F$186="SMB")*(commission_calc!$C$5:$C$186=2)*commission_calc!$K$5:$K$186) -> 44000
C18: Mar | E18: =SUMPRODUCT((commission_calc!$E$5:$E$186="AE")*(commission_calc!$F$5:$F$186="Enterprise")*(commission_calc!$C$5:$C$186=3)*commission_calc!$K$5:$K$186) -> 220000 | G18: =SUMPRODUCT((commission_calc!$E$5:$E$186="AE")*(commission_calc!$F$5:$F$186="Mid-Market")*(commission_calc!$C$5:$C$186=3)*commission_calc!$K$5:$K$186) -> 140000 | I18: =SUMPRODUCT((commission_calc!$E$5:$E$186="AE")*(commission_calc!$C$5:$C$186=3)*commission_calc!$K$5:$K$186) -> 415000 | L18: Mid-Market | N18: AE | P18: =SUMPRODUCT((commission_calc!$E$5:$E$186="AE")*(commission_calc!$F$5:$F$186="Mid-Market")*commission_calc!$U$5:$U$186) -> 159550 | R18: =IFERROR(P18/SUMPRODUCT(commission_calc!$U$5:$U$186),0) -> 0.25010071 | V18: =SUMPRODUCT((commission_calc!$E$5:$E$186="AE")*(commission_calc!$F$5:$F$186="SMB")*(commission_calc!$C$5:$C$186=3)*commission_calc!$K$5:$K$186) -> 55000
C19: Apr | E19: =SUMPRODUCT((commission_calc!$E$5:$E$186="AE")*(commission_calc!$F$5:$F$186="Enterprise")*(commission_calc!$C$5:$C$186=4)*commission_calc!$K$5:$K$186) -> 170000 | G19: =SUMPRODUCT((commission_calc!$E$5:$E$186="AE")*(commission_calc!$F$5:$F$186="Mid-Market")*(commission_calc!$C$5:$C$186=4)*commission_calc!$K$5:$K$186) -> 112000 | I19: =SUMPRODUCT((commission_calc!$E$5:$E$186="AE")*(commission_calc!$C$5:$C$186=4)*commission_calc!$K$5:$K$186) -> 326000 | L19: Mid-Market | N19: CSM | P19: =SUMPRODUCT((commission_calc!$E$5:$E$186="CSM")*(commission_calc!$F$5:$F$186="Mid-Market")*commission_calc!$U$5:$U$186) -> 26508 | R19: =IFERROR(P19/SUMPRODUCT(commission_calc!$U$5:$U$186),0) -> 0.041552302 | V19: =SUMPRODUCT((commission_calc!$E$5:$E$186="AE")*(commission_calc!$F$5:$F$186="SMB")*(commission_calc!$C$5:$C$186=4)*commission_calc!$K$5:$K$186) -> 44000
C20: May | E20: =SUMPRODUCT((commission_calc!$E$5:$E$186="AE")*(commission_calc!$F$5:$F$186="Enterprise")*(commission_calc!$C$5:$C$186=5)*commission_calc!$K$5:$K$186) -> 171000 | G20: =SUMPRODUCT((commission_calc!$E$5:$E$186="AE")*(commission_calc!$F$5:$F$186="Mid-Market")*(commission_calc!$C$5:$C$186=5)*commission_calc!$K$5:$K$186) -> 114000 | I20: =SUMPRODUCT((commission_calc!$E$5:$E$186="AE")*(commission_calc!$C$5:$C$186=5)*commission_calc!$K$5:$K$186) -> 330000 | L20: SMB | N20: AE | P20: =SUMPRODUCT((commission_calc!$E$5:$E$186="AE")*(commission_calc!$F$5:$F$186="SMB")*commission_calc!$U$5:$U$186) -> 61740 | R20: =IFERROR(P20/SUMPRODUCT(commission_calc!$U$5:$U$186),0) -> 0.096779806 | V20: =SUMPRODUCT((commission_calc!$E$5:$E$186="AE")*(commission_calc!$F$5:$F$186="SMB")*(commission_calc!$C$5:$C$186=5)*commission_calc!$K$5:$K$186) -> 45000
C21: Jun | E21: =SUMPRODUCT((commission_calc!$E$5:$E$186="AE")*(commission_calc!$F$5:$F$186="Enterprise")*(commission_calc!$C$5:$C$186=6)*commission_calc!$K$5:$K$186) -> 171000 | G21: =SUMPRODUCT((commission_calc!$E$5:$E$186="AE")*(commission_calc!$F$5:$F$186="Mid-Market")*(commission_calc!$C$5:$C$186=6)*commission_calc!$K$5:$K$186) -> 112000 | I21: =SUMPRODUCT((commission_calc!$E$5:$E$186="AE")*(commission_calc!$C$5:$C$186=6)*commission_calc!$K$5:$K$186) -> 325000 | L21: SMB | N21: CSM | P21: =SUMPRODUCT((commission_calc!$E$5:$E$186="CSM")*(commission_calc!$F$5:$F$186="SMB")*commission_calc!$U$5:$U$186) -> 4186.5 | R21: =IFERROR(P21/SUMPRODUCT(commission_calc!$U$5:$U$186),0) -> 0.0065624985 | V21: =SUMPRODUCT((commission_calc!$E$5:$E$186="AE")*(commission_calc!$F$5:$F$186="SMB")*(commission_calc!$C$5:$C$186=6)*commission_calc!$K$5:$K$186) -> 42000
C22: Jul | E22: =SUMPRODUCT((commission_calc!$E$5:$E$186="AE")*(commission_calc!$F$5:$F$186="Enterprise")*(commission_calc!$C$5:$C$186=7)*commission_calc!$K$5:$K$186) -> 137000 | G22: =SUMPRODUCT((commission_calc!$E$5:$E$186="AE")*(commission_calc!$F$5:$F$186="Mid-Market")*(commission_calc!$C$5:$C$186=7)*commission_calc!$K$5:$K$186) -> 89000 | I22: =SUMPRODUCT((commission_calc!$E$5:$E$186="AE")*(commission_calc!$C$5:$C$186=7)*commission_calc!$K$5:$K$186) -> 258000 | L22: Enterprise | N22: SDR | P22: =SUMPRODUCT((commission_calc!$E$5:$E$186="SDR")*(commission_calc!$F$5:$F$186="Enterprise")*commission_calc!$U$5:$U$186) -> 26700.3 | R22: =IFERROR(P22/SUMPRODUCT(commission_calc!$U$5:$U$186),0) -> 0.041853739 | V22: =SUMPRODUCT((commission_calc!$E$5:$E$186="AE")*(commission_calc!$F$5:$F$186="SMB")*(commission_calc!$C$5:$C$186=7)*commission_calc!$K$5:$K$186) -> 32000
C23: Aug | E23: =SUMPRODUCT((commission_calc!$E$5:$E$186="AE")*(commission_calc!$F$5:$F$186="Enterprise")*(commission_calc!$C$5:$C$186=8)*commission_calc!$K$5:$K$186) -> 123000 | G23: =SUMPRODUCT((commission_calc!$E$5:$E$186="AE")*(commission_calc!$F$5:$F$186="Mid-Market")*(commission_calc!$C$5:$C$186=8)*commission_calc!$K$5:$K$186) -> 82000 | I23: =SUMPRODUCT((commission_calc!$E$5:$E$186="AE")*(commission_calc!$C$5:$C$186=8)*commission_calc!$K$5:$K$186) -> 242000 | L23: Mid-Market | N23: SDR | P23: =SUMPRODUCT((commission_calc!$E$5:$E$186="SDR")*(commission_calc!$F$5:$F$186="Mid-Market")*commission_calc!$U$5:$U$186) -> 52271 | R23: =IFERROR(P23/SUMPRODUCT(commission_calc!$U$5:$U$186),0) -> 0.081936787 | V23: =SUMPRODUCT((commission_calc!$E$5:$E$186="AE")*(commission_calc!$F$5:$F$186="SMB")*(commission_calc!$C$5:$C$186=8)*commission_calc!$K$5:$K$186) -> 37000
C24: Sep | E24: =SUMPRODUCT((commission_calc!$E$5:$E$186="AE")*(commission_calc!$F$5:$F$186="Enterprise")*(commission_calc!$C$5:$C$186=9)*commission_calc!$K$5:$K$186) -> 148000 | G24: =SUMPRODUCT((commission_calc!$E$5:$E$186="AE")*(commission_calc!$F$5:$F$186="Mid-Market")*(commission_calc!$C$5:$C$186=9)*commission_calc!$K$5:$K$186) -> 98000 | I24: =SUMPRODUCT((commission_calc!$E$5:$E$186="AE")*(commission_calc!$C$5:$C$186=9)*commission_calc!$K$5:$K$186) -> 296000 | L24: SMB | N24: SDR | P24: =SUMPRODUCT((commission_calc!$E$5:$E$186="SDR")*(commission_calc!$F$5:$F$186="SMB")*commission_calc!$U$5:$U$186) -> 35582.2 | R24: =IFERROR(P24/SUMPRODUCT(commission_calc!$U$5:$U$186),0) -> 0.055776457 | V24: =SUMPRODUCT((commission_calc!$E$5:$E$186="AE")*(commission_calc!$F$5:$F$186="SMB")*(commission_calc!$C$5:$C$186=9)*commission_calc!$K$5:$K$186) -> 50000
C25: Oct | E25: =SUMPRODUCT((commission_calc!$E$5:$E$186="AE")*(commission_calc!$F$5:$F$186="Enterprise")*(commission_calc!$C$5:$C$186=10)*commission_calc!$K$5:$K$186) -> 117000 | G25: =SUMPRODUCT((commission_calc!$E$5:$E$186="AE")*(commission_calc!$F$5:$F$186="Mid-Market")*(commission_calc!$C$5:$C$186=10)*commission_calc!$K$5:$K$186) -> 78000 | I25: =SUMPRODUCT((commission_calc!$E$5:$E$186="AE")*(commission_calc!$C$5:$C$186=10)*commission_calc!$K$5:$K$186) -> 238000 | L25: TOTAL VARIABLE COMP | P25: =SUMPRODUCT(commission_calc!$U$5:$U$186) -> 637943 | R25: 100.0% | V25: =SUMPRODUCT((commission_calc!$E$5:$E$186="AE")*(commission_calc!$F$5:$F$186="SMB")*(commission_calc!$C$5:$C$186=10)*commission_calc!$K$5:$K$186) -> 43000
C26: Nov | E26: =SUMPRODUCT((commission_calc!$E$5:$E$186="AE")*(commission_calc!$F$5:$F$186="Enterprise")*(commission_calc!$C$5:$C$186=11)*commission_calc!$K$5:$K$186) -> 132000 | G26: =SUMPRODUCT((commission_calc!$E$5:$E$186="AE")*(commission_calc!$F$5:$F$186="Mid-Market")*(commission_calc!$C$5:$C$186=11)*commission_calc!$K$5:$K$186) -> 87000 | I26: =SUMPRODUCT((commission_calc!$E$5:$E$186="AE")*(commission_calc!$C$5:$C$186=11)*commission_calc!$K$5:$K$186) -> 262000 | U26: =SUMPRODUCT((commission_calc!$B$5:$B$186="R002")*commission_calc!$U$5:$U$186) -> 26700.3 | V26: =SUMPRODUCT((commission_calc!$E$5:$E$186="AE")*(commission_calc!$F$5:$F$186="SMB")*(commission_calc!$C$5:$C$186=11)*commission_calc!$K$5:$K$186) -> 43000
C27: Dec | E27: =SUMPRODUCT((commission_calc!$E$5:$E$186="AE")*(commission_calc!$F$5:$F$186="Enterprise")*(commission_calc!$C$5:$C$186=12)*commission_calc!$K$5:$K$186) -> 163000 | G27: =SUMPRODUCT((commission_calc!$E$5:$E$186="AE")*(commission_calc!$F$5:$F$186="Mid-Market")*(commission_calc!$C$5:$C$186=12)*commission_calc!$K$5:$K$186) -> 110000 | I27: =SUMPRODUCT((commission_calc!$E$5:$E$186="AE")*(commission_calc!$C$5:$C$186=12)*commission_calc!$K$5:$K$186) -> 327000 | U27: =SUMPRODUCT((commission_calc!$B$5:$B$186="R003")*commission_calc!$U$5:$U$186) -> 112625 | V27: =SUMPRODUCT((commission_calc!$E$5:$E$186="AE")*(commission_calc!$F$5:$F$186="SMB")*(commission_calc!$C$5:$C$186=12)*commission_calc!$K$5:$K$186) -> 54000
C28: TOTAL | E28: =SUM(E16:E27) -> 1932000 | G28: =SUM(G16:G27) -> 1274000 | I28: =SUM(I16:I27) -> 3745000 | U28: =SUMPRODUCT((commission_calc!$B$5:$B$186="R004")*commission_calc!$U$5:$U$186) -> 129500
U29: =SUMPRODUCT((commission_calc!$B$5:$B$186="R005")*commission_calc!$U$5:$U$186) -> 27060
U30: =SUMPRODUCT((commission_calc!$B$5:$B$186="R006")*commission_calc!$U$5:$U$186) -> 2220
C31: FULL-YEAR ATTAINMENT · AEs & CSMs | U31: =SUMPRODUCT((commission_calc!$B$5:$B$186="R008")*commission_calc!$U$5:$U$186) -> 15948.5
C32: Rep Name | E32: Role | F32: Segment | H32: Annual Quota | J32: Annual Actual | L32: Ann Att% | M32: Q1 Att% | N32: Q2 Att% | O32: Q3 Att% | P32: Q4 Att% | Q32: Annual Variable | S32: Status | U32: =SUMPRODUCT((commission_calc!$B$5:$B$186="R009")*commission_calc!$U$5:$U$186) -> 24841.25
C33: =VLOOKUP("R003",rep_roster!$A:$B,2,0) -> James Harrington | E33: AE | F33: Enterprise | H33: =SUMPRODUCT((commission_calc!$B$5:$B$186="R003")*commission_calc!$J$5:$J$186) -> 900000 | J33: =SUMPRODUCT((commission_calc!$B$5:$B$186="R003")*commission_calc!$K$5:$K$186) -> 923000 | L33: =IF(H33>0,J33/H33,0) -> 1.0255556 | M33: =IFERROR(SUMPRODUCT((commission_calc!$B$5:$B$186="R003")*(commission_calc!$C$5:$C$186>=1)*(commission_calc!$C$5:$C$186<=3)*commission_calc!$K$5:$K$186)/SUMPRODUCT((commission_calc!$B$5:$B$186="R003")*(commission_calc!$C$5:$C$186>=1)*(commission_calc!$C$5:$C$186<=3)*commission_calc!$J$5:$J$186),0) -> 1.28 | N33: =IFERROR(SUMPRODUCT((commission_calc!$B$5:$B$186="R003")*(commission_calc!$C$5:$C$186>=4)*(commission_calc!$C$5:$C$186<=6)*commission_calc!$K$5:$K$186)/SUMPRODUCT((commission_calc!$B$5:$B$186="R003")*(commission_calc!$C$5:$C$186>=4)*(commission_calc!$C$5:$C$186<=6)*commission_calc!$J$5:$J$186),0) -> 1.0977778 | O33: =IFERROR(SUMPRODUCT((commission_calc!$B$5:$B$186="R003")*(commission_calc!$C$5:$C$186>=7)*(commission_calc!$C$5:$C$186<=9)*commission_calc!$K$5:$K$186)/SUMPRODUCT((commission_calc!$B$5:$B$186="R003")*(commission_calc!$C$5:$C$186>=7)*(commission_calc!$C$5:$C$186<=9)*commission_calc!$J$5:$J$186),0) -> 0.85777778 | P33: =IFERROR(SUMPRODUCT((commission_calc!$B$5:$B$186="R003")*(commission_calc!$C$5:$C$186>=10)*(commission_calc!$C$5:$C$186<=12)*commission_calc!$K$5:$K$186)/SUMPRODUCT((commission_calc!$B$5:$B$186="R003")*(commission_calc!$C$5:$C$186>=10)*(commission_calc!$C$5:$C$186<=12)*commission_calc!$J$5:$J$186),0) -> 0.86666667 | Q33: =SUMPRODUCT((commission_calc!$B$5:$B$186="R003")*commission_calc!$U$5:$U$186) -> 112625 | S33: On track | U33: =SUMPRODUCT((commission_calc!$B$5:$B$186="R010")*commission_calc!$U$5:$U$186) -> 11481.25
C34: =VLOOKUP("R004",rep_roster!$A:$B,2,0) -> Olivia Brooks | E34: AE | F34: Enterprise | H34: =SUMPRODUCT((commission_calc!$B$5:$B$186="R004")*commission_calc!$J$5:$J$186) -> 900000 | J34: =SUMPRODUCT((commission_calc!$B$5:$B$186="R004")*commission_calc!$K$5:$K$186) -> 1009000 | L34: =IF(H34>0,J34/H34,0) -> 1.1211111 | M34: =IFERROR(SUMPRODUCT((commission_calc!$B$5:$B$186="R004")*(commission_calc!$C$5:$C$186>=1)*(commission_calc!$C$5:$C$186<=3)*commission_calc!$K$5:$K$186)/SUMPRODUCT((commission_calc!$B$5:$B$186="R004")*(commission_calc!$C$5:$C$186>=1)*(commission_calc!$C$5:$C$186<=3)*commission_calc!$J$5:$J$186),0) -> 1.3866667 | N34: =IFERROR(SUMPRODUCT((commission_calc!$B$5:$B$186="R004")*(commission_calc!$C$5:$C$186>=4)*(commission_calc!$C$5:$C$186<=6)*commission_calc!$K$5:$K$186)/SUMPRODUCT((commission_calc!$B$5:$B$186="R004")*(commission_calc!$C$5:$C$186>=4)*(commission_calc!$C$5:$C$186<=6)*commission_calc!$J$5:$J$186),0) -> 1.1777778 | O34: =IFERROR(SUMPRODUCT((commission_calc!$B$5:$B$186="R004")*(commission_calc!$C$5:$C$186>=7)*(commission_calc!$C$5:$C$186<=9)*commission_calc!$K$5:$K$186)/SUMPRODUCT((commission_calc!$B$5:$B$186="R004")*(commission_calc!$C$5:$C$186>=7)*(commission_calc!$C$5:$C$186<=9)*commission_calc!$J$5:$J$186),0) -> 0.95555556 | P34: =IFERROR(SUMPRODUCT((commission_calc!$B$5:$B$186="R004")*(commission_calc!$C$5:$C$186>=10)*(commission_calc!$C$5:$C$186<=12)*commission_calc!$K$5:$K$186)/SUMPRODUCT((commission_calc!$B$5:$B$186="R004")*(commission_calc!$C$5:$C$186>=10)*(commission_calc!$C$5:$C$186<=12)*commission_calc!$J$5:$J$186),0) -> 0.96444444 | Q34: =SUMPRODUCT((commission_calc!$B$5:$B$186="R004")*commission_calc!$U$5:$U$186) -> 129500 | S34: Top performer | U34: =SUMPRODUCT((commission_calc!$B$5:$B$186="R011")*commission_calc!$U$5:$U$186) -> 74825
C35: =VLOOKUP("R005",rep_roster!$A:$B,2,0) -> David Kim | E35: CSM | F35: Enterprise | H35: =SUMPRODUCT((commission_calc!$B$5:$B$186="R005")*commission_calc!$J$5:$J$186) -> 360000 | J35: =SUMPRODUCT((commission_calc!$B$5:$B$186="R005")*commission_calc!$K$5:$K$186) -> 393000 | L35: =IF(H35>0,J35/H35,0) -> 1.0916667 | M35: =IFERROR(SUMPRODUCT((commission_calc!$B$5:$B$186="R005")*(commission_calc!$C$5:$C$186>=1)*(commission_calc!$C$5:$C$186<=3)*commission_calc!$K$5:$K$186)/SUMPRODUCT((commission_calc!$B$5:$B$186="R005")*(commission_calc!$C$5:$C$186>=1)*(commission_calc!$C$5:$C$186<=3)*commission_calc!$J$5:$J$186),0) -> 1.3166667 | N35: =IFERROR(SUMPRODUCT((commission_calc!$B$5:$B$186="R005")*(commission_calc!$C$5:$C$186>=4)*(commission_calc!$C$5:$C$186<=6)*commission_calc!$K$5:$K$186)/SUMPRODUCT((commission_calc!$B$5:$B$186="R005")*(commission_calc!$C$5:$C$186>=4)*(commission_calc!$C$5:$C$186<=6)*commission_calc!$J$5:$J$186),0) -> 1.1 | O35: =IFERROR(SUMPRODUCT((commission_calc!$B$5:$B$186="R005")*(commission_calc!$C$5:$C$186>=7)*(commission_calc!$C$5:$C$186<=9)*commission_calc!$K$5:$K$186)/SUMPRODUCT((commission_calc!$B$5:$B$186="R005")*(commission_calc!$C$5:$C$186>=7)*(commission_calc!$C$5:$C$186<=9)*commission_calc!$J$5:$J$186),0) -> 0.85833333 | P35: =IFERROR(SUMPRODUCT((commission_calc!$B$5:$B$186="R005")*(commission_calc!$C$5:$C$186>=10)*(commission_calc!$C$5:$C$186<=12)*commission_calc!$K$5:$K$186)/SUMPRODUCT((commission_calc!$B$5:$B$186="R005")*(commission_calc!$C$5:$C$186>=10)*(commission_calc!$C$5:$C$186<=12)*commission_calc!$J$5:$J$186),0) -> 0 | Q35: =SUMPRODUCT((commission_calc!$B$5:$B$186="R005")*commission_calc!$U$5:$U$186) -> 27060 | S35: Churned Q3 | U35: =SUMPRODUCT((commission_calc!$B$5:$B$186="R012")*commission_calc!$U$5:$U$186) -> 84725
C36: =VLOOKUP("R006",rep_roster!$A:$B,2,0) -> Lisa Park | E36: CSM | F36: Enterprise | H36: =SUMPRODUCT((commission_calc!$B$5:$B$186="R006")*commission_calc!$J$5:$J$186) -> 84000 | J36: =SUMPRODUCT((commission_calc!$B$5:$B$186="R006")*commission_calc!$K$5:$K$186) -> 37000 | L36: =IF(H36>0,J36/H36,0) -> 0.44047619 | M36: =IFERROR(SUMPRODUCT((commission_calc!$B$5:$B$186="R006")*(commission_calc!$C$5:$C$186>=1)*(commission_calc!$C$5:$C$186<=3)*commission_calc!$K$5:$K$186)/SUMPRODUCT((commission_calc!$B$5:$B$186="R006")*(commission_calc!$C$5:$C$186>=1)*(commission_calc!$C$5:$C$186<=3)*commission_calc!$J$5:$J$186),0) -> 0 | N36: =IFERROR(SUMPRODUCT((commission_calc!$B$5:$B$186="R006")*(commission_calc!$C$5:$C$186>=4)*(commission_calc!$C$5:$C$186<=6)*commission_calc!$K$5:$K$186)/SUMPRODUCT((commission_calc!$B$5:$B$186="R006")*(commission_calc!$C$5:$C$186>=4)*(commission_calc!$C$5:$C$186<=6)*commission_calc!$J$5:$J$186),0) -> 0 | O36: =IFERROR(SUMPRODUCT((commission_calc!$B$5:$B$186="R006")*(commission_calc!$C$5:$C$186>=7)*(commission_calc!$C$5:$C$186<=9)*commission_calc!$K$5:$K$186)/SUMPRODUCT((commission_calc!$B$5:$B$186="R006")*(commission_calc!$C$5:$C$186>=7)*(commission_calc!$C$5:$C$186<=9)*commission_calc!$J$5:$J$186),0) -> 0 | P36: =IFERROR(SUMPRODUCT((commission_calc!$B$5:$B$186="R006")*(commission_calc!$C$5:$C$186>=10)*(commission_calc!$C$5:$C$186<=12)*commission_calc!$K$5:$K$186)/SUMPRODUCT((commission_calc!$B$5:$B$186="R006")*(commission_calc!$C$5:$C$186>=10)*(commission_calc!$C$5:$C$186<=12)*commission_calc!$J$5:$J$186),0) -> 0.44047619 | Q36: =SUMPRODUCT((commission_calc!$B$5:$B$186="R006")*commission_calc!$U$5:$U$186) -> 2220 | S36: Ramping Q4 | U36: =SUMPRODUCT((commission_calc!$B$5:$B$186="R013")*commission_calc!$U$5:$U$186) -> 12492
C37: =VLOOKUP("R011",rep_roster!$A:$B,2,0) -> Ryan Thompson | E37: AE | F37: Mid-Market | H37: =SUMPRODUCT((commission_calc!$B$5:$B$186="R011")*commission_calc!$J$5:$J$186) -> 600000 | J37: =SUMPRODUCT((commission_calc!$B$5:$B$186="R011")*commission_calc!$K$5:$K$186) -> 615000 | L37: =IF(H37>0,J37/H37,0) -> 1.025 | M37: =IFERROR(SUMPRODUCT((commission_calc!$B$5:$B$186="R011")*(commission_calc!$C$5:$C$186>=1)*(commission_calc!$C$5:$C$186<=3)*commission_calc!$K$5:$K$186)/SUMPRODUCT((commission_calc!$B$5:$B$186="R011")*(commission_calc!$C$5:$C$186>=1)*(commission_calc!$C$5:$C$186<=3)*commission_calc!$J$5:$J$186),0) -> 1.2533333 | N37: =IFERROR(SUMPRODUCT((commission_calc!$B$5:$B$186="R011")*(commission_calc!$C$5:$C$186>=4)*(commission_calc!$C$5:$C$186<=6)*commission_calc!$K$5:$K$186)/SUMPRODUCT((commission_calc!$B$5:$B$186="R011")*(commission_calc!$C$5:$C$186>=4)*(commission_calc!$C$5:$C$186<=6)*commission_calc!$J$5:$J$186),0) -> 1.0866667 | O37: =IFERROR(SUMPRODUCT((commission_calc!$B$5:$B$186="R011")*(commission_calc!$C$5:$C$186>=7)*(commission_calc!$C$5:$C$186<=9)*commission_calc!$K$5:$K$186)/SUMPRODUCT((commission_calc!$B$5:$B$186="R011")*(commission_calc!$C$5:$C$186>=7)*(commission_calc!$C$5:$C$186<=9)*commission_calc!$J$5:$J$186),0) -> 0.88 | P37: =IFERROR(SUMPRODUCT((commission_calc!$B$5:$B$186="R011")*(commission_calc!$C$5:$C$186>=10)*(commission_calc!$C$5:$C$186<=12)*commission_calc!$K$5:$K$186)/SUMPRODUCT((commission_calc!$B$5:$B$186="R011")*(commission_calc!$C$5:$C$186>=10)*(commission_calc!$C$5:$C$186<=12)*commission_calc!$J$5:$J$186),0) -> 0.88 | Q37: =SUMPRODUCT((commission_calc!$B$5:$B$186="R011")*commission_calc!$U$5:$U$186) -> 74825 | S37: On track | U37: =SUMPRODUCT((commission_calc!$B$5:$B$186="R014")*commission_calc!$U$5:$U$186) -> 14016
C38: =VLOOKUP("R012",rep_roster!$A:$B,2,0) -> Samantha Lee | E38: AE | F38: Mid-Market | H38: =SUMPRODUCT((commission_calc!$B$5:$B$186="R012")*commission_calc!$J$5:$J$186) -> 600000 | J38: =SUMPRODUCT((commission_calc!$B$5:$B$186="R012")*commission_calc!$K$5:$K$186) -> 659000 | L38: =IF(H38>0,J38/H38,0) -> 1.0983333 | M38: =IFERROR(SUMPRODUCT((commission_calc!$B$5:$B$186="R012")*(commission_calc!$C$5:$C$186>=1)*(commission_calc!$C$5:$C$186<=3)*commission_calc!$K$5:$K$186)/SUMPRODUCT((commission_calc!$B$5:$B$186="R012")*(commission_calc!$C$5:$C$186>=1)*(commission_calc!$C$5:$C$186<=3)*commission_calc!$J$5:$J$186),0) -> 1.36 | N38: =IFERROR(SUMPRODUCT((commission_calc!$B$5:$B$186="R012")*(commission_calc!$C$5:$C$186>=4)*(commission_calc!$C$5:$C$186<=6)*commission_calc!$K$5:$K$186)/SUMPRODUCT((commission_calc!$B$5:$B$186="R012")*(commission_calc!$C$5:$C$186>=4)*(commission_calc!$C$5:$C$186<=6)*commission_calc!$J$5:$J$186),0) -> 1.1666667 | O38: =IFERROR(SUMPRODUCT((commission_calc!$B$5:$B$186="R012")*(commission_calc!$C$5:$C$186>=7)*(commission_calc!$C$5:$C$186<=9)*commission_calc!$K$5:$K$186)/SUMPRODUCT((commission_calc!$B$5:$B$186="R012")*(commission_calc!$C$5:$C$186>=7)*(commission_calc!$C$5:$C$186<=9)*commission_calc!$J$5:$J$186),0) -> 0.91333333 | P38: =IFERROR(SUMPRODUCT((commission_calc!$B$5:$B$186="R012")*(commission_calc!$C$5:$C$186>=10)*(commission_calc!$C$5:$C$186<=12)*commission_calc!$K$5:$K$186)/SUMPRODUCT((commission_calc!$B$5:$B$186="R012")*(commission_calc!$C$5:$C$186>=10)*(commission_calc!$C$5:$C$186<=12)*commission_calc!$J$5:$J$186),0) -> 0.95333333 | Q38: =SUMPRODUCT((commission_calc!$B$5:$B$186="R012")*commission_calc!$U$5:$U$186) -> 84725 | S38: On track | U38: =SUMPRODUCT((commission_calc!$B$5:$B$186="R016")*commission_calc!$U$5:$U$186) -> 18636.6
C39: =VLOOKUP("R013",rep_roster!$A:$B,2,0) -> Daniel Foster | E39: CSM | F39: Mid-Market | H39: =SUMPRODUCT((commission_calc!$B$5:$B$186="R013")*commission_calc!$J$5:$J$186) -> 180000 | J39: =SUMPRODUCT((commission_calc!$B$5:$B$186="R013")*commission_calc!$K$5:$K$186) -> 186000 | L39: =IF(H39>0,J39/H39,0) -> 1.0333333 | M39: =IFERROR(SUMPRODUCT((commission_calc!$B$5:$B$186="R013")*(commission_calc!$C$5:$C$186>=1)*(commission_calc!$C$5:$C$186<=3)*commission_calc!$K$5:$K$186)/SUMPRODUCT((commission_calc!$B$5:$B$186="R013")*(commission_calc!$C$5:$C$186>=1)*(commission_calc!$C$5:$C$186<=3)*commission_calc!$J$5:$J$186),0) -> 1.3333333 | N39: =IFERROR(SUMPRODUCT((commission_calc!$B$5:$B$186="R013")*(commission_calc!$C$5:$C$186>=4)*(commission_calc!$C$5:$C$186<=6)*commission_calc!$K$5:$K$186)/SUMPRODUCT((commission_calc!$B$5:$B$186="R013")*(commission_calc!$C$5:$C$186>=4)*(commission_calc!$C$5:$C$186<=6)*commission_calc!$J$5:$J$186),0) -> 1.1333333 | O39: =IFERROR(SUMPRODUCT((commission_calc!$B$5:$B$186="R013")*(commission_calc!$C$5:$C$186>=7)*(commission_calc!$C$5:$C$186<=9)*commission_calc!$K$5:$K$186)/SUMPRODUCT((commission_calc!$B$5:$B$186="R013")*(commission_calc!$C$5:$C$186>=7)*(commission_calc!$C$5:$C$186<=9)*commission_calc!$J$5:$J$186),0) -> 0.84444444 | P39: =IFERROR(SUMPRODUCT((commission_calc!$B$5:$B$186="R013")*(commission_calc!$C$5:$C$186>=10)*(commission_calc!$C$5:$C$186<=12)*commission_calc!$K$5:$K$186)/SUMPRODUCT((commission_calc!$B$5:$B$186="R013")*(commission_calc!$C$5:$C$186>=10)*(commission_calc!$C$5:$C$186<=12)*commission_calc!$J$5:$J$186),0) -> 0.82222222 | Q39: =SUMPRODUCT((commission_calc!$B$5:$B$186="R013")*commission_calc!$U$5:$U$186) -> 12492 | S39: On track | U39: =SUMPRODUCT((commission_calc!$B$5:$B$186="R017")*commission_calc!$U$5:$U$186) -> 16945.6
C40: =VLOOKUP("R014",rep_roster!$A:$B,2,0) -> Rachel Green | E40: CSM | F40: Mid-Market | H40: =SUMPRODUCT((commission_calc!$B$5:$B$186="R014")*commission_calc!$J$5:$J$186) -> 180000 | J40: =SUMPRODUCT((commission_calc!$B$5:$B$186="R014")*commission_calc!$K$5:$K$186) -> 206000 | L40: =IF(H40>0,J40/H40,0) -> 1.1444444 | M40: =IFERROR(SUMPRODUCT((commission_calc!$B$5:$B$186="R014")*(commission_calc!$C$5:$C$186>=1)*(commission_calc!$C$5:$C$186<=3)*commission_calc!$K$5:$K$186)/SUMPRODUCT((commission_calc!$B$5:$B$186="R014")*(commission_calc!$C$5:$C$186>=1)*(commission_calc!$C$5:$C$186<=3)*commission_calc!$J$5:$J$186),0) -> 1.4666667 | N40: =IFERROR(SUMPRODUCT((commission_calc!$B$5:$B$186="R014")*(commission_calc!$C$5:$C$186>=4)*(commission_calc!$C$5:$C$186<=6)*commission_calc!$K$5:$K$186)/SUMPRODUCT((commission_calc!$B$5:$B$186="R014")*(commission_calc!$C$5:$C$186>=4)*(commission_calc!$C$5:$C$186<=6)*commission_calc!$J$5:$J$186),0) -> 1.2 | O40: =IFERROR(SUMPRODUCT((commission_calc!$B$5:$B$186="R014")*(commission_calc!$C$5:$C$186>=7)*(commission_calc!$C$5:$C$186<=9)*commission_calc!$K$5:$K$186)/SUMPRODUCT((commission_calc!$B$5:$B$186="R014")*(commission_calc!$C$5:$C$186>=7)*(commission_calc!$C$5:$C$186<=9)*commission_calc!$J$5:$J$186),0) -> 0.93333333 | P40: =IFERROR(SUMPRODUCT((commission_calc!$B$5:$B$186="R014")*(commission_calc!$C$5:$C$186>=10)*(commission_calc!$C$5:$C$186<=12)*commission_calc!$K$5:$K$186)/SUMPRODUCT((commission_calc!$B$5:$B$186="R014")*(commission_calc!$C$5:$C$186>=10)*(commission_calc!$C$5:$C$186<=12)*commission_calc!$J$5:$J$186),0) -> 0.97777778 | Q40: =SUMPRODUCT((commission_calc!$B$5:$B$186="R014")*commission_calc!$U$5:$U$186) -> 14016 | S40: On track | U40: =SUMPRODUCT((commission_calc!$B$5:$B$186="R018")*commission_calc!$U$5:$U$186) -> 9900
C41: =VLOOKUP("R018",rep_roster!$A:$B,2,0) -> Brandon Cole | E41: AE | F41: SMB | H41: =SUMPRODUCT((commission_calc!$B$5:$B$186="R018")*commission_calc!$J$5:$J$186) -> 150000 | J41: =SUMPRODUCT((commission_calc!$B$5:$B$186="R018")*commission_calc!$K$5:$K$186) -> 99000 | L41: =IF(H41>0,J41/H41,0) -> 0.66 | M41: =IFERROR(SUMPRODUCT((commission_calc!$B$5:$B$186="R018")*(commission_calc!$C$5:$C$186>=1)*(commission_calc!$C$5:$C$186<=3)*commission_calc!$K$5:$K$186)/SUMPRODUCT((commission_calc!$B$5:$B$186="R018")*(commission_calc!$C$5:$C$186>=1)*(commission_calc!$C$5:$C$186<=3)*commission_calc!$J$5:$J$186),0) -> 0.70666667 | N41: =IFERROR(SUMPRODUCT((commission_calc!$B$5:$B$186="R018")*(commission_calc!$C$5:$C$186>=4)*(commission_calc!$C$5:$C$186<=6)*commission_calc!$K$5:$K$186)/SUMPRODUCT((commission_calc!$B$5:$B$186="R018")*(commission_calc!$C$5:$C$186>=4)*(commission_calc!$C$5:$C$186<=6)*commission_calc!$J$5:$J$186),0) -> 0.61333333 | O41: =IFERROR(SUMPRODUCT((commission_calc!$B$5:$B$186="R018")*(commission_calc!$C$5:$C$186>=7)*(commission_calc!$C$5:$C$186<=9)*commission_calc!$K$5:$K$186)/SUMPRODUCT((commission_calc!$B$5:$B$186="R018")*(commission_calc!$C$5:$C$186>=7)*(commission_calc!$C$5:$C$186<=9)*commission_calc!$J$5:$J$186),0) -> 0 | P41: =IFERROR(SUMPRODUCT((commission_calc!$B$5:$B$186="R018")*(commission_calc!$C$5:$C$186>=10)*(commission_calc!$C$5:$C$186<=12)*commission_calc!$K$5:$K$186)/SUMPRODUCT((commission_calc!$B$5:$B$186="R018")*(commission_calc!$C$5:$C$186>=10)*(commission_calc!$C$5:$C$186<=12)*commission_calc!$J$5:$J$186),0) -> 0 | Q41: =SUMPRODUCT((commission_calc!$B$5:$B$186="R018")*commission_calc!$U$5:$U$186) -> 9900 | S41: Churned Q2 | U41: =SUMPRODUCT((commission_calc!$B$5:$B$186="R019")*commission_calc!$U$5:$U$186) -> 13520
C42: =VLOOKUP("R019",rep_roster!$A:$B,2,0) -> Stephanie Kim | E42: AE | F42: SMB | H42: =SUMPRODUCT((commission_calc!$B$5:$B$186="R019")*commission_calc!$J$5:$J$186) -> 127500 | J42: =SUMPRODUCT((commission_calc!$B$5:$B$186="R019")*commission_calc!$K$5:$K$186) -> 123000 | L42: =IF(H42>0,J42/H42,0) -> 0.96470588 | M42: =IFERROR(SUMPRODUCT((commission_calc!$B$5:$B$186="R019")*(commission_calc!$C$5:$C$186>=1)*(commission_calc!$C$5:$C$186<=3)*commission_calc!$K$5:$K$186)/SUMPRODUCT((commission_calc!$B$5:$B$186="R019")*(commission_calc!$C$5:$C$186>=1)*(commission_calc!$C$5:$C$186<=3)*commission_calc!$J$5:$J$186),0) -> 0 | N42: =IFERROR(SUMPRODUCT((commission_calc!$B$5:$B$186="R019")*(commission_calc!$C$5:$C$186>=4)*(commission_calc!$C$5:$C$186<=6)*commission_calc!$K$5:$K$186)/SUMPRODUCT((commission_calc!$B$5:$B$186="R019")*(commission_calc!$C$5:$C$186>=4)*(commission_calc!$C$5:$C$186<=6)*commission_calc!$J$5:$J$186),0) -> 0 | O42: =IFERROR(SUMPRODUCT((commission_calc!$B$5:$B$186="R019")*(commission_calc!$C$5:$C$186>=7)*(commission_calc!$C$5:$C$186<=9)*commission_calc!$K$5:$K$186)/SUMPRODUCT((commission_calc!$B$5:$B$186="R019")*(commission_calc!$C$5:$C$186>=7)*(commission_calc!$C$5:$C$186<=9)*commission_calc!$J$5:$J$186),0) -> 0.99047619 | P42: =IFERROR(SUMPRODUCT((commission_calc!$B$5:$B$186="R019")*(commission_calc!$C$5:$C$186>=10)*(commission_calc!$C$5:$C$186<=12)*commission_calc!$K$5:$K$186)/SUMPRODUCT((commission_calc!$B$5:$B$186="R019")*(commission_calc!$C$5:$C$186>=10)*(commission_calc!$C$5:$C$186<=12)*commission_calc!$J$5:$J$186),0) -> 0.94666667 | Q42: =SUMPRODUCT((commission_calc!$B$5:$B$186="R019")*commission_calc!$U$5:$U$186) -> 13520 | S42: Ramping H2 | U42: =SUMPRODUCT((commission_calc!$B$5:$B$186="R020")*commission_calc!$U$5:$U$186) -> 38320
C43: =VLOOKUP("R020",rep_roster!$A:$B,2,0) -> Amy Chen | E43: AE | F43: SMB | H43: =SUMPRODUCT((commission_calc!$B$5:$B$186="R020")*commission_calc!$J$5:$J$186) -> 300000 | J43: =SUMPRODUCT((commission_calc!$B$5:$B$186="R020")*commission_calc!$K$5:$K$186) -> 317000 | L43: =IF(H43>0,J43/H43,0) -> 1.0566667 | M43: =IFERROR(SUMPRODUCT((commission_calc!$B$5:$B$186="R020")*(commission_calc!$C$5:$C$186>=1)*(commission_calc!$C$5:$C$186<=3)*commission_calc!$K$5:$K$186)/SUMPRODUCT((commission_calc!$B$5:$B$186="R020")*(commission_calc!$C$5:$C$186>=1)*(commission_calc!$C$5:$C$186<=3)*commission_calc!$J$5:$J$186),0) -> 1.28 | N43: =IFERROR(SUMPRODUCT((commission_calc!$B$5:$B$186="R020")*(commission_calc!$C$5:$C$186>=4)*(commission_calc!$C$5:$C$186<=6)*commission_calc!$K$5:$K$186)/SUMPRODUCT((commission_calc!$B$5:$B$186="R020")*(commission_calc!$C$5:$C$186>=4)*(commission_calc!$C$5:$C$186<=6)*commission_calc!$J$5:$J$186),0) -> 1.1333333 | O43: =IFERROR(SUMPRODUCT((commission_calc!$B$5:$B$186="R020")*(commission_calc!$C$5:$C$186>=7)*(commission_calc!$C$5:$C$186<=9)*commission_calc!$K$5:$K$186)/SUMPRODUCT((commission_calc!$B$5:$B$186="R020")*(commission_calc!$C$5:$C$186>=7)*(commission_calc!$C$5:$C$186<=9)*commission_calc!$J$5:$J$186),0) -> 0.89333333 | P43: =IFERROR(SUMPRODUCT((commission_calc!$B$5:$B$186="R020")*(commission_calc!$C$5:$C$186>=10)*(commission_calc!$C$5:$C$186<=12)*commission_calc!$K$5:$K$186)/SUMPRODUCT((commission_calc!$B$5:$B$186="R020")*(commission_calc!$C$5:$C$186>=10)*(commission_calc!$C$5:$C$186<=12)*commission_calc!$J$5:$J$186),0) -> 0.92 | Q43: =SUMPRODUCT((commission_calc!$B$5:$B$186="R020")*commission_calc!$U$5:$U$186) -> 38320 | S43: On track | U43: =SUMPRODUCT((commission_calc!$B$5:$B$186="R021")*commission_calc!$U$5:$U$186) -> 4186.5
C44: =VLOOKUP("R021",rep_roster!$A:$B,2,0) -> Jennifer Walsh | E44: CSM | F44: SMB | H44: =SUMPRODUCT((commission_calc!$B$5:$B$186="R021")*commission_calc!$J$5:$J$186) -> 60000 | J44: =SUMPRODUCT((commission_calc!$B$5:$B$186="R021")*commission_calc!$K$5:$K$186) -> 64000 | L44: =IF(H44>0,J44/H44,0) -> 1.0666667 | M44: =IFERROR(SUMPRODUCT((commission_calc!$B$5:$B$186="R021")*(commission_calc!$C$5:$C$186>=1)*(commission_calc!$C$5:$C$186<=3)*commission_calc!$K$5:$K$186)/SUMPRODUCT((commission_calc!$B$5:$B$186="R021")*(commission_calc!$C$5:$C$186>=1)*(commission_calc!$C$5:$C$186<=3)*commission_calc!$J$5:$J$186),0) -> 1.4 | N44: =IFERROR(SUMPRODUCT((commission_calc!$B$5:$B$186="R021")*(commission_calc!$C$5:$C$186>=4)*(commission_calc!$C$5:$C$186<=6)*commission_calc!$K$5:$K$186)/SUMPRODUCT((commission_calc!$B$5:$B$186="R021")*(commission_calc!$C$5:$C$186>=4)*(commission_calc!$C$5:$C$186<=6)*commission_calc!$J$5:$J$186),0) -> 1.1666667 | O44: =IFERROR(SUMPRODUCT((commission_calc!$B$5:$B$186="R021")*(commission_calc!$C$5:$C$186>=7)*(commission_calc!$C$5:$C$186<=9)*commission_calc!$K$5:$K$186)/SUMPRODUCT((commission_calc!$B$5:$B$186="R021")*(commission_calc!$C$5:$C$186>=7)*(commission_calc!$C$5:$C$186<=9)*commission_calc!$J$5:$J$186),0) -> 0.86666667 | P44: =IFERROR(SUMPRODUCT((commission_calc!$B$5:$B$186="R021")*(commission_calc!$C$5:$C$186>=10)*(commission_calc!$C$5:$C$186<=12)*commission_calc!$K$5:$K$186)/SUMPRODUCT((commission_calc!$B$5:$B$186="R021")*(commission_calc!$C$5:$C$186>=10)*(commission_calc!$C$5:$C$186<=12)*commission_calc!$J$5:$J$186),0) -> 0.83333333 | Q44: =SUMPRODUCT((commission_calc!$B$5:$B$186="R021")*commission_calc!$U$5:$U$186) -> 4186.5 | S44: On track
C47: SDR PERFORMANCE SUMMARY · HELD MEETINGS & VARIABLE COMP
C48: SDR Name | E48: Segment | G48: Status | H48: Annual Held | J48: Ann Quota | K48: Att% | L48: Annual Variable | N48: Avg Show Rate | P48: Accel? | Q48: Notes
C49: =VLOOKUP("R002",rep_roster!$A:$B,2,0) -> Marcus Williams | E49: Enterprise | G49: Active | H49: 96 | J49: 96 | K49: =IFERROR(H49/J49,0) -> 1 | L49: =SUMPRODUCT((commission_calc!$B$5:$B$186="R002")*commission_calc!$U$5:$U$186) -> 26700.3 | N49: 0.85 | P49: No | Q49: Strong show rate, consistent performer
C50: =VLOOKUP("R008",rep_roster!$A:$B,2,0) -> Kevin O'Brien | E50: Mid-Market | G50: Churned | H50: 80 | J50: 100 | K50: =IFERROR(H50/J50,0) -> 0.8 | L50: =SUMPRODUCT((commission_calc!$B$5:$B$186="R008")*commission_calc!$U$5:$U$186) -> 15948.5 | N50: 0.72 | P50: No | Q50: Churned August — partial year credit
C51: =VLOOKUP("R009",rep_roster!$A:$B,2,0) -> Aisha Johnson | E51: Mid-Market | G51: Active | H51: 119 | J51: 120 | K51: =IFERROR(H51/J51,0) -> 0.99166667 | L51: =SUMPRODUCT((commission_calc!$B$5:$B$186="R009")*commission_calc!$U$5:$U$186) -> 24841.25 | N51: 0.74 | P51: No | Q51: Slightly below annual quota, reliable
C52: =VLOOKUP("R010",rep_roster!$A:$B,2,0) -> Jessica Martinez | E52: Mid-Market | G52: Ramping | H52: 56 | J52: 60 | K52: =IFERROR(H52/J52,0) -> 0.93333333 | L52: =SUMPRODUCT((commission_calc!$B$5:$B$186="R010")*commission_calc!$U$5:$U$186) -> 11481.25 | N52: 0.71 | P52: No | Q52: Joined July — 6 active months, on ramp
C53: =VLOOKUP("R016",rep_roster!$A:$B,2,0) -> Nina Patel | E53: SMB | G53: Active | H53: 174 | J53: 192 | K53: =IFERROR(H53/J53,0) -> 0.90625 | L53: =SUMPRODUCT((commission_calc!$B$5:$B$186="R016")*commission_calc!$U$5:$U$186) -> 18636.6 | N53: 0.7 | P53: No | Q53: High volume, hit min show rate all year
C54: =VLOOKUP("R017",rep_roster!$A:$B,2,0) -> Derek Washington | E54: SMB | G54: Active | H54: 163 | J54: 192 | K54: =IFERROR(H54/J54,0) -> 0.84895833 | L54: =SUMPRODUCT((commission_calc!$B$5:$B$186="R017")*commission_calc!$U$5:$U$186) -> 16945.6 | N54: 0.69 | P54: No | Q54: Slightly below quota, show rate borderline
C57: ANALYST INSIGHTS · FY 2025 KEY FINDINGS
C58: Q1 BLOWOUT | H58: H2 SLOWDOWN | N58: COMP EFFICIENCY
C59: Org hit ~118% attainment in Q1. Multiple AEs triggered Tier 1 and Tier 2 accelerators. Olivia Brooks (Ent AE) led with 120%+ every quarter. | H59: August showed -15 to -20% drop across all segments. Q3+Q4 below quota driven by market softening and rep churn (3 departures mid-year). | N59: Top 20% concentration formula: SUMPRODUCT(LARGE(range,{1,2,3,4}))/SUM(range). High concentration signals quota calibration review for 2026 plan.
A61: Veltora Inc. · Revenue Operations · FY 2025 Sales Compensation Model · All figures derived from commission_calc, rep_roster, and plan_catalog sheets · Confidential — For Internal Use Only
